Workbook
Name ETkoProjCurr: 0
Name ETkoProjName: 0
Name TABLE: 'Private Paving'!$Q$56:$U$56
Name TABLE: 'ROW Paving'!$Q$56:$U$56
Name TABLE_2: 'Private Paving'!$Q$56:$U$56
Name TABLE_2: 'ROW Paving'!$Q$56:$U$56
Name TABLE_3: 'Private Paving'!$Q$56:$U$56
Name TABLE_3: 'ROW Paving'!$Q$56:$U$56

Sheet Summary
B2: JOB NAME: | C2: =Information!C2 -> 0 | O2: DATE | P2: REV
B3: JOB ADDRESS: | C3: =Information!C3 -> 0 | J3: ARCHITECTUAL: | K3: =Information!I13 -> 0 | O3: =Information!L13 -> 0
B4: CITY, STATE: | C4: =Information!C4 -> 0 | J4: STRUCTURAL: | K4: =Information!I14 -> 0 | O4: =Information!L14 -> 0 | S4: Entered by: | T4: =Information!C8 -> Chad McKinney
C5: NUMBER | E5: DATE | J5: CIVIL: | K5: =Information!I15 -> 0 | O5: =Information!L15 -> 0 | S5: =Information!H5 -> Approved by Chad:
B6: BID: | C6: =Information!I2 -> 0 | E6: =Information!J2 -> 0 | J6: LANDSCAPE: | K6: =Information!I16 -> 0 | O6: =Information!L16 -> 0 | S6: =Information!H6 -> Approved by Edward:
B7: REVISION: | C7: =Information!I3 -> 0 | E7: =Information!J3 -> 0 | M7: JOB COST SUMMARY
B8: Concrete Supplier: | D8: =Pricing!A2 -> Martin Marrieta | G8: FORMS | H8: Sand & Rock | I8: P.T. CABLES | J8: REBAR | K8: REBAR ACCES. | L8: CON CRETE | M8: SEALERS CURE | N8: OTHER SUBS | O8: SUB LABOR | P8: LABOR | Q8: SUPV | R8: EQUIP | S8: OUT OF TOWN | T8: COST BY UNIT | U8: TOTAL COST | V8: %
E9: SALE | F9: Sale by | V9: of
A10: DESCRIPTION | C10: QUANTITY | D10: UNT | E10: AMOUNT | F10: Unit | V10: sale | W10: CY
A12: MONO SLABS Garden Style | C12: ='Mono Slab on Grade Garden Style'!I83 -> 0 | D12: SF | E12: ='Mono Slab on Grade Garden Style'!E64 -> 0 | F12: =IF(C12=0,0,E12/$C$12) -> 0 | G12: ='Mono Slab on Grade Garden Style'!AO83+'Mono Slab on Grade Garden Style'!AO96+'Mono Slab on Grade Garden Style'!AO90++'Mono Slab on Grade Garden Style'!AO135 -> 0 | H12: ='Mono Slab on Grade Garden Style'!AO84+'Mono Slab on Grade Garden Style'!AO85 -> 0 | I12: ='Mono Slab on Grade Garden Style'!AO88 -> 0 | J12: ='Mono Slab on Grade Garden Style'!AO86 -> 0 | K12: ='Mono Slab on Grade Garden Style'!AO87 -> 0 | L12: ='Mono Slab on Grade Garden Style'!AO89 -> 0 | M12: ='Mono Slab on Grade Garden Style'!AO91 -> 0 | N12: ='Mono Slab on Grade Garden Style'!AO106+'Mono Slab on Grade Garden Style'!AO107+'Mono Slab on Grade Garden Style'!AO108+'Mono Slab on Grade Garden Style'!AO109+'Mono Slab on Grade Garden Style'!AO110+'Mono Slab on Grade Garden Style'!AO111 -> 0 | O12: ='Mono Slab on Grade Garden Style'!AO113+'Mono Slab on Grade Garden Style'!AO114+'Mono Slab on Grade Garden Style'!AO115+'Mono Slab on Grade Garden Style'!AO116+'Mono Slab on Grade Garden Style'!AO117+'Mono Slab on Grade Garden Style'!AO118+'Mono Slab on Grade Garden Style'!AO119+'Mono Slab on Grade Garden Style'!AO120+'Mono Slab on Grade Garden Style'!AO121+'Mono Slab on Grade Garden Style'!AO122+'Mono Slab on Grade Garden Style'!AO125+'Mono Slab on Grade Garden Style'!AO126+'Mono Slab on Grade Garden Style'!AO127+'Mono Slab on Grade Garden Style'!AO128+'Mono Slab on Grade Garden Style'!AO129+'Mono Slab on Grade Garden Style'!AO130+'Mono Slab on Grade Garden Style'!AO131+'Mono Slab on Grade Garden Style'!AO132 -> 0 | P12: ='Mono Slab on Grade Garden Style'!AO102 -> 0 | Q12: ='Mono Slab on Grade Garden Style'!AO100+'Mono Slab on Grade Garden Style'!AO101 -> 0 | R12: ='Mono Slab on Grade Garden Style'!AO133+'Mono Slab on Grade Garden Style'!AO134 -> 0 | S12: ='Mono Slab on Grade Garden Style'!AO103 -> 0 | U12: =IF(C12=0,0,SUM(G12:T12)) -> 0 | V12: =IF(C12=0,0,1-(U12/E12)) -> 0 | W12: =SUM('Mono Slab on Grade Garden Style'!L71:L73) -> 0 | X12: ='Mono Slab on Grade Garden Style'!AC64 -> 0 | Y12: =X12-U12 -> 0
G13: =IF(C12=0,0,G12/C12) -> 0 | H13: =IF($C12=0,0,H12/$C$12) -> 0 | I13: =IF($C12=0,0,I12/$C$12) -> 0 | J13: =IF($C12=0,0,J12/$C$12) -> 0 | K13: =IF($C12=0,0,K12/$C$12) -> 0 | L13: =IF($C12=0,0,L12/$C$12) -> 0 | M13: =IF($C12=0,0,M12/$C$12) -> 0 | N13: =IF($C12=0,0,N12/$C$12) -> 0 | O13: =IF($C12=0,0,O12/$C$12) -> 0 | ... S13: =IF($C12=0,0,S12/$C$12) -> 0 | T13: =SUM(G13:S13) -> 0 | X13: .
A14: MONO SLABS Wrap Bld 1 | C14: ='Mono Slab on Grade Building 1'!I83 -> 0 | D14: SF | E14: ='Mono Slab on Grade Building 1'!E64 -> 0 | F14: =IF(C14=0,0,E14/$C$14) -> 0 | G14: ='Mono Slab on Grade Building 1'!AO83+'Mono Slab on Grade Building 1'!AO96+'Mono Slab on Grade Building 1'!AO90++'Mono Slab on Grade Building 1'!AO135 -> 0 | H14: ='Mono Slab on Grade Building 1'!AO84+'Mono Slab on Grade Building 1'!AO85 -> 0 | I14: ='Mono Slab on Grade Building 1'!AO88 -> 0 | J14: ='Mono Slab on Grade Building 1'!AO86 -> 0 | K14: ='Mono Slab on Grade Building 1'!AO87 -> 0 | L14: ='Mono Slab on Grade Building 1'!AO89 -> 0 | M14: ='Mono Slab on Grade Building 1'!AO91 -> 0 | N14: ='Mono Slab on Grade Building 1'!AO106+'Mono Slab on Grade Building 1'!AO107+'Mono Slab on Grade Building 1'!AO108+'Mono Slab on Grade Building 1'!AO109+'Mono Slab on Grade Building 1'!AO110+'Mono Slab on Grade Building 1'!AO111 -> 0 | O14: ='Mono Slab on Grade Building 1'!AO113+'Mono Slab on Grade Building 1'!AO114+'Mono Slab on Grade Building 1'!AO115+'Mono Slab on Grade Building 1'!AO116+'Mono Slab on Grade Building 1'!AO117+'Mono Slab on Grade Building 1'!AO118+'Mono Slab on Grade Building 1'!AO119+'Mono Slab on Grade Building 1'!AO120+'Mono Slab on Grade Building 1'!AO121+'Mono Slab on Grade Building 1'!AO122+'Mono Slab on Grade Building 1'!AO125+'Mono Slab on Grade Building 1'!AO126+'Mono Slab on Grade Building 1'!AO127+'Mono Slab on Grade Building 1'!AO128+'Mono Slab on Grade Building 1'!AO129+'Mono Slab on Grade Building 1'!AO130+'Mono Slab on Grade Building 1'!AO131+'Mono Slab on Grade Building 1'!AO132 -> 0 | P14: ='Mono Slab on Grade Building 1'!AO102 -> 0 | Q14: ='Mono Slab on Grade Building 1'!AO100+'Mono Slab on Grade Building 1'!AO101 -> 0 | R14: ='Mono Slab on Grade Building 1'!AO133+'Mono Slab on Grade Building 1'!AO134 -> 0 | S14: ='Mono Slab on Grade Building 1'!AO103 -> 0 | U14: =IF(C14=0,0,SUM(G14:T14)) -> 0 | V14: =IF(C14=0,0,1-(U14/E14)) -> 0 | W14: =SUM('Mono Slab on Grade Building 1'!L71:L73) -> 0 | X14: ='Mono Slab on Grade Building 1'!AC64 -> 0 | Y14: =X14-U14 -> 0
C15: ='Mono Slab on Grade Building 1'!I84 -> 0 | G15: =IF(C14=0,0,G14/C14) -> 0 | H15: =IF($C14=0,0,H14/$C$14) -> 0 | I15: =IF($C14=0,0,I14/$C$14) -> 0 | J15: =IF($C14=0,0,J14/$C$14) -> 0 | K15: =IF($C14=0,0,K14/$C$14) -> 0 | L15: =IF($C14=0,0,L14/$C$14) -> 0 | M15: =IF($C14=0,0,M14/$C$14) -> 0 | N15: =IF($C14=0,0,N14/$C$14) -> 0 | O15: =IF($C14=0,0,O14/$C$14) -> 0 | ... S15: =IF($C14=0,0,S14/$C$14) -> 0 | T15: =SUM(G15:S15) -> 0 | X15: .
A16: MONO SLABS Wrap Bld 2 | C16: ='Mono Slab on Grade Building 2'!I83 -> 0 | D16: SF | E16: ='Mono Slab on Grade Building 2'!E64 -> 0 | F16: =IF(C16=0,0,E16/$C$12) -> 0 | G16: ='Mono Slab on Grade Building 2'!AO83+'Mono Slab on Grade Building 2'!AO96+'Mono Slab on Grade Building 2'!AO90++'Mono Slab on Grade Building 2'!AO135 -> 0 | H16: ='Mono Slab on Grade Building 2'!AO84+'Mono Slab on Grade Building 2'!AO85 -> 0 | I16: ='Mono Slab on Grade Building 2'!AO88 -> 0 | J16: ='Mono Slab on Grade Building 2'!AO86 -> 0 | K16: ='Mono Slab on Grade Building 2'!AO87 -> 0 | L16: ='Mono Slab on Grade Building 2'!AO89 -> 0 | M16: ='Mono Slab on Grade Building 2'!AO91 -> 0 | N16: ='Mono Slab on Grade Building 2'!AO106+'Mono Slab on Grade Building 2'!AO107+'Mono Slab on Grade Building 2'!AO108+'Mono Slab on Grade Building 2'!AO109+'Mono Slab on Grade Building 2'!AO110+'Mono Slab on Grade Building 2'!AO111 -> 0 | O16: ='Mono Slab on Grade Building 2'!AO113+'Mono Slab on Grade Building 2'!AO114+'Mono Slab on Grade Building 2'!AO115+'Mono Slab on Grade Building 2'!AO116+'Mono Slab on Grade Building 2'!AO117+'Mono Slab on Grade Building 2'!AO118+'Mono Slab on Grade Building 2'!AO119+'Mono Slab on Grade Building 2'!AO120+'Mono Slab on Grade Building 2'!AO121+'Mono Slab on Grade Building 2'!AO122+'Mono Slab on Grade Building 2'!AO125+'Mono Slab on Grade Building 2'!AO126+'Mono Slab on Grade Building 2'!AO127+'Mono Slab on Grade Building 2'!AO128+'Mono Slab on Grade Building 2'!AO129+'Mono Slab on Grade Building 2'!AO130+'Mono Slab on Grade Building 2'!AO131+'Mono Slab on Grade Building 2'!AO132 -> 0 | P16: ='Mono Slab on Grade Building 2'!AO102 -> 0 | Q16: ='Mono Slab on Grade Building 2'!AO100+'Mono Slab on Grade Building 2'!AO101 -> 0 | R16: ='Mono Slab on Grade Building 2'!AO133+'Mono Slab on Grade Building 2'!AO134 -> 0 | S16: ='Mono Slab on Grade Building 2'!AO103 -> 0 | U16: =IF(C16=0,0,SUM(G16:T16)) -> 0 | V16: =IF(C16=0,0,1-(U16/E16)) -> 0 | W16: =SUM('Mono Slab on Grade Building 2'!L71:L73) -> 0 | X16: ='Mono Slab on Grade Building 2'!AC64 -> 0 | Y16: =X16-U16 -> 0
G17: =IF(C16=0,0,G16/C16) -> 0 | H17: =IF($C16=0,0,H16/$C$12) -> 0 | I17: =IF($C16=0,0,I16/$C$12) -> 0 | J17: =IF($C16=0,0,J16/$C$12) -> 0 | K17: =IF($C16=0,0,K16/$C$12) -> 0 | L17: =IF($C16=0,0,L16/$C$12) -> 0 | M17: =IF($C16=0,0,M16/$C$12) -> 0 | N17: =IF($C16=0,0,N16/$C$12) -> 0 | O17: =IF($C16=0,0,O16/$C$12) -> 0 | ... S17: =IF($C16=0,0,S16/$C$12) -> 0 | T17: =SUM(G17:S17) -> 0 | X17: .
A19: PIERS | C19: =PIERS!E39 -> 0 | D19: EA | E19: =PIERS!E42 -> 0 | F19: =IF(C19=0,0,E19/C19) -> 0 | G19: =SUM(PIERS!W49:W70) -> 0 | J19: =PIERS!O52 -> 0 | K19: =SUM(PIERS!W71:W76) -> 0 | L19: =SUM(PIERS!O49:P51) -> 0 | M19: =SUM(PIERS!W77:W79) -> 0 | N19: =SUM(PIERS!O76:P81)-PIERS!O80+PIERS!O53 -> 0 | O19: =SUM(PIERS!O56:P60) -> 0 | P19: =SUM(PIERS!L56:M60) -> 0 | Q19: =SUM(PIERS!O63:P67) -> 0 | R19: =PIERS!AE125+PIERS!AE126 -> 0 | S19: =PIERS!O80 -> 0 | U19: =IF(C19=0,0,SUM(G19:T19)) -> 0 | V19: =IF(C19=0,0,1-(U19/E19)) -> 0 | W19: =PIERS!S39 -> 0 | X19: =PIERS!T42 -> 0 | Y19: =X19-U19 -> 0
A20: GRADE BEAMS | C20: ='Gd Beams'!I63 -> 0 | D20: SF | E20: ='Gd Beams'!E41 -> 0 | F20: =IF(C20=0,0,E20/C20) -> 0 | G20: ='Gd Beams'!AF67+'Gd Beams'!AF74+'Gd Beams'!AF117 -> 0 | H20: ='Gd Beams'!AF68+'Gd Beams'!AF69 -> 0 | I20: ='Gd Beams'!AF72 -> 0 | J20: ='Gd Beams'!AF70 -> 0 | K20: ='Gd Beams'!AF71 -> 0 | L20: ='Gd Beams'!AF73 -> 0 | M20: ='Gd Beams'!AF75 -> 0 | N20: ='Gd Beams'!AF88+'Gd Beams'!AF89+'Gd Beams'!AF90+'Gd Beams'!AF91+'Gd Beams'!AF92+'Gd Beams'!AF93 -> 0 | O20: =SUM('Gd Beams'!AF95:AF114) -> 0 | P20: ='Gd Beams'!AF84 -> 0 | Q20: ='Gd Beams'!AF82+'Gd Beams'!AF83 -> 0 | R20: ='Gd Beams'!AF115+'Gd Beams'!AF116 -> 0 | S20: ='Gd Beams'!AF85 -> 0 | T20: =IF(U20=0,0,SUM(G20:S20)/C20) -> 0 | U20: =IF(C20=0,0,SUM(G20:S20)) -> 0 | V20: =IF(C20=0,0,1-(U20/E20)) -> 0 | W20: ='Gd Beams'!L49+'Gd Beams'!L50+'Gd Beams'!L51 -> 0 | X20: ='Gd Beams'!U41 -> 0 | Y20: =X20-U20 -> 0
A21: GD Beams or Cont Footings | C21: ='Gd Beams or Cont Footings'!I63 -> 0 | D21: SF | E21: ='Gd Beams or Cont Footings'!E41 -> 0 | F21: =IF(C21=0,0,E21/C21) -> 0 | G21: ='Gd Beams or Cont Footings'!AF67+'Gd Beams or Cont Footings'!AF74+'Gd Beams or Cont Footings'!AF117 -> 0 | H21: ='Gd Beams or Cont Footings'!AF68+'Gd Beams or Cont Footings'!AF69 -> 0 | I21: ='Gd Beams or Cont Footings'!AF72 -> 0 | J21: ='Gd Beams or Cont Footings'!AF70 -> 0 | K21: ='Gd Beams or Cont Footings'!AF71 -> 0 | L21: ='Gd Beams or Cont Footings'!AF73 -> 0 | M21: ='Gd Beams or Cont Footings'!AF75 -> 0 | N21: ='Gd Beams or Cont Footings'!AF88+'Gd Beams or Cont Footings'!AF89+'Gd Beams or Cont Footings'!AF90+'Gd Beams or Cont Footings'!AF91+'Gd Beams or Cont Footings'!AF92+'Gd Beams or Cont Footings'!AF93 -> 0 | O21: =SUM('Gd Beams or Cont Footings'!AF95:AF114) -> 0 | P21: ='Gd Beams or Cont Footings'!AF84 -> 0 | Q21: ='Gd Beams or Cont Footings'!AF82+'Gd Beams or Cont Footings'!AF83 -> 0 | R21: ='Gd Beams or Cont Footings'!AF115+'Gd Beams or Cont Footings'!AF116 -> 0 | S21: ='Gd Beams or Cont Footings'!AF85 -> 0 | T21: =IF(U21=0,0,SUM(G21:S21)/C21) -> 0 | U21: =IF(C21=0,0,SUM(G21:S21)) -> 0 | V21: =IF(C21=0,0,1-(U21/E21)) -> 0 | W21: ='Gd Beams or Cont Footings'!L49+'Gd Beams or Cont Footings'!L50+'Gd Beams or Cont Footings'!L51 -> 0 | X21: ='Gd Beams or Cont Footings'!U41 -> 0 | Y21: =X21-U21 -> 0
A22: SLAB ON DECK | C22: ='SLAB ON DECK'!C27:D27 -> 0 | D22: SF | E22: ='SLAB ON DECK'!D31 -> 0 | F22: =IF(C22=0,0,E22/C22) -> 0 | G22: =SUM('SLAB ON DECK'!W38:W63)+'SLAB ON DECK'!N43 -> 0 | H22: ='SLAB ON DECK'!N45+'SLAB ON DECK'!N46 -> 0 | I22: ='SLAB ON DECK'!N44 -> 0 | J22: ='SLAB ON DECK'!N41+'SLAB ON DECK'!N42 -> 0 | K22: =SUM('SLAB ON DECK'!W64:W69) -> 0 | L22: =SUM('SLAB ON DECK'!N38:O40) -> 0 | M22: =SUM('SLAB ON DECK'!W70:W72) -> 0 | N22: =SUM('SLAB ON DECK'!N67:O73)+'SLAB ON DECK'!N75 -> 0 | O22: =SUM('SLAB ON DECK'!N50:O55) -> 0 | P22: =SUM('SLAB ON DECK'!K50:L55) -> 0 | Q22: =SUM('SLAB ON DECK'!N58:O60) -> 0 | R22: ='SLAB ON DECK'!AD115+'SLAB ON DECK'!AD116 -> 0 | S22: ='SLAB ON DECK'!N74 -> 0 | T22: =IF(C22=0,0,U22/C22) -> 0 | U22: =IF(C22=0,0,SUM(G22:S22)) -> 0 | V22: =IF(C22=0,0,1-(U22/E22)) -> 0 | W22: ='SLAB ON DECK'!K38+'SLAB ON DECK'!K39+'SLAB ON DECK'!K40 -> 0 | X22: ='SLAB ON DECK'!T31 -> 0 | Y22: =X22-U22 -> 0
G23: =IF($C$22=0,0,G22/$C$22) -> 0 | H23: =IF($C$22=0,0,H22/$C$22) -> 0 | I23: =IF($C$22=0,0,I22/$C$22) -> 0 | J23: =IF($C$22=0,0,J22/$C$22) -> 0 | K23: =IF($C$22=0,0,K22/$C$22) -> 0 | L23: =IF($C$22=0,0,L22/$C$22) -> 0 | M23: =IF($C$22=0,0,M22/$C$22) -> 0 | N23: =IF($C$22=0,0,N22/$C$22) -> 0 | ... S23: =IF($C$22=0,0,S22/$C$22) -> 0 | T23: =SUM(G23:S23) -> 0 | Y23: =X23-U23 -> 0
A24: CIP ELEV. SLAB | C24: ='CIP EL. DECK'!D41 -> 0 | D24: SF | E24: ='CIP EL. DECK'!E52 -> 0 | F24: =IF(C24=0,0,E24/C24) -> 0 | G24: ='CIP EL. DECK'!AF70+'CIP EL. DECK'!AF121 -> 0 | H24: ='CIP EL. DECK'!AF71 -> 0 | I24: ='CIP EL. DECK'!AF75 -> 0 | J24: ='CIP EL. DECK'!AF73 -> 0 | K24: ='CIP EL. DECK'!AF74 -> 0 | L24: ='CIP EL. DECK'!AF76 -> 0 | M24: ='CIP EL. DECK'!AF78 -> 0 | N24: ='CIP EL. DECK'!AF92+'CIP EL. DECK'!AF96+'CIP EL. DECK'!O68+'CIP EL. DECK'!O69 -> 0 | O24: ='CIP EL. DECK'!AF101+'CIP EL. DECK'!AF102+'CIP EL. DECK'!AF103+'CIP EL. DECK'!AF104+'CIP EL. DECK'!AF105+'CIP EL. DECK'!AF118+'CIP EL. DECK'!AF110 -> 0 | P24: ='CIP EL. DECK'!AF88 -> 0 | Q24: ='CIP EL. DECK'!AF86+'CIP EL. DECK'!AF87 -> 0 | R24: ='CIP EL. DECK'!AF119+'CIP EL. DECK'!AF120 -> 0 | S24: ='CIP EL. DECK'!AF89 -> 0 | T24: =IF(C24=0,0,U24/C24) -> 0 | U24: =SUM(G24:S24) -> 0 | V24: =IF(C24=0,0,1-(U24/E24)) -> 0 | W24: ='CIP EL. DECK'!L60+'CIP EL. DECK'!L61+'CIP EL. DECK'!L62 -> 0 | X24: ='CIP EL. DECK'!U52 -> 0 | Y24: =X24-U24 -> 0
A26: SLAB ON GRADE | C26: ='SLAB ON GRADE'!H50 -> 0 | D26: SF | E26: ='SLAB ON GRADE'!D31 -> 0 | F26: =IF(C26=0,0,E26/C26) -> 0 | G26: =SUM('SLAB ON GRADE'!W38:W63)+'SLAB ON GRADE'!N43 -> 0 | H26: ='SLAB ON GRADE'!N45+'SLAB ON GRADE'!N46 -> 0 | I26: ='SLAB ON GRADE'!N44 -> 0 | J26: ='SLAB ON GRADE'!N41+'SLAB ON GRADE'!N42 -> 0 | K26: =SUM('SLAB ON GRADE'!W64:W69) -> 0 | L26: =SUM('SLAB ON GRADE'!N38:O40) -> 0 | M26: =SUM('SLAB ON GRADE'!W70:W72) -> 0 | N26: =SUM('SLAB ON GRADE'!N67:O73)+'SLAB ON GRADE'!N75 -> 0 | O26: =SUM('SLAB ON GRADE'!N50:O55) -> 0 | P26: =SUM('SLAB ON GRADE'!K50:L55) -> 0 | Q26: =SUM('SLAB ON GRADE'!N58:O60) -> 0 | R26: ='SLAB ON GRADE'!AD114+'SLAB ON GRADE'!AD115 -> 0 | S26: ='SLAB ON GRADE'!N74 -> 0 | T26: =IF(C26=0,0,U26/C26) -> 0 | U26: =IF(C26=0,0,SUM(G26:S26)) -> 0 | V26: =IF(C26=0,0,1-(U26/E26)) -> 0 | W26: ='SLAB ON GRADE'!K38+'SLAB ON GRADE'!K39+'SLAB ON GRADE'!K40 -> 0 | X26: ='SLAB ON GRADE'!T31 -> 0 | Y26: =X26-U26 -> 0
G27: =IF($C$26=0,0,G26/$C$26) -> 0 | H27: =IF($C$26=0,0,H26/$C$26) -> 0 | I27: =IF($C$26=0,0,I26/$C$26) -> 0 | J27: =IF($C$26=0,0,J26/$C$26) -> 0 | K27: =IF($C$26=0,0,K26/$C$26) -> 0 | L27: =IF($C$26=0,0,L26/$C$26) -> 0 | M27: =IF($C$26=0,0,M26/$C$26) -> 0 | N27: =IF($C$26=0,0,N26/$C$26) -> 0 | ... R27: =IF($C$26=0,0,R26/$C$26) -> 0 | S27: =IF($C$22=0,0,S26/$C$22) -> 0 | T27: =SUM(G27:S27) -> 0 | Y27: =X27-U27 -> 0
A28: COLUMNS | C28: =COLUMNS!E37 -> 0 | D28: EA | E28: =COLUMNS!E41 -> 0 | F28: =IF(C28=0,0,E28/C28) -> 0 | G28: =COLUMNS!AF67+COLUMNS!AF117 -> 0 | I28: =COLUMNS!AF72 -> 0 | J28: =COLUMNS!AF70 -> 0 | K28: =COLUMNS!AF71 -> 0 | L28: =COLUMNS!AF73 -> 0 | M28: =COLUMNS!AF75 -> 0 | N28: =COLUMNS!AF88+COLUMNS!AF79 -> 0 | O28: =COLUMNS!AF97+COLUMNS!AF98+COLUMNS!AF99+COLUMNS!AF100+COLUMNS!AF101+COLUMNS!O68+COLUMNS!O69+COLUMNS!AF110 -> 0 | P28: =COLUMNS!AF84 -> 0 | Q28: =COLUMNS!AF82+COLUMNS!AF83 -> 0 | R28: =COLUMNS!AF115+COLUMNS!AF116 -> 0 | S28: =COLUMNS!AF85 -> 0 | T28: =IF(C28=0,0,SUM(G28:S28)/C28) -> 0 | U28: =SUM(G28:S28) -> 0 | V28: =IF(C28=0,0,1-(U28/E28)) -> 0 | W28: =SUM(COLUMNS!V11:V36) -> 0 | X28: =COLUMNS!U41 -> 0 | Y28: =X28-U28 -> 0
A29: =Miscellaneous!A31 -> PANEL AND ANCHOR | C29: =Miscellaneous!F31 -> 0 | D29: EA | E29: =Miscellaneous!I31 -> 0 | F29: =IF(C29=0,0,E29/C29) -> 0 | G29: =Miscellaneous!O31 -> 0 | J29: =Miscellaneous!Q31 -> 0 | L29: =Miscellaneous!P31 -> 0 | O29: =Miscellaneous!AD31 -> 0 | Q29: =Miscellaneous!S31 -> 0 | R29: =Miscellaneous!T31 -> 0 | U29: =SUM(G29:S29) -> 0 | V29: =IF(C29=0,0,1-(U29/E29)) -> 0 | W29: =Miscellaneous!M31 -> 0 | Y29: =X29-U29 -> 0
W30: 0 | Y30: =X30-U30 -> 0
A31: =Miscellaneous!A16 -> ELEVATOR PITS | C31: =Miscellaneous!F16 -> 0 | D31: EA | E31: =Miscellaneous!I16 -> 0 | F31: =IF(C31>0,E31/C31,0) -> 0 | G31: =IF(C31>0,Miscellaneous!O16,0) -> 0 | J31: =IF(C31>0,Miscellaneous!Q16,0) -> 0 | L31: =IF(C31>0,Miscellaneous!P16,0) -> 0 | O31: =IF(C31>0,Miscellaneous!R16,0) -> 0 | Q31: =IF(C31>0,Miscellaneous!S16,0) -> 0 | R31: =IF(C31>0,Miscellaneous!T16,0) -> 0 | T31: =IF(C31=0,0,U31/C31) -> 0 | U31: =IF(C31=0,0,SUM(G31:S31)) -> 0 | V31: =IF(C31=0,0,1-(U31/E31)) -> 0 | W31: =Miscellaneous!M16 -> 0
A32: =Miscellaneous!A17 -> DOCK LEVELER PITS | C32: =Miscellaneous!F17 -> 0 | D32: EA | E32: =Miscellaneous!I17 -> 0 | F32: =IF(C32=0,0,E32/C32) -> 0 | G32: =Miscellaneous!O17 -> 0 | J32: =Miscellaneous!Q17 -> 0 | L32: =Miscellaneous!P17 -> 0 | O32: =Miscellaneous!AD17 -> 0 | Q32: =Miscellaneous!S17 -> 0 | R32: =IF(C32>0,Miscellaneous!T17,0) -> 0 | U32: =IF(C32=0,0,SUM(G32:S32)) -> 0
E33: 0
A34: TILT PANELS | C34: =PANELS!I148 -> 0 | D34: SF | E34: =PANELS!E124 -> 0 | F34: =IF(C34=0,0,E34/C34) -> 0 | G34: =PANELS!AH124+PANELS!AH131++PANELS!AH174 -> 0 | H34: =PANELS!AH125+PANELS!AH126 -> 0 | J34: =PANELS!AH127 -> 0 | K34: =PANELS!AH128 -> 0 | L34: =PANELS!AH130 -> 0 | M34: =PANELS!AH132 -> 0 | N34: =PANELS!AH145+PANELS!AH147+PANELS!AH148+PANELS!AH149+PANELS!AH150+PANELS!O168 -> 0 | O34: =PANELS!AH154+PANELS!AH155+PANELS!AH156+PANELS!AH157+PANELS!AH158+PANELS!AH159+PANELS!AH171+PANELS!AH165 -> 0 | P34: =PANELS!AH141 -> 0 | Q34: =PANELS!AH139+PANELS!AH140 -> 0 | R34: =PANELS!AH172+PANELS!AH173 -> 0 | S34: =PANELS!AH142 -> 0 | U34: =SUM(G34:S34) -> 0 | V34: =IF(C34=0,0,1-(U34/E34)) -> 0 | W34: =PANELS!L134+PANELS!L135+PANELS!L136 -> 0
A36: SITEWORK
A37: Private Paving | C37: ='Private Paving'!D28 -> 0 | D37: SF | E37: ='Private Paving'!E32 -> 0 | F37: =IF(E37=0,0,E37/C37) -> 0 | G37: =SUM('Private Paving'!W40:W65) -> 0 | H37: ='Private Paving'!O46+'Private Paving'!O47 -> 0 | J37: ='Private Paving'!O43+'Private Paving'!O44+'Private Paving'!W78 -> 0 | K37: =SUM('Private Paving'!W66:W71) -> 0 | L37: =SUM('Private Paving'!O40:P42) -> 0 | M37: =SUM('Private Paving'!W72:W75) -> 0 | N37: =SUM('Private Paving'!O70:P78)-'Private Paving'!O77 -> 0 | O37: =SUM('Private Paving'!O50:P54) -> 0 | P37: =SUM('Private Paving'!L50:M54) -> 0 | Q37: =SUM('Private Paving'!O57:P61) -> 0 | R37: ='Private Paving'!AE116+'Private Paving'!AE117 -> 0 | S37: ='Private Paving'!O77 -> 0 | U37: =IF(C37=0,0,SUM(G37:S37)) -> 0 | V37: =IF(C37=0,0,1-(U37/E37)) -> 0 | W37: =SUM('Private Paving'!L40:M42) -> 0 | X37: ='Private Paving'!U32 -> 0 | Y37: =X37-U37 -> 0
G38: =IF($C37=0,0,G37/$C37) -> 0 | H38: =IF($C37=0,0,H37/$C37) -> 0 | I38: =IF($C37=0,0,I37/$C37) -> 0 | J38: =IF($C37=0,0,J37/$C37) -> 0 | K38: =IF($C37=0,0,K37/$C37) -> 0 | L38: =IF($C37=0,0,L37/$C37) -> 0 | M38: =IF($C37=0,0,M37/$C37) -> 0 | N38: =IF($C37=0,0,N37/$C37) -> 0 | ... S38: =IF($C37=0,0,S37/$C37) -> 0 | T38: =SUM(G38:S38) -> 0 | Y38: =X38-U38 -> 0
A39: ROW Paving | C39: ='ROW Paving'!D28 -> 0 | D39: SF | E39: ='ROW Paving'!E32 -> 0 | F39: =IF(E39=0,0,E39/C39) -> 0 | G39: =SUM('ROW Paving'!W40:W65) -> 0 | H39: ='ROW Paving'!O46+'ROW Paving'!O47 -> 0 | J39: ='ROW Paving'!O43+'ROW Paving'!O44+'ROW Paving'!W78 -> 0 | K39: =SUM('ROW Paving'!W66:W71) -> 0 | L39: =SUM('ROW Paving'!O40:P42) -> 0 | M39: =SUM('ROW Paving'!W72:W75) -> 0 | N39: =SUM('ROW Paving'!O70:P78)-'ROW Paving'!O77 -> 0 | O39: =SUM('ROW Paving'!O50:P54) -> 0 | P39: =SUM('ROW Paving'!L50:M54) -> 0 | Q39: =SUM('ROW Paving'!O57:P61) -> 0 | R39: ='ROW Paving'!AE116+'ROW Paving'!AE117 -> 0 | S39: ='ROW Paving'!O77 -> 0 | U39: =IF(C39=0,0,SUM(G39:S39)) -> 0 | V39: =IF(C39=0,0,1-(U39/E39)) -> 0 | W39: =SUM('ROW Paving'!L42:M44) -> 0 | X39: ='ROW Paving'!U32 -> 0 | Y39: =X39-U39 -> 0
G40: =IF($C39=0,0,G39/$C39) -> 0 | H40: =IF($C39=0,0,H39/$C39) -> 0 | I40: =IF($C39=0,0,I39/$C39) -> 0 | J40: =IF($C39=0,0,J39/$C39) -> 0 | K40: =IF($C39=0,0,K39/$C39) -> 0 | L40: =IF($C39=0,0,L39/$C39) -> 0 | M40: =IF($C39=0,0,M39/$C39) -> 0 | N40: =IF($C39=0,0,N39/$C39) -> 0 | ... S40: =IF($C39=0,0,S39/$C39) -> 0 | T40: =SUM(G40:S40) -> 0 | Y40: =X40-U40 -> 0
Y41: =X41-U41 -> 0
A42: SIDEWALKS | C42: =SIDEWALKS!C27 -> 0 | D42: SF | E42: =SIDEWALKS!D31 -> 0 | F42: =IF(E42=0,0,E42/C42) -> 0 | G42: =SIDEWALKS!AD65+SIDEWALKS!AD117 -> 0 | H42: =SIDEWALKS!AD66+SIDEWALKS!AD67 -> 0 | J42: =SIDEWALKS!AD68 -> 0 | K42: =SIDEWALKS!AD69 -> 0 | L42: =SIDEWALKS!AD71 -> 0 | M42: =SIDEWALKS!AD73 -> 0 | N42: =SIDEWALKS!AG88+SIDEWALKS!AG92+SIDEWALKS!AG91+SIDEWALKS!BH28+SIDEWALKS!BG28+SIDEWALKS!BF28 -> 0 | O42: =SIDEWALKS!AG97+SIDEWALKS!AG99+SIDEWALKS!AG100+SIDEWALKS!AG101+SIDEWALKS!Q55 -> 0 | P42: =SIDEWALKS!AD84 -> 0 | Q42: =SIDEWALKS!AD82+SIDEWALKS!AD83 -> 0 | R42: =SIDEWALKS!AD115+SIDEWALKS!AD116 -> 0 | S42: =SIDEWALKS!AD85 -> 0 | T42: =IF(C42=0,0,SUM(G42:S42)/C42) -> 0 | U42: =SUM(G42:S42) -> 0 | V42: =IF(C42=0,0,1-(U42/E42)) -> 0 | W42: =SUM(SIDEWALKS!N38:O40) -> 0 | X42: =SIDEWALKS!W31 -> 0 | Y42: =X42-U42 -> 0
A43: WALLS /FOOTING | C43: ='Site Walls'!I71 -> 0 | D43: FF | E43: ='Site Walls'!E47 -> 0 | F43: ='Site Walls'!C48 -> 0 | G43: ='Site Walls'!AF73+'Site Walls'!AF80+'Site Walls'!AF125 -> 0 | H43: ='Site Walls'!AF74+'Site Walls'!AF75 -> 0 | I43: ='Site Walls'!AF78 -> 0 | J43: ='Site Walls'!AF76 -> 0 | K43: ='Site Walls'!AF77 -> 0 | L43: ='Site Walls'!AF79 -> 0 | M43: ='Site Walls'!AF83 -> 0 | N43: ='Site Walls'!AF96+'Site Walls'!AF99+'Site Walls'!AF100+'Site Walls'!O68 -> 0 | O43: =SUM('Site Walls'!AF103:AF122) -> 0 | P43: ='Site Walls'!AF92 -> 0 | Q43: ='Site Walls'!AF90+'Site Walls'!AF91 -> 0 | R43: ='Site Walls'!AF123+'Site Walls'!AF124 -> 0 | S43: ='Site Walls'!AF93 -> 0 | U43: =SUM(G43:S43) -> 0 | V43: =IF(C43=0,0,1-(U43/E43)) -> 0 | W43: ='Site Walls'!L57+'Site Walls'!L58+'Site Walls'!L59 -> 0 | X43: ='Site Walls'!U47 -> 0 | Y43: =X43-U43 -> 0
A44: FOOTINGS | C44: ='Site Walls'!I70 -> 0 | D44: SF | F44: ='Site Walls'!G48 -> 0 | U44: =SUM(G44:S44) -> 0
A45: Garage Walls | C45: ='Garage Walls'!I71 -> 0 | D45: FF | E45: ='Garage Walls'!E49 -> 0 | F45: ='Garage Walls'!C50 -> 0 | G45: ='Garage Walls'!AF73+'Garage Walls'!AF80+'Garage Walls'!AF125 -> 0 | H45: ='Garage Walls'!AF74+'Garage Walls'!AF75 -> 0 | I45: ='Garage Walls'!AF78 -> 0 | J45: ='Garage Walls'!AF76 -> 0 | K45: ='Garage Walls'!AF77 -> 0 | L45: ='Garage Walls'!AF79 -> 0 | M45: ='Garage Walls'!AF83 -> 0 | N45: ='Garage Walls'!AF96+'Garage Walls'!AF99+'Garage Walls'!AF100+'Garage Walls'!O68 -> 0 | O45: =SUM('Garage Walls'!AF103:AF122) -> 0 | P45: ='Garage Walls'!AF92 -> 0 | Q45: ='Garage Walls'!AF90+'Garage Walls'!AF91 -> 0 | R45: ='Garage Walls'!AF123+'Garage Walls'!AF124 -> 0 | S45: ='Garage Walls'!AF93 -> 0 | U45: =SUM(G45:S45) -> 0 | V45: =IF(C45=0,0,1-(U45/E45)) -> 0 | W45: ='Garage Walls'!L57+'Garage Walls'!L58+'Garage Walls'!L59 -> 0 | X45: ='Garage Walls'!U47 -> 0 | Y45: =X45-U45 -> 0
A46: FOOTINGS | C46: ='Garage Walls'!I70 -> 0 | D46: SF | F46: ='Garage Walls'!G48 -> 0 | U46: =SUM(G46:S46) -> 0
A47: Footings | C47: =Footings!I64+Footings!I65 -> 0 | D47: SF | E47: =Footings!E41 -> 0 | F47: =Footings!C42 -> 0 | G47: =Footings!AF67+Footings!AF74+Footings!AF12 -> 0 | H47: =Footings!AF68+Footings!AF69 -> 0 | I47: =Footings!AF72 -> 0 | J47: =Footings!AF70 -> 0 | K47: =Footings!AF71 -> 0 | L47: =Footings!AF73 -> 0 | M47: =Footings!AF77 -> 0 | N47: =Footings!AF90+Footings!AF93+Footings!AF94+Footings!O62 -> 0 | O47: =SUM(Footings!AF97:AF116) -> 0 | P47: =Footings!AF86 -> 0 | Q47: =Footings!AF84+Footings!AF85 -> 0 | R47: =Footings!AF117+Footings!AF118 -> 0 | S47: =Footings!AF87 -> 0 | U47: =SUM(G47:S47) -> 0 | V47: =IF(C47=0,0,1-(U47/E47)) -> 0 | W47: =Footings!L51+Footings!L52+Footings!L53 -> 0 | X47: =Footings!U41 -> 0 | Y47: =X47-U47 -> 0
A48: Garage Footings | C48: ='Garage Footings'!I65+'Garage Footings'!I64 -> 0 | D48: SF | E48: ='Garage Footings'!E41 -> 0 | F48: ='Garage Footings'!C42 -> 0 | G48: ='Garage Footings'!AF67+'Garage Footings'!AF74+'Garage Footings'!AF12 -> 0 | H48: ='Garage Footings'!AF68+'Garage Footings'!AF69 -> 0 | I48: ='Garage Footings'!AF72 -> 0 | J48: ='Garage Footings'!AF70 -> 0 | K48: ='Garage Footings'!AF71 -> 0 | L48: ='Garage Footings'!AF73 -> 0 | M48: ='Garage Footings'!AF77 -> 0 | N48: ='Garage Footings'!AF90+'Garage Footings'!AF93+'Garage Footings'!AF94+'Garage Footings'!O62 -> 0 | O48: =SUM('Garage Footings'!AF97:AF116) -> 0 | P48: ='Garage Footings'!AF86 -> 0 | Q48: ='Garage Footings'!AF84+'Garage Footings'!AF85 -> 0 | R48: ='Garage Footings'!AF117+'Garage Footings'!AF118 -> 0 | S48: ='Garage Footings'!AF87 -> 0 | U48: =SUM(G48:S48) -> 0 | V48: =IF(C48=0,0,1-(U48/E48)) -> 0 | W48: ='Garage Footings'!L51+'Garage Footings'!L52+'Garage Footings'!L53 -> 0 | X48: ='Garage Footings'!U41 -> 0 | Y48: =X48-U48 -> 0
A49: =Miscellaneous!A12 -> Light Bollard Footings | C49: =Miscellaneous!F12 -> 0 | D49: EA | E49: =Miscellaneous!I12 -> 0 | F49: =IF(C49>0,E49/C49,0) -> 0 | L49: =Miscellaneous!P12 -> 0 | O49: =Miscellaneous!AD12 -> 0 | P49: =Miscellaneous!AE12 -> 0 | Q49: =Miscellaneous!S12 -> 0 | R49: =Miscellaneous!T12 -> 0 | U49: =SUM(G49:S49) -> 0 | V49: =IF(C49=0,0,1-(U49/E49)) -> 0 | W49: =Miscellaneous!M12 -> 0
A50: MISCELLANIOUS | C50: =IF(Miscellaneous!F13+Miscellaneous!F18+Miscellaneous!F19+Miscellaneous!F21+Miscellaneous!F26+Miscellaneous!F27>0,1,0) -> 0 | D50: EA | E50: =Miscellaneous!I13+Miscellaneous!I18+Miscellaneous!I19+Miscellaneous!I21+Miscellaneous!I26+Miscellaneous!I27+Miscellaneous!I28+Miscellaneous!I29+Miscellaneous!I32+Miscellaneous!I33+Miscellaneous!I34+Miscellaneous!I35+Miscellaneous!I36+Miscellaneous!I37 -> 0 | G50: =Miscellaneous!O13+Miscellaneous!O18+Miscellaneous!O19+Miscellaneous!O21+Miscellaneous!O26+Miscellaneous!O27+Miscellaneous!O28+Miscellaneous!O29+Miscellaneous!O32+Miscellaneous!O33+Miscellaneous!O34+Miscellaneous!O35+Miscellaneous!O36+Miscellaneous!O37 -> 0 | H50: =Miscellaneous!N27 -> 0 | J50: =Miscellaneous!Q13+Miscellaneous!Q18+Miscellaneous!Q19+Miscellaneous!Q21+Miscellaneous!Q26+Miscellaneous!Q27+Miscellaneous!Q28+Miscellaneous!Q29+Miscellaneous!Q32+Miscellaneous!Q33+Miscellaneous!Q34+Miscellaneous!Q35+Miscellaneous!Q36+Miscellaneous!Q37 -> 0 | L50: =Miscellaneous!P13+Miscellaneous!P18+Miscellaneous!P19+Miscellaneous!P21+Miscellaneous!P26+Miscellaneous!P27+Miscellaneous!P28+Miscellaneous!P29+Miscellaneous!P32+Miscellaneous!P33+Miscellaneous!P34+Miscellaneous!P35+Miscellaneous!P36+Miscellaneous!P37 -> 0 | O50: =SUM(Miscellaneous!AD10:AD36)-Miscellaneous!AD31-Miscellaneous!AD25-Miscellaneous!AD24-Miscellaneous!AD17-Miscellaneous!AD16-Miscellaneous!AD12-Miscellaneous!AD10 -> 0 | P50: =SUM(Miscellaneous!AE10:AE36)-Miscellaneous!AE31-Miscellaneous!AE25-Miscellaneous!AE24-Miscellaneous!AE17-Miscellaneous!AE16-Miscellaneous!AE10-Miscellaneous!AE12 -> 0 | Q50: =Miscellaneous!S13+Miscellaneous!S18+Miscellaneous!S19+Miscellaneous!S21+Miscellaneous!S26+Miscellaneous!S27+Miscellaneous!S28+Miscellaneous!S29+Miscellaneous!S32+Miscellaneous!S33+Miscellaneous!S34+Miscellaneous!S35+Miscellaneous!S36+Miscellaneous!S37 -> 0 | R50: =Miscellaneous!T13+Miscellaneous!T18+Miscellaneous!T19+Miscellaneous!T21+Miscellaneous!T26+Miscellaneous!T27+Miscellaneous!T28+Miscellaneous!T29+Miscellaneous!T32+Miscellaneous!T33+Miscellaneous!T34+Miscellaneous!T35+Miscellaneous!T36+Miscellaneous!T37 -> 0 | U50: =SUM(G50:S50) -> 0 | V50: =IF(C50=0,0,1-(U50/E50)) -> 0 | W50: =Miscellaneous!M13+Miscellaneous!M18+Miscellaneous!M19+Miscellaneous!M21+Miscellaneous!M26+Miscellaneous!M27+Miscellaneous!M32 -> 0
A51: =Miscellaneous!A10 -> LIGHT POLE BASES | C51: =Miscellaneous!F10 -> 0 | D51: EA | E51: =Miscellaneous!I10 -> 0 | F51: =IF(C51>0,E51/C51,0) -> 0 | G51: =Miscellaneous!O10 -> 0 | J51: =Miscellaneous!Q10 -> 0 | L51: =Miscellaneous!P10 -> 0 | O51: =Miscellaneous!AD10 -> 0 | P51: =Miscellaneous!AE10 -> 0 | Q51: =Miscellaneous!S10 -> 0 | R51: =Miscellaneous!T10 -> 0 | U51: =SUM(G51:S51) -> 0 | V51: =IF(C51=0,0,1-(U51/E51)) -> 0 | W51: =Miscellaneous!M10 -> 0
A52: =Miscellaneous!A24 -> HOUSE KEEPING PADS | C52: =Miscellaneous!F24 -> 0 | D52: EA | E52: =Miscellaneous!I24 -> 0 | F52: =IF(C52>0,E52/C52,0) -> 0 | G52: =Miscellaneous!O24 -> 0 | H52: =Miscellaneous!N24 -> 0 | J52: =Miscellaneous!Q24 -> 0 | L52: =Miscellaneous!P24 -> 0 | O52: =AD29 -> 0 | P52: =Miscellaneous!AE24 -> 0 | Q52: =Miscellaneous!S24 -> 0 | R52: =Miscellaneous!T24 -> 0 | U52: =SUM(G52:S52) -> 0 | V52: =IF(C52=0,0,1-(U52/E52)) -> 0 | W52: =Miscellaneous!M24 -> 0
A53: =Miscellaneous!A25 -> BLOCK OUTS | C53: =Miscellaneous!F25 -> 0 | D53: EA | E53: =Miscellaneous!I25 -> 0 | F53: =IF(C53>0,E53/C53,0) -> 0 | G53: =Miscellaneous!O25 -> 0 | J53: =Miscellaneous!Q25 -> 0 | L53: =Miscellaneous!P25 -> 0 | O53: =AD30 -> 0 | P53: =Miscellaneous!AE25 -> 0 | Q53: =Miscellaneous!S25 -> 0 | R53: =Miscellaneous!T25 -> 0 | U53: =SUM(G53:S53) -> 0 | V53: =IF(C53=0,0,1-(U53/E53)) -> 0 | W53: =Miscellaneous!M25 -> 0
J54: TONS | L54: CU YDS | Q54: WKS
J55: =(PIERS!L52+'Gd Beams'!L52+'SLAB ON DECK'!K41+COLUMNS!L53+'CIP EL. DECK'!L63+'Site Walls'!L60+SIDEWALKS!N41+'Private Paving'!L43+Miscellaneous!N38+PANELS!L137+'SLAB ON GRADE'!K41+'Mono Slab on Grade Building 1'!L74)/2000 -> 0 | L55: =SUM(W56) -> 0 | Q55: =H96/100/5 -> 0 | U55: =O106-H79 -> 0 | W55: 0
B56: TOTALS | E56: =SUM(E12:E55) -> 0 | G56: =SUM(G12:G53)-G13-G23-G38-G15-G17 -> 0 | H56: =SUM(H12:H53)-H13-H23-H38-H15-H17-H27 -> 0 | I56: =SUM(I12:I53)-I13-I23-I38-I15-I17-I27 -> 0 | J56: =SUM(J12:J53)-J13-J23-J38-J15-J17-J27 -> 0 | K56: =SUM(K12:K53)-K13-K23-K38-K15-K17-K27 -> 0 | L56: =SUM(L12:L53)-L13-L23-L38-L15-L17-L27 -> 0 | M56: =SUM(M12:M53)-M13-M23-M38-M15-M17-M27 -> 0 | N56: =SUM(N12:N53)-N13-N23-N38-N15-N17-N27 -> 0 | O56: =SUM(O12:O53)-O13-O23-O38-O15-O17-O27 -> 0 | ... S56: =SUM(S12:S53)-S13-S23-S38-S15-S17-S27 -> 0 | U56: =SUM(U12:U54) -> 0 | W56: =SUM(W12:W55) -> 0 | X56: Total CY
C57: TOTAL BOND | D57: =U59*(1+P64+P63) -> 0 | G57: =IF($E$56=0,0,G56/$E56) -> 0 | H57: =IF($E$56=0,0,H56/$E56) -> 0 | I57: =IF($E$56=0,0,I56/$E56) -> 0 | J57: =IF($E$56=0,0,J56/$E56) -> 0 | K57: =IF($E$56=0,0,K56/$E56) -> 0 | L57: =IF($E$56=0,0,L56/$E56) -> 0 | M57: =IF($E$56=0,0,M56/$E56) -> 0 | N57: =IF($E$56=0,0,N56/$E56) -> 0 | ... S57: =IF($E$56=0,0,S56/$E56) -> 0 | U57: =SUM(G57:T57) -> 0 | W57: =IF(W56=0,0,E56/W56) -> 0 | X57: Per CY
A58: CONTRACT PRICE | D58: =E56+D57 -> 0 | U58: =U56-U55 -> 0
O59: BOND ? | P59: N | S59: BONDING PRICE | U59: =IF(P59="y",IF(E56<100000,E56*0.025,2500)+IF(E56>100000,(-100000+E56)*0.015,0)+IF(E56>500000,(-500000+E56)*0.01,0),0) -> 0
S60: TOTAL COST | U60: =U59+U56 -> 0
U61: =O106 -> 0
I62: TOTAL MATERIAL | L62: =SUM(G56:M56) -> 0 | M62: =L62/D58 -> #DIV/0! | O62: TYPE | P62: % | Q62: AMOUNT
I63: TOTAL LABOR | L63: =P56+Q56 -> 0 | M63: =L63/D58 -> #DIV/0! | O63: Margin | P63: 0.18 | Q63: =L66/(P63+P64)*P63 -> 0
I64: TOTAL SUB LABOR | L64: =O56 -> 0 | M64: =L64/D58 -> #DIV/0! | O64: Contengency | P64: 0 | Q64: =L66/(P63+P64)*P64 -> 0
I65: TOTAL OTHER | L65: =N56+R56+S56+U59 -> 0 | M65: =L65/D58 -> #DIV/0! | O65: Tax Exempt | P65: n | Q65: Tax Rate | R65: 0.0825
I66: ESTIMATED PROFIT | L66: =D58-U60 -> 0 | M66: =1-SUM(M62:M65) -> #DIV/0! | Q66: =SUM(Q63:R65) -> 0.0825
L67: =D58-SUM(L62:L65) -> 0 | M67: =L66-L67 -> 0
C72: BID TO:
C73: JOB NAME: | D73: 0
C74: LOCATION: | D74: 0
C75: BID # | D75: 0
C76: Code | D76: Budget Name | H76: Total | K76: Budget Name | O76: Total
C78: 0 | D78: No Buget | H78: ='Mono Slab on Grade Building 1'!AO81+'Gd Beams'!AF65+'Private Paving'!AE66+PIERS!AE75+Miscellaneous!AK8+'CIP EL. DECK'!AF68+COLUMNS!AF65+'SLAB ON DECK'!AD65+SIDEWALKS!AG65+'Site Walls'!AF71+PANELS!AH122+'SLAB ON GRADE'!AD64+'Gd Beams or Cont Footings'!AF65+Footings!AF65+'Garage Footings'!AF65+'Garage Walls'!AF65+'Mono Slab on Grade Building 2'!AO81+'Mono Slab on Grade Garden Style'!AO81+'ROW Paving'!AE66 -> 0 | J78: 35 | K78: Sub Demolition | O78: ='Mono Slab on Grade Building 1'!AO111+'Gd Beams'!AF93+'Private Paving'!AE94+PIERS!AE103+Miscellaneous!AK37+'CIP EL. DECK'!AF97+COLUMNS!AF93+'SLAB ON DECK'!AD93+SIDEWALKS!AG93+'Site Walls'!AF101+PANELS!AH150+'SLAB ON GRADE'!AD92+Footings!AF95+'Gd Beams or Cont Footings'!AF93+'Garage Footings'!AF95+'Mono Slab on Grade Building 2'!AO111+'Mono Slab on Grade Garden Style'!AO111+'Private Paving'!AE94+'Garage Walls'!AF101 -> 0
C79: 1 | D79: General Requirements | H79: =U59 -> 0 | J79: 36 | K79: Sub Panel Drawings | O79: ='Mono Slab on Grade Building 1'!AO112+'Gd Beams'!AF94+'Private Paving'!AE95+PIERS!AE104+Miscellaneous!AK38+'CIP EL. DECK'!AF98+COLUMNS!AF94+'SLAB ON DECK'!AD94+SIDEWALKS!AG94+'Site Walls'!AF102+PANELS!AH151+'SLAB ON GRADE'!AD93+Footings!AF96+'Gd Beams or Cont Footings'!AF94+'Garage Footings'!AF96+'Mono Slab on Grade Building 2'!AO112+'Mono Slab on Grade Garden Style'!AO112+'Private Paving'!AE95+'Garage Walls'!AF102 -> 0
C80: 2 | D80: Lumber Material | H80: ='Mono Slab on Grade Building 1'!AO83+'Gd Beams'!AF67+'Private Paving'!AE68+PIERS!AE77+Miscellaneous!AK10+'CIP EL. DECK'!AF70+COLUMNS!AF67+'SLAB ON DECK'!AD67+SIDEWALKS!AG67+'Site Walls'!AF73+PANELS!AH124+'SLAB ON GRADE'!AD66+'Gd Beams or Cont Footings'!AF67+Footings!AF67+'Garage Footings'!AF67+'Garage Walls'!AF67+'Mono Slab on Grade Building 2'!AO83+'Mono Slab on Grade Garden Style'!AO83+'Private Paving'!AE68 -> 0 | J80: 39 | K80: Sub Labor Pier Caps | O80: ='Mono Slab on Grade Building 1'!AO113+'Gd Beams'!AF95+'Private Paving'!AE96+PIERS!AE105+Miscellaneous!AK39+'CIP EL. DECK'!AF99+COLUMNS!AF95+'SLAB ON DECK'!AD95+SIDEWALKS!AG95+'Site Walls'!AF103+PANELS!AH152+'SLAB ON GRADE'!AD94+Footings!AF97+'Gd Beams or Cont Footings'!AF95+'Garage Footings'!AF97+'Mono Slab on Grade Building 2'!AO113+'Mono Slab on Grade Garden Style'!AO113+'Private Paving'!AE96+'Garage Walls'!AF103 -> 0
C81: 3 | D81: Sand Material | H81: ='Mono Slab on Grade Building 1'!AO84+'Gd Beams'!AF68+'Private Paving'!AE69+PIERS!AE78+Miscellaneous!AK11+'CIP EL. DECK'!AF71+COLUMNS!AF68+'SLAB ON DECK'!AD68+SIDEWALKS!AG68+'Site Walls'!AF74+PANELS!AH125+'SLAB ON GRADE'!AD67+'Gd Beams or Cont Footings'!AF68+Footings!AF68+'Garage Footings'!AF68+'Garage Walls'!AF68+'Mono Slab on Grade Building 2'!AO84+'Mono Slab on Grade Garden Style'!AO84+'Private Paving'!AE69 -> 0 | J81: 40 | K81: Sub Labor | O81: ='Mono Slab on Grade Building 1'!AO114+'Gd Beams'!AF96+'Private Paving'!AE97+PIERS!AE106+Miscellaneous!AK40+'CIP EL. DECK'!AF100+COLUMNS!AF96+'SLAB ON DECK'!AD96+SIDEWALKS!AG96+'Site Walls'!AF104+PANELS!AH153+'SLAB ON GRADE'!AD95+Footings!AF98+'Gd Beams or Cont Footings'!AF96+'Garage Footings'!AF98+'Mono Slab on Grade Building 2'!AO114+'Mono Slab on Grade Garden Style'!AO114+'Private Paving'!AE97+'Garage Walls'!AF104 -> 0
C82: 4 | D82: Rock Material | H82: ='Mono Slab on Grade Building 1'!AO85+'Gd Beams'!AF69+'Private Paving'!AE70+PIERS!AE79+Miscellaneous!AK12+'CIP EL. DECK'!AF72+COLUMNS!AF69+'SLAB ON DECK'!AD69+SIDEWALKS!AG69+'Site Walls'!AF75+PANELS!AH126+'SLAB ON GRADE'!AD68+'Gd Beams or Cont Footings'!AF69+Footings!AF69+'Garage Footings'!AF69+'Garage Walls'!AF75+'Mono Slab on Grade Building 2'!AO85+'Mono Slab on Grade Garden Style'!AO85+'ROW Paving'!AE70 -> 0 | J82: 41 | K82: Sub Labor Forming | O82: ='Mono Slab on Grade Building 1'!AO115+'Gd Beams'!AF97+'Private Paving'!AE98+PIERS!AE107+Miscellaneous!AK41+'CIP EL. DECK'!AF101+COLUMNS!AF97+'SLAB ON DECK'!AD97+SIDEWALKS!AG97+'Site Walls'!AF105+PANELS!AH154+'SLAB ON GRADE'!AD96+Footings!AF99+'Gd Beams or Cont Footings'!AF97+'Garage Footings'!AF99+'Mono Slab on Grade Building 2'!AO115+'Mono Slab on Grade Garden Style'!AO115+'Private Paving'!AE98+'Garage Walls'!AF105 -> 0
C83: 5 | D83: Reinforcement Material | H83: ='Mono Slab on Grade Building 1'!AO86+'Gd Beams'!AF70+'Private Paving'!AE71+PIERS!AE80+Miscellaneous!AK13+'CIP EL. DECK'!AF73+COLUMNS!AF70+'SLAB ON DECK'!AD70+SIDEWALKS!AG70+'Site Walls'!AF76+PANELS!AH127+'SLAB ON GRADE'!AD69+'Gd Beams or Cont Footings'!AF70+Footings!AF70+'Garage Footings'!AF70+'Garage Walls'!AF76+'Mono Slab on Grade Building 2'!AO86+'Mono Slab on Grade Garden Style'!AO86+'ROW Paving'!AE71 -> 0 | J83: 42 | K83: Sub Labor Grade, Poly, Reinf. | O83: ='Mono Slab on Grade Building 1'!AO116+'Gd Beams'!AF98+'Private Paving'!AE99+PIERS!AE108+Miscellaneous!AK42+'CIP EL. DECK'!AF102+COLUMNS!AF98+'SLAB ON DECK'!AD98+SIDEWALKS!AG98+'Site Walls'!AF106+PANELS!AH155+'SLAB ON GRADE'!AD97+Footings!AF100+'Gd Beams or Cont Footings'!AF98+'Garage Footings'!AF100+'Mono Slab on Grade Building 2'!AO116+'Mono Slab on Grade Garden Style'!AO116+'Private Paving'!AE99+'Garage Walls'!AF106 -> 0
C84: 6 | D84: Reinforcement Accessories | H84: ='Mono Slab on Grade Building 1'!AO87+'Gd Beams'!AF71+'Private Paving'!AE72+PIERS!AE81+Miscellaneous!AK14+'CIP EL. DECK'!AF74+COLUMNS!AF71+'SLAB ON DECK'!AD71+SIDEWALKS!AG71+'Site Walls'!AF77+PANELS!AH128+'SLAB ON GRADE'!AD70+'Gd Beams or Cont Footings'!AF71+Footings!AF71+'Garage Footings'!AF71+'Garage Walls'!AF77+'Mono Slab on Grade Building 2'!AO87+'Mono Slab on Grade Garden Style'!AO87+'ROW Paving'!AE72 -> 0 | J84: 44 | K84: Sub Labor Place & Finish | O84: ='Mono Slab on Grade Building 1'!AO117+'Gd Beams'!AF99+'Private Paving'!AE100+PIERS!AE109+Miscellaneous!AK43+'CIP EL. DECK'!AF103+COLUMNS!AF99+'SLAB ON DECK'!AD99+SIDEWALKS!AG99+'Site Walls'!AF107+PANELS!AH156+'SLAB ON GRADE'!AD98+Footings!AF101+'Gd Beams or Cont Footings'!AF99+'Garage Footings'!AF101+'Mono Slab on Grade Building 2'!AO117+'Mono Slab on Grade Garden Style'!AO117+'Private Paving'!AE100+'Garage Walls'!AF107 -> 0
C85: 7 | D85: P.T. Cable Material | H85: ='Mono Slab on Grade Building 1'!AO88+'Gd Beams'!AF72+'Private Paving'!AE73+PIERS!AE82+Miscellaneous!AK15+'CIP EL. DECK'!AF75+COLUMNS!AF72+'SLAB ON DECK'!AD72+SIDEWALKS!AG72+'Site Walls'!AF78+PANELS!AH129+'SLAB ON GRADE'!AD71+'Gd Beams or Cont Footings'!AF72+Footings!AF72+'Garage Footings'!AF72+'Garage Walls'!AF78+'Mono Slab on Grade Building 2'!AO88+'Mono Slab on Grade Garden Style'!AO88+'ROW Paving'!AE73 -> 0 | J85: 45 | K85: Sub Labor - Drops | O85: ='Mono Slab on Grade Building 1'!AO118+'Gd Beams'!AF100+'Private Paving'!AE101+PIERS!AE110+Miscellaneous!AK44+'CIP EL. DECK'!AF104+COLUMNS!AF100+'SLAB ON DECK'!AD100+SIDEWALKS!AG100+'Site Walls'!AF108+PANELS!AH157+'SLAB ON GRADE'!AD99+Footings!AF102+'Gd Beams or Cont Footings'!AF100+'Garage Footings'!AF102+'Mono Slab on Grade Building 2'!AO118+'Mono Slab on Grade Garden Style'!AO118+'Private Paving'!AE101+'Garage Walls'!AF108 -> 0
C86: 8 | D86: Concrete Material | H86: ='Mono Slab on Grade Building 1'!AO89+'Gd Beams'!AF73+'Private Paving'!AE74+PIERS!AE83+Miscellaneous!AK16+'CIP EL. DECK'!AF76+COLUMNS!AF73+'SLAB ON DECK'!AD73+SIDEWALKS!AG73+'Site Walls'!AF79+PANELS!AH130+'SLAB ON GRADE'!AD72+'Gd Beams or Cont Footings'!AF73+Footings!AF73+'Garage Footings'!AF73+'Garage Walls'!AF79+'Mono Slab on Grade Building 2'!AO89+'Mono Slab on Grade Garden Style'!AO89+'ROW Paving'!AE74 -> 0 | J86: 46 | K86: Sub Labor Strip Forms | O86: ='Mono Slab on Grade Building 1'!AO119+'Gd Beams'!AF101+'Private Paving'!AE102+PIERS!AE111+Miscellaneous!AK45+'CIP EL. DECK'!AF105+COLUMNS!AF101+'SLAB ON DECK'!AD101+SIDEWALKS!AG101+'Site Walls'!AF109+PANELS!AH158+'SLAB ON GRADE'!AD100+Footings!AF103+'Gd Beams or Cont Footings'!AF101+'Garage Footings'!AF103+'Mono Slab on Grade Building 2'!AO119+'Mono Slab on Grade Garden Style'!AO119+'Private Paving'!AE102+'Garage Walls'!AF109 -> 0
C87: 9 | D87: Carton Forms | H87: ='Mono Slab on Grade Building 1'!AO90+'Gd Beams'!AF74+'Private Paving'!AE75+PIERS!AE84+Miscellaneous!AK17+'CIP EL. DECK'!AF77+COLUMNS!AF74+'SLAB ON DECK'!AD74+SIDEWALKS!AG74+'Site Walls'!AF80+PANELS!AH131+'SLAB ON GRADE'!AD73+'Gd Beams or Cont Footings'!AF74+Footings!AF74+'Garage Footings'!AF74+'Garage Walls'!AF80+'Mono Slab on Grade Building 2'!AO90+'Mono Slab on Grade Garden Style'!AO90+'ROW Paving'!AE75 -> 0 | J87: 47 | K87: Sub Labor Piers | O87: ='Mono Slab on Grade Building 1'!AO120+'Gd Beams'!AF102+'Private Paving'!AE103+PIERS!AE112+Miscellaneous!AK46+'CIP EL. DECK'!AF106+COLUMNS!AF102+'SLAB ON DECK'!AD102+SIDEWALKS!AG102+'Site Walls'!AF110+PANELS!AH159+'SLAB ON GRADE'!AD101+Footings!AF104+'Gd Beams or Cont Footings'!AF102+'Garage Footings'!AF104+'Mono Slab on Grade Building 2'!AO120+'Mono Slab on Grade Garden Style'!AO120+'Private Paving'!AE103+'Garage Walls'!AF110 -> 0
C88: 10 | D88: Cures / Sealers | H88: ='Mono Slab on Grade Building 1'!AO91+'Gd Beams'!AF75+'Private Paving'!AE76+PIERS!AE85+Miscellaneous!AK18+'CIP EL. DECK'!AF78+COLUMNS!AF75+'SLAB ON DECK'!AD75+SIDEWALKS!AG75+'Site Walls'!AF83+PANELS!AH132+'SLAB ON GRADE'!AD74+'Gd Beams or Cont Footings'!AF75+Footings!AF77+'Garage Footings'!AF77+'Garage Walls'!AF83+'Mono Slab on Grade Building 2'!AO91+'Mono Slab on Grade Garden Style'!AO91+'ROW Paving'!AE76 -> 0 | J88: 48 | K88: Sub Labor Paving | O88: ='Mono Slab on Grade Building 1'!AO121+'Gd Beams'!AF103+'Private Paving'!AE104+PIERS!AE113+Miscellaneous!AK47+'CIP EL. DECK'!AF107+COLUMNS!AF103+'SLAB ON DECK'!AD103+SIDEWALKS!AG103+'Site Walls'!AF111+PANELS!AH160+'SLAB ON GRADE'!AD102+Footings!AF105+'Gd Beams or Cont Footings'!AF103+'Garage Footings'!AF105+'Mono Slab on Grade Building 2'!AO121+'Mono Slab on Grade Garden Style'!AO121+'Private Paving'!AE104+'Garage Walls'!AF111 -> 0
C89: 11 | D89: Patch & Grout Materials | H89: ='Mono Slab on Grade Building 1'!AO92+'Gd Beams'!AF76+'Private Paving'!AE77+PIERS!AE86+Miscellaneous!AK19+'CIP EL. DECK'!AF79+COLUMNS!AF76+'SLAB ON DECK'!AD76+SIDEWALKS!AG76+'Site Walls'!AF84+PANELS!AH133+'SLAB ON GRADE'!AD75+'Gd Beams or Cont Footings'!AF76+Footings!AF78+'Garage Footings'!AF78+'Garage Walls'!AF84+'Mono Slab on Grade Building 2'!AO92+'Mono Slab on Grade Garden Style'!AO92+'ROW Paving'!AE77 -> 0 | J89: 49 | K89: Sub Labor Metal Decks | O89: ='Mono Slab on Grade Building 1'!AO122+'Gd Beams'!AF104+'Private Paving'!AE105+PIERS!AE114+Miscellaneous!AK48+'CIP EL. DECK'!AF108+COLUMNS!AF104+'SLAB ON DECK'!AD104+SIDEWALKS!AG104+'Site Walls'!AF112+PANELS!AH161+'SLAB ON GRADE'!AD103+Footings!AF106+'Gd Beams or Cont Footings'!AF104+'Garage Footings'!AF106+'Mono Slab on Grade Building 2'!AO122+'Mono Slab on Grade Garden Style'!AO122+'Private Paving'!AE105+'Garage Walls'!AF112 -> 0
C90: 12 | D90: Panel Accessories | H90: ='Mono Slab on Grade Building 1'!AO93+'Gd Beams'!AF77+'Private Paving'!AE78+PIERS!AE87+Miscellaneous!AK21+'CIP EL. DECK'!AF80+COLUMNS!AF77+'SLAB ON DECK'!AD77+SIDEWALKS!AG77+'Site Walls'!AF85+PANELS!AH134+'SLAB ON GRADE'!AD76+'Gd Beams or Cont Footings'!AF77+Footings!AF79+'Garage Footings'!AF79+'Garage Walls'!AF85+'Mono Slab on Grade Building 2'!AO93+'Mono Slab on Grade Garden Style'!AO93+'ROW Paving'!AE78 -> 0 | J90: 50 | K90: Sub Labor Walls | O90: ='Mono Slab on Grade Building 1'!AO123+'Gd Beams'!AF105+'Private Paving'!AE106+PIERS!AE115+Miscellaneous!AK49+'CIP EL. DECK'!AF109+COLUMNS!AF105+'SLAB ON DECK'!AD105+SIDEWALKS!AG105+'Site Walls'!AF113+PANELS!AH162+'SLAB ON GRADE'!AD104+Footings!AF107+'Gd Beams or Cont Footings'!AF105+'Garage Footings'!AF107+'Mono Slab on Grade Building 2'!AO123+'Mono Slab on Grade Garden Style'!AO123+'Private Paving'!AE106+'Garage Walls'!AF113 -> 0
C91: 15 | D91: Carton Forms Material | H91: ='Mono Slab on Grade Building 1'!AO94+'Gd Beams'!AF78+'Private Paving'!AE79+PIERS!AE88+Miscellaneous!AK22+'CIP EL. DECK'!AF81+COLUMNS!AF78+'SLAB ON DECK'!AD78+SIDEWALKS!AG78+'Site Walls'!AF86+PANELS!AH135+'SLAB ON GRADE'!AD77+'Gd Beams or Cont Footings'!AF78+Footings!AF80+'Garage Footings'!AF80+'Garage Walls'!AF86+'Mono Slab on Grade Building 2'!AO94+'Mono Slab on Grade Garden Style'!AO94+'ROW Paving'!AE79 -> 0 | J91: 51 | K91: Sub Labor Elevated Slab | O91: ='Mono Slab on Grade Building 1'!AO124+'Gd Beams'!AF106+'Private Paving'!AE107+PIERS!AE116+Miscellaneous!AK50+'CIP EL. DECK'!AF110+COLUMNS!AF106+'SLAB ON DECK'!AD106+SIDEWALKS!AG106+'Site Walls'!AF114+PANELS!AH163+'SLAB ON GRADE'!AD105+Footings!AF108+'Gd Beams or Cont Footings'!AF106+'Garage Footings'!AF108+'Mono Slab on Grade Building 2'!AO124+'Mono Slab on Grade Garden Style'!AO124+'Private Paving'!AE107+'Garage Walls'!AF114 -> 0
C92: 16 | D92: Column form Rental | H92: ='Mono Slab on Grade Building 1'!AO96+'Gd Beams'!AF79+'Private Paving'!AE80+PIERS!AE89+Miscellaneous!AK23+'CIP EL. DECK'!AF82+COLUMNS!AF79+'SLAB ON DECK'!AD79+SIDEWALKS!AG79+'Site Walls'!AF87+PANELS!AH136+'SLAB ON GRADE'!AD78+'Gd Beams or Cont Footings'!AF79+Footings!AF81+'Garage Footings'!AF81+'Garage Walls'!AF87+'Mono Slab on Grade Building 2'!AO96+'Mono Slab on Grade Garden Style'!AO96+'ROW Paving'!AE80 -> 0 | J92: 52 | K92: Sub Labor Walks | O92: ='Mono Slab on Grade Building 1'!AO125+'Gd Beams'!AF107+'Private Paving'!AE108+PIERS!AE117+Miscellaneous!AK51+'CIP EL. DECK'!AF111+COLUMNS!AF107+'SLAB ON DECK'!AD107+SIDEWALKS!AG107+'Site Walls'!AF115+PANELS!AH164+'SLAB ON GRADE'!AD106+Footings!AF109+'Gd Beams or Cont Footings'!AF107+'Garage Footings'!AF109+'Mono Slab on Grade Building 2'!AO125+'Mono Slab on Grade Garden Style'!AO125+'Private Paving'!AE108+'Garage Walls'!AF115 -> 0
C93: 17 | D93: Deck Form Rental | H93: ='Mono Slab on Grade Building 1'!AO97+'Gd Beams'!AF80+'Private Paving'!AE81+PIERS!AE90+Miscellaneous!AK24+'CIP EL. DECK'!AF83+COLUMNS!AF80+'SLAB ON DECK'!AD80+SIDEWALKS!AG80+'Site Walls'!AF88+PANELS!AH137+'SLAB ON GRADE'!AD79+'Gd Beams or Cont Footings'!AF80+Footings!AF82+'Garage Footings'!AF82+'Garage Walls'!AF88+'Mono Slab on Grade Building 2'!AO97+'Mono Slab on Grade Garden Style'!AO97+'ROW Paving'!AE81 -> 0 | J93: 53 | K93: Sub Labor Panels | O93: ='Mono Slab on Grade Building 1'!AO126+'Gd Beams'!AF108+'Private Paving'!AE109+PIERS!AE118+Miscellaneous!AK52+'CIP EL. DECK'!AF112+COLUMNS!AF108+'SLAB ON DECK'!AD108+SIDEWALKS!AG108+'Site Walls'!AF116+PANELS!AH165+'SLAB ON GRADE'!AD107+Footings!AF110+'Gd Beams or Cont Footings'!AF108+'Garage Footings'!AF110+'Mono Slab on Grade Building 2'!AO126+'Mono Slab on Grade Garden Style'!AO126+'Private Paving'!AE109+'Garage Walls'!AF116 -> 0
C94: 18 | D94: Wall Form Rental | H94: ='Mono Slab on Grade Building 1'!AO98+'Gd Beams'!AF81+'Private Paving'!AE82+PIERS!AE91+Miscellaneous!AK25+'CIP EL. DECK'!AF84+COLUMNS!AF81+'SLAB ON DECK'!AD81+SIDEWALKS!AG81+'Site Walls'!AF89+PANELS!AH138+'SLAB ON GRADE'!AD80+'Gd Beams or Cont Footings'!AF81+Footings!AF83+'Garage Footings'!AF83+'Garage Walls'!AF89+'Mono Slab on Grade Building 2'!AO98+'Mono Slab on Grade Garden Style'!AO98+'ROW Paving'!AE82 -> 0 | J94: 54 | K94: Sub Labor Curbs | O94: ='Mono Slab on Grade Building 1'!AO127+'Gd Beams'!AF109+'Private Paving'!AE110+PIERS!AE119+Miscellaneous!AK53+'CIP EL. DECK'!AF113+COLUMNS!AF109+'SLAB ON DECK'!AD109+SIDEWALKS!AG109+'Site Walls'!AF117+PANELS!AH166+'SLAB ON GRADE'!AD108+Footings!AF111+'Gd Beams or Cont Footings'!AF109+'Garage Footings'!AF111+'Mono Slab on Grade Building 2'!AO127+'Mono Slab on Grade Garden Style'!AO127+'Private Paving'!AE110+'Garage Walls'!AF117 -> 0
C95: 20 | D95: Supervision | H95: ='Mono Slab on Grade Building 1'!AO99+'Gd Beams'!AF82+'Private Paving'!AE83+PIERS!AE92+Miscellaneous!AK26+'CIP EL. DECK'!AF85+COLUMNS!AF82+'SLAB ON DECK'!AD82+SIDEWALKS!AG82+'Site Walls'!AF90+PANELS!AH139+'SLAB ON GRADE'!AD81+'Gd Beams or Cont Footings'!AF82+Footings!AF84+'Garage Footings'!AF84+'Garage Walls'!AF90+'Mono Slab on Grade Building 2'!AO99+'Mono Slab on Grade Garden Style'!AO99+'ROW Paving'!AE83 -> 0 | J95: 55 | K95: Sub Labor Columns | O95: ='Mono Slab on Grade Building 1'!AO128+'Gd Beams'!AF110+'Private Paving'!AE111+PIERS!AE120+Miscellaneous!AK54+'CIP EL. DECK'!AF114+COLUMNS!AF110+'SLAB ON DECK'!AD110+SIDEWALKS!AG110+'Site Walls'!AF118+PANELS!AH167+'SLAB ON GRADE'!AD109+Footings!AF112+'Gd Beams or Cont Footings'!AF110+'Garage Footings'!AF112+'Mono Slab on Grade Building 2'!AO128+'Mono Slab on Grade Garden Style'!AO128+'Private Paving'!AE111+'Garage Walls'!AF118 -> 0
C96: 21 | D96: Supervision Expenses | H96: ='Mono Slab on Grade Building 1'!AO100+'Gd Beams'!AF83+'Private Paving'!AE84+PIERS!AE93+Miscellaneous!AK27+'CIP EL. DECK'!AF86+COLUMNS!AF83+'SLAB ON DECK'!AD83+SIDEWALKS!AG83+'Site Walls'!AF91+PANELS!AH140+'SLAB ON GRADE'!AD82+'Gd Beams or Cont Footings'!AF83+Footings!AF85+'Garage Footings'!AF85+'Garage Walls'!AF91+'Mono Slab on Grade Building 2'!AO100+'Mono Slab on Grade Garden Style'!AO100+'ROW Paving'!AE84 -> 0 | J96: 56 | K96: Sub Labor - Elevator Pit | O96: ='Mono Slab on Grade Building 1'!AO129+'Gd Beams'!AF111+'Private Paving'!AE112+PIERS!AE121+Miscellaneous!AK55+'CIP EL. DECK'!AF115+COLUMNS!AF111+'SLAB ON DECK'!AD111+SIDEWALKS!AG111+'Site Walls'!AF119+PANELS!AH168+'SLAB ON GRADE'!AD110+Footings!AF113+'Gd Beams or Cont Footings'!AF111+'Garage Footings'!AF113+'Mono Slab on Grade Building 2'!AO129+'Mono Slab on Grade Garden Style'!AO129+'Private Paving'!AE112+'Garage Walls'!AF119 -> 0
C97: 22 | D97: In House Labor | H97: ='Mono Slab on Grade Building 1'!AO101+'Gd Beams'!AF84+'Private Paving'!AE85+PIERS!AE94+Miscellaneous!AK28+'CIP EL. DECK'!AF87+COLUMNS!AF84+'SLAB ON DECK'!AD84+SIDEWALKS!AG84+'Site Walls'!AF92+PANELS!AH141+'SLAB ON GRADE'!AD83+'Gd Beams or Cont Footings'!AF84+Footings!AF86+'Garage Footings'!AF86+'Garage Walls'!AF92+'Mono Slab on Grade Building 2'!AO101+'Mono Slab on Grade Garden Style'!AO101+'ROW Paving'!AE85 -> 0 | J97: 57 | K97: Sub Labor - Walls and Footings | O97: ='Mono Slab on Grade Building 1'!AO130+'Gd Beams'!AF112+'Private Paving'!AE113+PIERS!AE122+Miscellaneous!AK56+'CIP EL. DECK'!AF116+COLUMNS!AF112+'SLAB ON DECK'!AD112+SIDEWALKS!AG112+'Site Walls'!AF120+PANELS!AH169+'SLAB ON GRADE'!AD111+Footings!AF114+'Gd Beams or Cont Footings'!AF112+'Garage Footings'!AF114+'Mono Slab on Grade Building 2'!AO130+'Mono Slab on Grade Garden Style'!AO130+'Private Paving'!AE113+'Garage Walls'!AF120 -> 0
C98: 23 | D98: Out of Town Expenses | H98: ='Mono Slab on Grade Building 1'!AO102+'Gd Beams'!AF85+'Private Paving'!AE86+PIERS!AE95+Miscellaneous!AK29+'CIP EL. DECK'!AF88+COLUMNS!AF85+'SLAB ON DECK'!AD85+SIDEWALKS!AG85+'Site Walls'!AF93+PANELS!AH142+'SLAB ON GRADE'!AD84+'Gd Beams or Cont Footings'!AF85+Footings!AF87+'Garage Footings'!AF87+'Garage Walls'!AF93+'Mono Slab on Grade Building 2'!AO102+'Mono Slab on Grade Garden Style'!AO102+'ROW Paving'!AE86 -> 0 | J98: 58 | K98: Sub Labor Other | O98: ='Mono Slab on Grade Building 1'!AO131+'Gd Beams'!AF113+'Private Paving'!AE114+PIERS!AE123+Miscellaneous!AK57+'CIP EL. DECK'!AF117+COLUMNS!AF113+'SLAB ON DECK'!AD113+SIDEWALKS!AG113+'Site Walls'!AF121+PANELS!AH170+'SLAB ON GRADE'!AD112+Footings!AF115+'Gd Beams or Cont Footings'!AF113+'Garage Footings'!AF115+'Mono Slab on Grade Building 2'!AO131+'Mono Slab on Grade Garden Style'!AO131+'Private Paving'!AE114+'Garage Walls'!AF121 -> 0
C99: 24 | D99: Labor Burden | H99: ='Mono Slab on Grade Building 1'!AO103+'Gd Beams'!AF86+'Private Paving'!AE87+PIERS!AE96+Miscellaneous!AK30+'CIP EL. DECK'!AF89+COLUMNS!AF86+'SLAB ON DECK'!AD86+SIDEWALKS!AG86+'Site Walls'!AF94+PANELS!AH143+'SLAB ON GRADE'!AD85+'Gd Beams or Cont Footings'!AF86+Footings!AF88+'Garage Footings'!AF88+'Garage Walls'!AF94+'Mono Slab on Grade Building 2'!AO103+'Mono Slab on Grade Garden Style'!AO103+'ROW Paving'!AE87 -> 0 | J99: 59 | K99: Sub Labor Rebar Per Ton | O99: ='Mono Slab on Grade Building 1'!AO132+'Gd Beams'!AF114+'Private Paving'!AE115+PIERS!AE124+Miscellaneous!AK58+'CIP EL. DECK'!AF118+COLUMNS!AF114+'SLAB ON DECK'!AD114+SIDEWALKS!AG114+'Site Walls'!AF122+PANELS!AH171+'SLAB ON GRADE'!AD113+Footings!AF116+'Gd Beams or Cont Footings'!AF114+'Garage Footings'!AF116+'Mono Slab on Grade Building 2'!AO132+'Mono Slab on Grade Garden Style'!AO132+'Private Paving'!AE115+'Garage Walls'!AF122 -> 0
C100: 25 | D100: In House Labor - Walks & Site | H100: ='Mono Slab on Grade Building 1'!AO104+'Gd Beams'!AF87+'Private Paving'!AE88+PIERS!AE97+Miscellaneous!AK31+'CIP EL. DECK'!AF90+COLUMNS!AF87+'SLAB ON DECK'!AD87+SIDEWALKS!AG87+'Site Walls'!AF95+PANELS!AH144+'SLAB ON GRADE'!AD86+'Gd Beams or Cont Footings'!AF87+Footings!AF89+'Garage Footings'!AF89+'Garage Walls'!AF95+'Mono Slab on Grade Building 2'!AO104+'Mono Slab on Grade Garden Style'!AO104+'ROW Paving'!AE88 -> 0 | J100: 60 | K100: Equipment Rental | O100: ='Mono Slab on Grade Building 1'!AO133+'Gd Beams'!AF115+'Private Paving'!AE116+PIERS!AE125+Miscellaneous!AK59+'CIP EL. DECK'!AF119+COLUMNS!AF115+'SLAB ON DECK'!AD115+SIDEWALKS!AG115+'Site Walls'!AF123+PANELS!AH172+'SLAB ON GRADE'!AD114+Footings!AF117+'Gd Beams or Cont Footings'!AF115+'Garage Footings'!AF117+'Mono Slab on Grade Building 2'!AO133+'Mono Slab on Grade Garden Style'!AO133+'Private Paving'!AE116+'Garage Walls'!AF123 -> 0
C101: 30 | D101: Sub Pumping | H101: ='Mono Slab on Grade Building 1'!AO105+'Gd Beams'!AF88+'Private Paving'!AE89+PIERS!AE98+Miscellaneous!AK32+'CIP EL. DECK'!AF91+COLUMNS!AF88+'SLAB ON DECK'!AD88+SIDEWALKS!AG88+'Site Walls'!AF96+PANELS!AH145+'SLAB ON GRADE'!AD87+'Gd Beams or Cont Footings'!AF88+Footings!AF90+'Garage Footings'!AF90+'Garage Walls'!AF96+'Mono Slab on Grade Building 2'!AO105+'Mono Slab on Grade Garden Style'!AO105+'ROW Paving'!AE89 -> 0 | J101: 65 | K101: Small Tools | O101: ='Mono Slab on Grade Building 1'!AO134+'Gd Beams'!AF116+'Private Paving'!AE117+PIERS!AE126+Miscellaneous!AK60+'CIP EL. DECK'!AF120+COLUMNS!AF116+'SLAB ON DECK'!AD116+SIDEWALKS!AG116+'Site Walls'!AF124+PANELS!AH173+'SLAB ON GRADE'!AD115+Footings!AF118+'Gd Beams or Cont Footings'!AF116+'Garage Footings'!AF118+'Mono Slab on Grade Building 2'!AO134+'Mono Slab on Grade Garden Style'!AO134+'Private Paving'!AE117+'Garage Walls'!AF124 -> 0
C102: 31 | D102: Sub Surveying | H102: ='Mono Slab on Grade Building 1'!AO106+'Gd Beams'!AF89+'Private Paving'!AE90+PIERS!AE99+Miscellaneous!AK33+'CIP EL. DECK'!AF92+COLUMNS!AF89+'SLAB ON DECK'!AD89+SIDEWALKS!AG89+'Site Walls'!AF97+PANELS!AH146+'SLAB ON GRADE'!AD88+'Gd Beams or Cont Footings'!AF89+Footings!AF91+'Garage Footings'!AF91+'Garage Walls'!AF97+'Mono Slab on Grade Building 2'!AO106+'Mono Slab on Grade Garden Style'!AO106+'ROW Paving'!AE90 -> 0 | J102: 95 | K102: Unrecognized savings | O102: ='Mono Slab on Grade Building 1'!AO135+'Gd Beams'!AF117+'Private Paving'!AE118+PIERS!AE127+Miscellaneous!AK61+'CIP EL. DECK'!AF121+COLUMNS!AF117+'SLAB ON DECK'!AD117+SIDEWALKS!AG117+'Site Walls'!AF125+PANELS!AH174+'SLAB ON GRADE'!AD116+Footings!AF119+'Gd Beams or Cont Footings'!AF117+'Garage Footings'!AF119+'Mono Slab on Grade Building 2'!AO135+'Mono Slab on Grade Garden Style'!AO135+'Private Paving'!AE118+'Garage Walls'!AF125 -> 0
C103: 32 | D103: Sub Drilling | H103: ='Mono Slab on Grade Building 1'!AO107+'Gd Beams'!AF90+'Private Paving'!AE91+PIERS!AE100+Miscellaneous!AK34+'CIP EL. DECK'!AF93+COLUMNS!AF90+'SLAB ON DECK'!AD90+SIDEWALKS!AG90+'Site Walls'!AF98+PANELS!AH147+'SLAB ON GRADE'!AD89+'Gd Beams or Cont Footings'!AF90+Footings!AF92+'Garage Footings'!AF92+'Garage Walls'!AF98+'Mono Slab on Grade Building 2'!AO107+'Mono Slab on Grade Garden Style'!AO107+'ROW Paving'!AE91 -> 0
C104: 33 | D104: Sub Haul-Off Spoils | H104: ='Mono Slab on Grade Building 1'!AO108+'Gd Beams'!AF91+'Private Paving'!AE92+PIERS!AE101+Miscellaneous!AK35+'CIP EL. DECK'!AF94+COLUMNS!AF91+'SLAB ON DECK'!AD91+SIDEWALKS!AG91+'Site Walls'!AF99+PANELS!AH148+'SLAB ON GRADE'!AD90+'Gd Beams or Cont Footings'!AF91+Footings!AF93+'Garage Footings'!AF93+'Garage Walls'!AF99+'Mono Slab on Grade Building 2'!AO108+'Mono Slab on Grade Garden Style'!AO108+'ROW Paving'!AE92 -> 0
C105: 34 | D105: Sub Sawcutting/Sealing | H105: ='Mono Slab on Grade Building 1'!AO109+'Gd Beams'!AF92+'Private Paving'!AE93+PIERS!AE102+Miscellaneous!AK36+'CIP EL. DECK'!AF95+COLUMNS!AF92+'SLAB ON DECK'!AD92+SIDEWALKS!AG92+'Site Walls'!AF100+PANELS!AH149+'SLAB ON GRADE'!AD91+'Gd Beams or Cont Footings'!AF92+Footings!AF94+'Garage Footings'!AF94+'Garage Walls'!AF100+'Mono Slab on Grade Building 2'!AO109+'Mono Slab on Grade Garden Style'!AO109+'ROW Paving'!AE93 -> 0
O106: =SUM(O78:P102)+SUM(H79:I105) -> 0

Sheet Pricing
A1: COMPANY | C1: CONTACT | D1: Phone | E1: DATE | F1: 3000 PSI W/ ASH PIERS, SOG | G1: 3500 Psi | H1: 4000 psi | I1: 4500 psi | J1: 5000 psi | K1: 3000 PSI Sidewalk and Hardscape | M1: Whitecap update 5/12/2025
A2: =IF(F2=F3,A3,IF(F2=F4,A4,IF(F2=F5,A5,IF(F2=F6,A6,0)))) -> Martin Marrieta | F2: =MIN(IF(F3>0,F3,1000),IF(F4>0,F4,1000),IF(F5>0,F5,1000),IF(F6>0,F6,1000),IF(F7>0,F7,1000),IF(F8>0,F8,1000)) -> 147 | G2: =MIN(IF(G3>0,G3,1000),IF(G4>0,G4,1000),IF(G5>0,G5,1000),IF(G6>0,G6,1000),IF(G7>0,G7,1000),IF(G8>0,G8,1000)) -> 152 | H2: =MIN(IF(H3>0,H3,1000),IF(H4>0,H4,1000),IF(H5>0,H5,1000),IF(H6>0,H6,1000),IF(H7>0,H7,1000),IF(H8>0,H8,1000)) -> 157 | I2: =MIN(IF(I3>0,I3,1000),IF(I4>0,I4,1000),IF(I5>0,I5,1000),IF(I6>0,I6,1000),IF(I7>0,I7,1000),IF(I8>0,I8,1000)) -> 162 | J2: =MIN(IF(J3>0,J3,1000),IF(J4>0,J4,1000),IF(J5>0,J5,1000),IF(J6>0,J6,1000),IF(J7>0,J7,1000),IF(J8>0,J8,1000)) -> 167 | K2: =MIN(IF(K3>0,K3,1000),IF(K4>0,K4,1000),IF(K5>0,K5,1000),IF(K6>0,K6,1000),IF(K7>0,K7,1000),IF(K8>0,K8,1000)) -> 147 | L2: =MIN(IF(L3>0,L3,1000),IF(L4>0,L4,1000),IF(L5>0,L5,1000),IF(L6>0,L6,1000),IF(L7>0,L7,1000),IF(L8>0,L8,1000)) -> 1000 | M2: LUMBER AND ACCSESS | N2: Unit Cost | O2: Unit | P2: CODE | T2: Low Cost calculator
A3: Martin Marrieta | C3: Justin | F3: 147 | G3: =F3+5 -> 152 | H3: =G3+5 -> 157 | I3: =H3+5 -> 162 | J3: =I3+5 -> 167 | K3: =F3 -> 147 | M3: 2 X 4 X 16' | N3: =9/16 -> 0.5625 | O3: /LNFT | T3: MIX 1 | U3: MIX 2 | V3: MIX 3 | W3: MIX 4 | X3: MIX 5 | Y3: MIX 6
M4: 2 X 6 X 16' | N4: =10.5/16 -> 0.65625 | O4: /LNFT | S4: MONO | T4: ='Mono Slab on Grade Garden Style'!BK105 -> 0 | U4: ='Mono Slab on Grade Garden Style'!BM105 -> 0 | V4: ='Mono Slab on Grade Garden Style'!BQ105 -> 0 | W4: ='Mono Slab on Grade Garden Style'!BR105 -> 0 | X4: ='Mono Slab on Grade Garden Style'!BS105 -> 0 | Y4: ='Mono Slab on Grade Garden Style'!BT105 -> 0
M5: 2 X 8 X 16' | N5: 1 | O5: /LNFT | S5: GRADE | T5: ='Gd Beams'!AN36 -> 0 | U5: ='Gd Beams'!AO36 -> 0 | V5: ='Gd Beams'!AP36 -> 0 | W5: ='Gd Beams'!AQ36 -> 0 | X5: ='Gd Beams'!AR36 -> 0 | Y5: ='Gd Beams'!AS36 -> 0 | AA5: =IF(F5>0,F5) -> FALSE
M6: 2 X 10 X 16' | N6: =20/16 -> 1.25 | O6: /LNFT | S6: SOG | T6: ='SLAB ON DECK'!AL27 -> 0 | U6: ='SLAB ON DECK'!AM27 -> 0 | V6: ='SLAB ON DECK'!AN27 -> 0 | W6: ='SLAB ON DECK'!AO27 -> 0 | X6: ='SLAB ON DECK'!AP27 -> 0 | Y6: ='SLAB ON DECK'!AQ27 -> 0
M7: 3/4 " FORMING PLY | N7: 50 | O7: /SHEET | S7: PAVING | T7: ='Private Paving'!AI27 -> 0 | U7: ='Private Paving'!AJ27 -> 0 | V7: ='Private Paving'!AK27 -> 0 | W7: ='Private Paving'!AL27 -> 0 | X7: ='Private Paving'!AM27 -> 0 | Y7: ='Private Paving'!AN27 -> 0
M8: MASONITE SIDING | N8: 19 | O8: /SHEET | S8: PIERS | T8: =PIERS!AS34 -> 0 | U8: =PIERS!AT34 -> 0 | V8: =PIERS!AU34 -> 0 | W8: =PIERS!AV34 -> 0 | X8: =PIERS!AW34 -> 0 | Y8: =PIERS!AX34 -> 0
A9: COST PER INCH FOR BELLS | E9: 1.5 | M9: 1 X 1 TACT STRIP | N9: 0.15 | O9: /LNFT | S9: SIDE WALKS | T9: =SIDEWALKS!AE27 -> 0 | U9: =SIDEWALKS!AF27 -> 0 | V9: =SIDEWALKS!AG27 -> 0 | W9: =SIDEWALKS!AH27 -> 0 | X9: =SIDEWALKS!AI27 -> 0 | Y9: =SIDEWALKS!AJ27 -> 0
A10: DIA. PIERS IN INCHES | M10: 1 X 4 RED WOOD | N10: 1 | O10: /LNFT | S10: MISC | T10: =IF(T4<T5,T4,T5) -> 0 | U10: =IF(U4<U5,U4,U5) -> 0 | V10: =IF(V4<V5,V4,V5) -> 0 | W10: =IF(W4<W5,W4,W5) -> 0 | X10: =IF(X4<X5,X4,X5) -> 0 | Y10: =IF(Y4<Y5,Y4,Y5) -> 0
A11: 12 | B11: 18 | C11: 24 | D11: 30 | E11: 36 | F11: 42 | G11: 48 | H11: 54 | M11: 1 X 6 RED WOOD | N11: 1.25 | O11: /LNFT
A12: 6 | B12: 9 | C12: 10 | D12: 12 | E12: 15 | F12: 18 | G12: 21 | H12: 36 | M12: 1 X 8 RED WOOD | N12: 0.9 | O12: /LNFT | T12: =IF(T6<T7,T6,T7) -> 0 | U12: =IF(U6<U7,U6,U7) -> 0 | V12: =IF(V6<V7,V6,V7) -> 0 | W12: =IF(W6<W7,W6,W7) -> 0 | X12: =IF(X6<X7,X6,X7) -> 0 | Y12: =IF(Y6<Y7,Y6,Y7) -> 0
A13: CASING | K13: 6 | L13: =K13/16 -> 0.375 | M13: ACCESSORIES | N13: 0.04 | O13: /LB
A14: 10 | B14: 12 | C14: 14 | D14: 16 | E14: 18 | F14: 12 | G14: 15 | H14: 18 | K14: 7.2 | L14: =K14/16 -> 0.45 | M14: 2 x 2 x 30 Stakes | N14: 18 | O14: /BNDLE | Q14: GUAGE | R14: DIA. | T14: =IF(T8<T9,T8,T9) -> 0 | U14: =IF(U8<U9,U8,U9) -> 0 | V14: =IF(V8<V9,V8,V9) -> 0 | W14: =IF(W8<W9,W8,W9) -> 0 | X14: =IF(X8<X9,X8,X9) -> 0 | Y14: =IF(Y8<Y9,Y8,Y9) -> 0
A15: DEDUCT | K15: 9.46 | L15: =K15/16 -> 0.59125 | M15: 16p NAILS DUPLEX | N15: 42 | O15: /BOX | Q15: 7 | R15: 0.1793 | T15: =IF(T10<T12,T10,T12) -> 0 | U15: =IF(U10<U12,U10,U12) -> 0 | V15: =IF(V10<V12,V10,V12) -> 0 | W15: =IF(W10<W12,W10,W12) -> 0 | X15: =IF(X10<X12,X10,X12) -> 0 | Y15: =IF(Y10<Y12,Y10,Y12) -> 0
A16: 0 | C16: 0 | D16: 0 | E16: 0 | K16: 11.34 | L16: =K16/16 -> 0.70875 | M16: 8p DUPLEX | N16: 42 | O16: /BOX | Q16: 8 | R16: 0.1644 | T16: =IF(T11<T13,T11,T13) -> 0 | U16: =IF(U11<U13,U11,U13) -> 0 | V16: =IF(V11<V13,V11,V13) -> 0 | W16: =IF(W11<W13,W11,W13) -> 0 | X16: =IF(X11<X13,X11,X13) -> 0 | Y16: =IF(Y11<Y13,Y11,Y13) -> 0
M17: 6p NAILS | N17: 42 | O17: /BOX | Q17: 9 | R17: 0.1495 | T17: =IF(T12<T14,T12,T14) -> 0 | U17: =IF(U12<U14,U12,U14) -> 0 | V17: =IF(V12<V14,V12,V14) -> 0 | W17: =IF(W12<W14,W12,W14) -> 0 | X17: =IF(X12<X14,X12,X14) -> 0 | Y17: =IF(Y12<Y14,Y12,Y14) -> 0
A18: SAND DELIVERED PER TON | D18: 25 | E18: /YD | K18: 6.6 | L18: =K18/16 -> 0.4125 | M18: KEYWAY | N18: 0.78 | O18: /LNFT
A19: ROCK DELEVERED PER TON | D19: 40 | E19: /YD | K19: 8.75 | L19: =K19/16 -> 0.546875 | M19: CHAMFER | N19: 0.16 | O19: /LNFT | Q19: 10 | R19: 0.1345 | T19: =IF(T15<T17,T15,T17) -> 0 | U19: =IF(U15<U17,U15,U17) -> 0 | V19: =IF(V15<V17,V15,V17) -> 0 | W19: =IF(W15<W17,W15,W17) -> 0 | X19: =IF(X15<X17,X15,X17) -> 0 | Y19: =IF(Y15<Y17,Y15,Y17) -> 0
A20: STEEL | K20: 9.59 | L20: =K20/16 -> 0.599375 | M20: WALL TIES | N20: 45 | O20: 50/BOX
A21: REBAR PIERS | D21: 0.6 | E21: /LB | K21: 11.45 | L21: =K21/16 -> 0.715625 | M21: 1 X 2 X 18" STAKES | N21: 8 | O21: /BNDL
A22: REBAR GRADE BEAM | D22: 0.6 | E22: /LB | F22: =Summary!J56 -> 0 | M22: Structural Accessories
A23: REBAR PAVING | D23: 0.55 | E23: /LB | M23: METAL CHAIRS 2.5" | N23: 45 | O23: /BAG/500
A24: DOWEL SPACING / 3/4" & CAP | D24: 2 | E24: /EACH | M24: LIFT INSERT | N24: 12 | O24: /EACH
A25: WIRE MESH | C25: 10 GAGE | D25: 0.4 | E25: /SQ FT | M25: CAMLOCKS | N25: 0.25 | O25: /EACH
A26: WIRE MESH | C26: 8 GAGE | D26: 0.4 | E26: /SQ FT | M26: TURNBUCKLES | N26: 0.75 | O26: /EACH | R26: =R19*0.5 -> 0.06725 | S26: =R19*0.5 -> 0.06725 | T26: 3.145 | U26: 0.2836 | V26: 240 | W26: 12 | X26: =R26*S26*T26*U26*V26*W26 -> 11.617266
A27: WIRE MESH | C27: 6 GAGE | D27: 0.4 | E27: /SQ FT | M27: PATCH MATERIAL | N27: 15 | O27: /BAG
A28: POST TENSION CABLES | D28: 0.65 | E28: /SQ FT | M28: PIER SLEDS | N28: 1.7 | O28: /EACH | Q28: 6X6 | R28: =R19/2*R19/2*3.145*0.2836*20*6 -> 0.48405276
A29: 1/2" SMOOTH DOWELS & CAP | D29: 1.75 | E29: /EACH | M29: PIER BOOTS | N29: 2.7 | O29: /EACH
A30: EQUIPMENT RENTAL | D30: DAY | M30: SLAB CHAIRS | N30: 27 | O30: /BAG
A31: BACKHOE | D31: 385 | E31: /DAY | M31: POLSTERS | N31: 1.25 | O31: /LNFT
A32: BOXBLADE | D32: 245 | E32: /DAY | M32: BRACE INSERTS | N32: 8
A33: BOBCATS | D33: 350 | E33: /DAY | M33: ANCHOR BOLTS | N33: 25.5 | O33: /BOX
A34: TRENCHER | D34: 300 | E34: /DAY | M34: TIE WIRE | N34: 4 | O34: /ROLL
A35: CHIPPING HAMMER | D35: 50 | E35: /DAY | M35: Site Accessories
A36: COMPRESSOR | D36: 150 | E36: /DAY | M36: 2-1/4 PAVING CHAIRS | N36: 20 | O36: /BAG
A37: TOWER LIGHT w/ GENERATOR | D37: 65 | E37: /DAY | M37: 3-1/4 PAVING CHAIRS | N37: 35 | O37: /BAG
A38: GENERATOR | D38: 32 | E38: /DAY | M38: ANCHOR BOLTS 8"x1/2" (50/BX) | N38: 20 | O38: /BOX
A39: SKY LIFT | D39: 420 | E39: /DAY | M39: SPEED DOWEL INSERT w/ BASE | N39: 1 | O39: /EACH
A40: CRANE AND OPERATOR | D40: 1260 | E40: /DAY | M40: SNAP TIES | N40: 40 | O40: /BOX
A41: Concrete Pumping | D41: 16 | E41: /YD | M41: POLY 10 mill | N41: 100 | O41: /ROLL
A42: COMPACTOR | D42: 200 | E42: /DAY | M42: SLAB CURE | N42: 540 | O42: /DRUM
M43: FORM RELEASE | N43: 542 | O43: /DRUM
A44: Metro Pricing | C44: 39222 | M44: BOND BREAKER | N44: 635 | O44: /DRUM
A45: saw joints | C45: 0.35 | M45: Poly vapor barrier
A46: expansion | C46: 0.75 | M46: 6 mil 20 x 100 | N46: 60 | O46: /ROLL
A47: Silicone saw joints | C47: 0.7 | M47: 6 mil 32 x 100 | N47: 80 | O47: /ROLL
A48: Silicone expansions | C48: 1.45 | M48: 10 mil 20 x 100 | N48: 120 | O48: /ROLL
F49: Minimum | G49: Austin | H49: Buomount | K49: Whitecap | L49: 45789 | M49: STEGO WRAP 10 mil. 20 x 150 | N49: 400 | O49: /ROLL
A50: sawcutting | C50: 0.25 | D50: ln ft | F50: 150 | G50: 600 | H50: 800 | M50: RW Medows 15 mil VAPOR MAT | N50: =325+30 -> 355 | O50: /ROLL
A51: sawcutting | C51: 0.35 | D51: ln ft weekend | F51: 250
A52: curb cutting .25 / inch | F52: 150 | M52: FOAM FILL VOID | N52: 22.76 | O52: 2" x 4 x 8
M53: FOAM FILL VOID | N53: 1.65 | O53: /CU FT
A54: curb and gutter demo 8" | C54: 6 | D54: ln ft

Sheet CONCRETE BIDS
A1: company
A2: address
A3: city, state zip | D3: =NOW() -> 46139.548
A8: FROM: | B8: =Information!C8 -> Chad McKinney | E8: PHONE:
E9: FAX:
A11: RE: | B11: PLEASE SEND WRITTEN QUOTES FOR THE FOLLOWING JOB.
A14: Message
B15: PROJECT-G.C. | E15: CITY | G15: Location
B16: =Information!C2 -> 0 | E16: =Information!C4 -> 0 | G16: =Information!C3 -> 0 | L16: 3000 PSI / 4.5 SACK SIDE WALKS | M16: 3000 PSI 5 SACK PIERS GRADE BEAMS SOG PAVING | N16: 4000 PSI EL. DECK | O16: 5000 PSI BEAMS AND WALLS | P16: 5500 PSI COLUMNS
B19: =Pricing!F1 -> 3000 PSI W/ ASH PIERS, SOG | E19: =PIERS!AT39+'SLAB ON GRADE'!AJ27+'Mono Slab on Grade Building 1'!BI49+'CIP EL. DECK'!AU41+'Gd Beams'!AO37+'SLAB ON DECK'!AK27+COLUMNS!AO37+'Site Walls'!AI43+SIDEWALKS!AH27+'Private Paving'!AJ28+PANELS!AK120 -> 0 | F19: CY
B21: =Pricing!G1 -> 3500 Psi | E21: =PIERS!AU39+'SLAB ON GRADE'!AK27+'Mono Slab on Grade Building 1'!BJ49+'CIP EL. DECK'!AV41+'Gd Beams'!AP37+'SLAB ON DECK'!AL27+COLUMNS!AP37+'Site Walls'!AJ43+SIDEWALKS!AI27+'Private Paving'!AK28+PANELS!AL120 -> 0 | F21: CY
B23: =Pricing!H1 -> 4000 psi | E23: =PIERS!AV39+'SLAB ON GRADE'!AL27+'Mono Slab on Grade Building 1'!BK49+'CIP EL. DECK'!AW41+'Gd Beams'!AQ37+'SLAB ON DECK'!AM27+COLUMNS!AQ37+'Site Walls'!AK43+SIDEWALKS!AJ27+'Private Paving'!AL28+PANELS!AM120 -> 0 | F23: CY
B25: =Pricing!I1 -> 4500 psi | E25: =PIERS!AW39+'SLAB ON GRADE'!AM27+'Mono Slab on Grade Building 1'!BL49+'CIP EL. DECK'!AX41+'Gd Beams'!AR7+'SLAB ON DECK'!AN27+COLUMNS!AR37+'Site Walls'!AL43+SIDEWALKS!AK27+'Private Paving'!AM28+PANELS!AN120 -> 0 | F25: CY
B27: =Pricing!J1 -> 5000 psi | E27: =PIERS!AX39+'SLAB ON GRADE'!AN27+'Mono Slab on Grade Building 1'!BM49+'CIP EL. DECK'!AY41+'Gd Beams'!AS7+'SLAB ON DECK'!AO27+COLUMNS!AS37+'Site Walls'!AM43+SIDEWALKS!AL27+'Private Paving'!AN28+PANELS!AO120 -> 0 | F27: CY
B29: =Pricing!K1 -> 3000 PSI Sidewalk and Hardscape | E29: =PIERS!AY39+'SLAB ON GRADE'!AO27+'Mono Slab on Grade Building 1'!BN49+'CIP EL. DECK'!AZ41+'Gd Beams'!AT7+'SLAB ON DECK'!AP27+COLUMNS!AT37+'Site Walls'!AN43+SIDEWALKS!AM27+'Private Paving'!AO28+PANELS!AP120 -> 0 | F29: CY
E30: =SUM(E19:E29) -> 0
B31: Please price the above mix designs.
E32: Environmental Fee
E33: fuel charge
B35: If accepted by this date | F35: prices will be good through duration of project.
D36: Date
B40: Signature
B43: Company Name

Sheet Mono Slab on Grade Garden Style
B2: JOB NAME | AA2: DATE: | AC2: 37456
B3: =Summary!C2 -> 0 | I3: DWGS SUPPLIED: | K3: NAME | O3: DATE | S3: Rev. | AA3: Entered by: | AC3: =Information!C8 -> Chad McKinney
B4: =Summary!C3 -> 0 | I4: ARCHITECTUAL: | J4: =Summary!K3 -> 0 | O4: =Summary!O3 -> 0 | S4: =Summary!P3 -> 0
B5: =Summary!C4 -> 0 | I5: STRUCTURAL: | J5: =Summary!K4 -> 0 | O5: =Summary!O4 -> 0 | S5: =Summary!P4 -> 0 | AA5: =Information!H5 -> Approved by Chad:
B6: NUMBER | D6: DATE | I6: CIVIL: | J6: =Summary!K5 -> 0 | O6: =Summary!O5 -> 0 | S6: =Summary!P5 -> 0
B7: 0 | D7: 0 | I7: LANDSCAPE: | J7: =Summary!K6 -> 0 | O7: =Summary!O6 -> 0 | S7: =Summary!P6 -> 0 | AA7: =Information!H6 -> Approved by Edward:
B8: 0 | D8: 0 | G8: Concrete Supplier | J8: =Pricing!A2 -> Martin Marrieta
B9: TYPE | C9: BLD # | D9: SQUARE FOOTAGE | F9: THICK INCH | G9: QTY | H9: CABLE | I9: MIX DESIGN | J9: INCH OF SAND | K9: PERM. EDGE | L9: REINFORCING | N9: WIRE MESH Y/N | O9: EXP GB | Q9: Drops | S9: GRADE BEAMS | AC9: STEEL WT LBS | AD9: TOTAL YDS CON CRETE | AE9: PRICE PER SQ FT | AF9: TOTAL PRICE EACH | AG9: SF Per Yard | AV9: yrds conc. Beams | CB9: =SUM(BZ29:CD29) -> 0 | CO9: drops | CP9: Drop 2 | CQ9: GB1 | CR9: GB2 | CS9: GB3 | CT9: GB4 | CU9: GB5 | CV9: Horizontal | CW9: Total
G10: SLABS | L10: SIZE | M10: SPACE | O10: TYPE | P10: LN FT | Q10: TYPE | R10: LN FT | S10: TYPE | T10: LN FT | U10: TYPE | V10: LN FT | W10: TYPE | X10: LN FT | Y10: TYPE | Z10: LN FT | AA10: TYPE | AB10: LN FT | AO10: Drops | AQ10: CONCRETE GRADE BEAMS | AY10: rebar grade beams | BD10: TOTAL STEEL | BE10: SLAB REBAR | BF10: SQ FTWIRE MESH | BG10: QTY SLABS | BH10: Traf con | BI10: MIX #1 | BJ10: MIX #2 | BK10: MIX #3 | BL10: MIX #4 | BM10: MIX#5 | BN10: MIX #6 | BO10: TOTAL | BP10: SQ FT CABLES | BQ10: TOTAL PERIMITER | BR10: FF DROPS | BT10: TOTAL SQ FT | BU10: SAND | BW10: TOTAL COST EACH | BX10: TOTAL CONCRETE | BY10: TOTAL STEEL | BZ10: In-House Labor | CA10: Sub Labor | CB10: THICK EDGE | CC10: CURBS | CD10: TIE STEEL | CE10: SUPR | CF10: LUMBER | CG10: EQUIP | CH10: CONTRACT | CI10: ACCESS | CJ10: CABLES | CK10: CARTONS | CL10: WIRE MESH | CM10: SAND | CO10: Poly area | CP10: Poly area | CQ10: Poly area | CR10: poly area | CS10: poly area | CT10: poly area | CU10: poly area
O11: 9 | Q11: 10 | S11: 1 | T11: =K11 -> 0 | U11: 2 | W11: 3 | Y11: 4 | AA11: 5 | AC11: =IF(BG11=0,0,SUM(BD11:BE11)/BG11) -> 0 | AD11: =((D11*F11/324)*(1+K$71)+AV11) -> 0 | AE11: =IF(D11=0,0,AF11/D11) -> 0 | AF11: =SUM(BW11)*(1+M$64+Summary!P$64) -> 0 | AG11: =D11/AD11 -> #DIV/0! | AH11: =AF11*G11 -> 0 | AO11: =IF(O11=1,P11*$T$52,0)+IF(O11=2,P11*$T$53,0)+IF(O11=3,P11*$T$54,0)+IF(O11=4,P11*$T$55,0)+IF(O11=5,P11*$T$56,0)+IF(O11=6,P11*$T$57,0)+IF(O11=7,P11*$T$58,0)+IF(O11=8,P11*$T$59,0)+IF(O11=9,P11*$T$60,0)+IF(O11=10,P11*$T$61,0) -> 0 | AP11: =IF(Q11=1,R11*$T$52,0)+IF(Q11=2,R11*$T$53,0)+IF(Q11=3,R11*$T$54,0)+IF(Q11=4,R11*$T$55,0)+IF(Q11=5,R11*$T$56,0)+IF(Q11=6,R11*$T$57,0)+IF(Q11=7,R11*$T$58,0)+IF(Q11=8,R11*$T$59,0)+IF(Q11=9,R11*$T$60,0)+IF(Q11=10,R11*$T$61,0) -> 0 | AQ11: =IF(S11=1,T11*$T$52,0)+IF(S11=2,T11*$T$53,0)+IF(S11=3,T11*$T$54,0)+IF(S11=4,T11*$T$55,0)+IF(S11=5,T11*$T$56,0)+IF(S11=6,T11*$T$57,0)+IF(S11=7,T11*$T$58,0)+IF(S11=8,T11*$T$59,0)+IF(S11=9,T11*$T$60,0)+IF(S11=10,T11*$T$61,0) -> 0 | AR11: =IF(U11=1,V11*$T$52,0)+IF(U11=2,V11*$T$53,0)+IF(U11=3,V11*$T$54,0)+IF(U11=4,V11*$T$55,0)+IF(U11=5,V11*$T$56,0)+IF(U11=6,V11*$T$57,0)+IF(U11=7,V11*$T$58,0)+IF(U11=8,V11*$T$59,0)+IF(U11=9,V11*$T$60,0)+IF(U11=10,V11*$T$61,0) -> 0 | AS11: =IF(W11=1,X11*$T$52,0)+IF(W11=2,X11*$T$53,0)+IF(W11=3,X11*$T$54,0)+IF(W11=4,X11*$T$55,0)+IF(W11=5,X11*$T$56,0)+IF(W11=6,X11*$T$57,0)+IF(W11=7,X11*$T$58,0)+IF(W11=8,X11*$T$59,0)+IF(W11=9,X11*$T$60,0)+IF(W11=10,X11*$T$61,0) -> 0 | AT11: =IF(Y11=1,Z11*$T$52,0)+IF(Y11=2,Z11*$T$53,0)+IF(Y11=3,Z11*$T$54,0)+IF(Y11=4,Z11*$T$55,0)+IF(Y11=5,Z11*$T$56,0)+IF(Y11=6,Z11*$T$57,0)+IF(Y11=7,Z11*$T$58,0)+IF(Y11=8,Z11*$T$59,0)+IF(Y11=9,Z11*$T$60,0)+IF(Y11=10,Z11*$T$61,0) -> 0 | AU11: =IF(AA11=1,AB11*$T$52,0)+IF(AA11=2,AB11*$T$53,0)+IF(AA11=3,AB11*$T$54,0)+IF(AA11=4,AB11*$T$55,0)+IF(AA11=5,AB11*$T$56,0)+IF(AA11=6,AB11*$T$57,0)+IF(AA11=7,AB11*$T$58,0)+IF(AA11=8,AB11*$T$59,0)+IF(AA11=9,AB11*$T$60,0)+IF(AA11=10,AB11*$T$61,0) -> 0 | AV11: =SUM(AO11:AU11) -> 0 | AW11: =ROUNDUP(IF(O11=1,P11*$P$52,0)+IF(O11=2,P11*$P$53,0)+IF(O11=3,P11*$P$54,0)+IF(O11=4,P11*$P$55,0)+IF(O11=5,P11*$P$56,0)+IF(O11=6,P11*$P$57,0)+IF(O11=7,P11*$P$58,0)+IF(O11=8,P11*$P$59,0)+IF(O11=9,P11*$P$60,0)+IF(O11=10,P11*$P$61,0),0)*BG11 -> 0 | AX11: =ROUNDUP(IF(Q11=1,R11*$P$52,0)+IF(Q11=2,R11*$P$53,0)+IF(Q11=3,R11*$P$54,0)+IF(Q11=4,R11*$P$55,0)+IF(Q11=5,R11*$P$56,0)+IF(Q11=6,R11*$P$57,0)+IF(Q11=7,R11*$P$58,0)+IF(Q11=8,R11*$P$59,0)+IF(Q11=9,R11*$P$60,0)+IF(Q11=10,R11*$P$61,0),0) -> 0 | AY11: =ROUNDUP(IF(S11=1,T11*$P$52,0)+IF(S11=2,T11*$P$53,0)+IF(S11=3,T11*$P$54,0)+IF(S11=4,T11*$P$55,0)+IF(S11=5,T11*$P$56,0)+IF(S11=6,T11*$P$57,0)+IF(S11=7,T11*$P$58,0)+IF(S11=8,T11*$P$59,0)+IF(S11=9,T11*$P$60,0)+IF(S11=10,T11*$P$61,0),0) -> 0 | AZ11: =ROUNDUP(IF(U11=1,V11*$P$52,0)+IF(U11=2,V11*$P$53,0)+IF(U11=3,V11*$P$54,0)+IF(U11=4,V11*$P$55,0)+IF(U11=5,V11*$P$56,0)+IF(U11=6,V11*$P$57,0)+IF(U11=7,V11*$P$58,0)+IF(U11=8,V11*$P$59,0)+IF(U11=9,V11*$P$60,0)+IF(U11=10,V11*$P$61,0),0) -> 0 | BA11: =ROUNDUP(IF(W11=1,X11*$P$52,0)+IF(W11=2,X11*$P$53,0)+IF(W11=3,X11*$P$54,0)+IF(W11=4,X11*$P$55,0)+IF(W11=5,X11*$P$56,0)+IF(W11=6,X11*$P$57,0)+IF(W11=7,X11*$P$58,0)+IF(W11=8,X11*$P$59,0)+IF(W11=9,X11*$P$60,0)+IF(W11=10,X11*$P$61,0),0) -> 0 | BB11: =ROUNDUP(IF(Y11=1,Z11*$P$52,0)+IF(Y11=2,Z11*$P$53,0)+IF(Y11=3,Z11*$P$54,0)+IF(Y11=4,Z11*$P$55,0)+IF(Y11=5,Z11*$P$56,0)+IF(Y11=6,Z11*$P$57,0)+IF(Y11=7,Z11*$P$58,0)+IF(Y11=8,Z11*$P$59,0)+IF(Y11=9,Z11*$P$60,0)+IF(Y11=10,Z11*$P$61,0),0) -> 0 | BC11: =ROUNDUP(IF(AA11=1,AB11*$P$52,0)+IF(AA11=2,AB11*$P$53,0)+IF(AA11=3,AB11*$P$54,0)+IF(AA11=4,AB11*$P$55,0)+IF(AA11=5,AB11*$P$56,0)+IF(AA11=6,AB11*$P$57,0)+IF(AA11=7,AB11*$P$58,0)+IF(AA11=8,AB11*$P$59,0)+IF(AA11=9,AB11*$P$60,0)+IF(AA11=10,AB11*$P$61,0),0) -> 0 | BD11: =SUM(AW11:BC11)*BG11 -> 0 | BE11: =IF(M11=0,0,(M11/12+M11/12)/(M11/12*M11/12)*D11*((L11/16*L11/16)*10.6870159))*(1+K$74)*BG11 -> 0 | BF11: =IF(N11="Y",D11*(1+K$75)*BG11,0) -> 0 | BG11: =G11 -> 0 | BH11: =IF(N11="y",D11,0) -> 0 | BI11: =IF($I11=1,$AD11,0)*BG11 -> 0 | BJ11: =IF($I11=2,$AD11,0)*BG11 -> 0 | BK11: =IF($I11=3,$AD11,0)*BG11 -> 0 | BL11: =IF($I11=4,$AD11,0)*BG11 -> 0 | BM11: =IF($I11=5,$AD11,0)*BG11 -> 0 | BN11: =IF($I11=6,$AD11,0)*BG11 -> 0 | BO11: =SUM(BI11:BN11) -> 0 | BP11: =IF(H11="N",0,D11)*BG11 -> 0 | BQ11: =K11*BG11 -> 0 | BR11: =IF(O11=1,D$52*P11/12,IF(O11=2,D$53*P11/12,IF(O11=3,D$54*P11/12,IF(O11=4,D$55*P11/12,IF(O11=5,D$56*P11/12,IF(O11=6,D$57*P11/12,IF(O11=7,D$58*P11/12,IF(O11=8,D$59*P11/12,IF(O11=9,D$60*P11/12,IF(O11=10,D$61*P11/12,0))))))*BG11)))) -> 0 | BS11: =IF(Q11=1,D$52*R11/12,IF(Q11=2,D$53*R11/12,IF(Q11=3,D$54*R11/12,IF(Q11=4,D$55*R11/12,IF(Q11=5,D$56*R11/12,IF(Q11=6,D$57*R11/12,IF(Q11=7,D$58*R11/12,IF(Q11=8,D$59*R11/12,IF(Q11=9,D$60*R11/12,IF(Q11=10,D$61*R11/12,0))))))*BG11)))) -> 0 | BT11: =D11*BG11 -> 0 | BU11: =D11*J11/324*(1+K$77)*BG11 -> 0 | BV11: =AC11*BG11 -> 0 | BW11: =IF(BG11=0,0,SUM(BX11:CM11)/BG11) -> 0 | BX11: =(BI11*Pricing!F$2+BJ11*Pricing!G$2+BK11*Pricing!H$2+BL11*Pricing!I$2+BM11*Pricing!J$2+BN11*Pricing!K$2)*IF(AC$63="N",(1+AE$63),1) -> 0 | BY11: =AC11*G$74*IF(AC$63="n",1+AE$63,1)*BG11 -> 0 | BZ11: =IF(I$83=0,0,D11*(SUM(L$83:M$86)+L$88)/I$83*BG11) -> 0 | CA11: =IF(I$83=0,0,D11*(SUM(O$83:P$86)+O$88)/I$83*BG11) -> 0 | CB11: =BR11+BS11*E$87 -> 0 | CD11: =BD11/2000*E$89 -> 0 | CE11: =IF(D$49=0,0,SUM(O$92:P$96)/D$49*D11)*BG11 -> 0 | CF11: =IF(D$49=0,0,SUM(AF$72:AF$99)/D$49*D11*BG11) -> 0 | CG11: =IF(D$49=0,0,SUM(O$98:P$103)/D$49*D11)*BG11 -> 0 | CH11: =IF(D$49=0,0,SUM(O$105:O$111)/D$49)*D11*BG11 -> 0 | CI11: =IF(D$49=0,0,SUM(AF$100:AF$111)/D$49*D11*BG11) -> 0 | CJ11: =IF(J$76>0,J$76/D$49*D11*G11,BP11*(G$76*(1+AE$63))) -> 0 | CK11: =IF(L$78=0,0,O$78/L$78)*AW11+IF(L$79=0,0,O$79/L$79)*BC11+IF(L$80=0,0,O$80/L$80)*BC11 -> 0 | CL11: =BF11*G$75*IF(AC$63="Y",1,1+AE$63) -> 0 | CM11: =BU11*G$77*IF(AC$63="Y",1,1+AE$63) -> 0 | CO11: =IF(O11=1,P11*$AM$52,0)+IF(O11=2,P11*$AM$53,0)+IF(O11=3,P11*$AM$54,0)+IF(O11=4,P11*$AM$55,0)+IF(O11=5,P11*$AM$56,0)+IF(O11=6,P11*$AM$57,0)+IF(O11=7,P11*$AM$58,0)+IF(O11=8,P11*$AM$59,0)+IF(O11=9,P11*$AM$60,0)+IF(O11=10,P11*$AM$61,0) -> 0 | CP11: =IF(Q11=1,R11*$AM$52,0)+IF(Q11=2,R11*$AM$53,0)+IF(Q11=3,R11*$AM$54,0)+IF(Q11=4,R11*$AM$55,0)+IF(Q11=5,R11*$AM$56,0)+IF(Q11=6,R11*$AM$57,0)+IF(Q11=7,R11*$AM$58,0)+IF(Q11=8,R11*$AM$59,0)+IF(Q11=9,R11*$AM$60,0)+IF(Q11=10,R11*$AM$61,0) -> 0 | CQ11: =IF(S11=1,T11*$AM$52,0)+IF(S11=2,T11*$AM$53,0)+IF(S11=3,T11*$AM$54,0)+IF(S11=4,T11*$AM$55,0)+IF(S11=5,T11*$AM$56,0)+IF(S11=6,T11*$AM$57,0)+IF(S11=7,T11*$AM$58,0)+IF(S11=8,T11*$AM$59,0)+IF(S11=9,T11*$AM$60,0)+IF(S11=10,T11*$AM$61,0) -> 0 | CR11: =IF(U11=1,V11*$AM$52,0)+IF(U11=2,V11*$AM$53,0)+IF(U11=3,V11*$AM$54,0)+IF(U11=4,V11*$AM$55,0)+IF(U11=5,V11*$AM$56,0)+IF(U11=6,V11*$AM$57,0)+IF(U11=7,V11*$AM$58,0)+IF(U11=8,V11*$AM$59,0)+IF(U11=9,V11*$AM$60,0)+IF(U11=10,V11*$AM$61,0) -> 0 | CS11: =IF(W11=1,X11*$AM$52,0)+IF(W11=2,X11*$AM$53,0)+IF(W11=3,X11*$AM$54,0)+IF(W11=4,X11*$AM$55,0)+IF(W11=5,X11*$AM$56,0)+IF(W11=6,X11*$AM$57,0)+IF(W11=7,X11*$AM$58,0)+IF(W11=8,X11*$AM$59,0)+IF(W11=9,X11*$AM$60,0)+IF(W11=10,X11*$AM$61,0) -> 0 | CT11: =IF(Y11=1,Z11*$AM$52,0)+IF(Y11=2,Z11*$AM$53,0)+IF(Y11=3,Z11*$AM$54,0)+IF(Y11=4,Z11*$AM$55,0)+IF(Y11=5,Z11*$AM$56,0)+IF(Y11=6,Z11*$AM$57,0)+IF(Y11=7,Z11*$AM$58,0)+IF(Y11=8,Z11*$AM$59,0)+IF(Y11=9,Z11*$AM$60,0)+IF(Y11=10,Z11*$AM$61,0) -> 0 | CU11: =IF(AA11=1,AB11*$AM$52,0)+IF(AA11=2,AB11*$AM$53,0)+IF(AA11=3,AB11*$AM$54,0)+IF(AA11=4,AB11*$AM$55,0)+IF(AA11=5,AB11*$AM$56,0)+IF(AA11=6,AB11*$AM$57,0)+IF(AA11=7,AB11*$AM$58,0)+IF(AA11=8,AB11*$AM$59,0)+IF(AA11=9,AB11*$AM$60,0)+IF(AA11=10,AB11*$AM$61,0) -> 0 | CV11: =D11 -> 0 | CW11: =SUM(CO11:CV11)*BG11 -> 0
O12: 9 | Q12: 10 | S12: 1 | T12: =K12 -> 0 | U12: 2 | W12: 3 | Y12: 4 | AA12: 5 | AC12: =IF(BG12=0,0,SUM(BD12:BE12)/BG12) -> 0 | AD12: =(D12*F12/324)*(1+K$71)+AV12 -> 0 | AE12: =IF(D12=0,0,AF12/D12) -> 0 | AF12: =SUM(BW12)*(1+M$64+Summary!P$64) -> 0 | AG12: =D12/AD12 -> #DIV/0! | AH12: =AF12*G12 -> 0 | AO12: =IF(O12=1,P12*$T$52,0)+IF(O12=2,P12*$T$53,0)+IF(O12=3,P12*$T$54,0)+IF(O12=4,P12*$T$55,0)+IF(O12=5,P12*$T$56,0)+IF(O12=6,P12*$T$57,0)+IF(O12=7,P12*$T$58,0)+IF(O12=8,P12*$T$59,0)+IF(O12=9,P12*$T$60,0)+IF(O12=10,P12*$T$61,0) -> 0 | AP12: =IF(Q12=1,R12*$T$52,0)+IF(Q12=2,R12*$T$53,0)+IF(Q12=3,R12*$T$54,0)+IF(Q12=4,R12*$T$55,0)+IF(Q12=5,R12*$T$56,0)+IF(Q12=6,R12*$T$57,0)+IF(Q12=7,R12*$T$58,0)+IF(Q12=8,R12*$T$59,0)+IF(Q12=9,R12*$T$60,0)+IF(Q12=10,R12*$T$61,0) -> 0 | AQ12: =IF(S12=1,T12*$T$52,0)+IF(S12=2,T12*$T$53,0)+IF(S12=3,T12*$T$54,0)+IF(S12=4,T12*$T$55,0)+IF(S12=5,T12*$T$56,0)+IF(S12=6,T12*$T$57,0)+IF(S12=7,T12*$T$58,0)+IF(S12=8,T12*$T$59,0)+IF(S12=9,T12*$T$60,0)+IF(S12=10,T12*$T$61,0) -> 0 | AR12: =IF(U12=1,V12*$T$52,0)+IF(U12=2,V12*$T$53,0)+IF(U12=3,V12*$T$54,0)+IF(U12=4,V12*$T$55,0)+IF(U12=5,V12*$T$56,0)+IF(U12=6,V12*$T$57,0)+IF(U12=7,V12*$T$58,0)+IF(U12=8,V12*$T$59,0)+IF(U12=9,V12*$T$60,0)+IF(U12=10,V12*$T$61,0) -> 0 | AS12: =IF(W12=1,X12*$T$52,0)+IF(W12=2,X12*$T$53,0)+IF(W12=3,X12*$T$54,0)+IF(W12=4,X12*$T$55,0)+IF(W12=5,X12*$T$56,0)+IF(W12=6,X12*$T$57,0)+IF(W12=7,X12*$T$58,0)+IF(W12=8,X12*$T$59,0)+IF(W12=9,X12*$T$60,0)+IF(W12=10,X12*$T$61,0) -> 0 | AT12: =IF(Y12=1,Z12*$T$52,0)+IF(Y12=2,Z12*$T$53,0)+IF(Y12=3,Z12*$T$54,0)+IF(Y12=4,Z12*$T$55,0)+IF(Y12=5,Z12*$T$56,0)+IF(Y12=6,Z12*$T$57,0)+IF(Y12=7,Z12*$T$58,0)+IF(Y12=8,Z12*$T$59,0)+IF(Y12=9,Z12*$T$60,0)+IF(Y12=10,Z12*$T$61,0) -> 0 | AU12: =IF(AA12=1,AB12*$T$52,0)+IF(AA12=2,AB12*$T$53,0)+IF(AA12=3,AB12*$T$54,0)+IF(AA12=4,AB12*$T$55,0)+IF(AA12=5,AB12*$T$56,0)+IF(AA12=6,AB12*$T$57,0)+IF(AA12=7,AB12*$T$58,0)+IF(AA12=8,AB12*$T$59,0)+IF(AA12=9,AB12*$T$60,0)+IF(AA12=10,AB12*$T$61,0) -> 0 | AV12: =SUM(AO12:AU12) -> 0 | AW12: =ROUNDUP(IF(O12=1,P12*$P$52,0)+IF(O12=2,P12*$P$53,0)+IF(O12=3,P12*$P$54,0)+IF(O12=4,P12*$P$55,0)+IF(O12=5,P12*$P$56,0)+IF(O12=6,P12*$P$57,0)+IF(O12=7,P12*$P$58,0)+IF(O12=8,P12*$P$59,0)+IF(O12=9,P12*$P$60,0)+IF(O12=10,P12*$P$61,0),0)*BG12 -> 0 | AX12: =ROUNDUP(IF(Q12=1,R12*$P$52,0)+IF(Q12=2,R12*$P$53,0)+IF(Q12=3,R12*$P$54,0)+IF(Q12=4,R12*$P$55,0)+IF(Q12=5,R12*$P$56,0)+IF(Q12=6,R12*$P$57,0)+IF(Q12=7,R12*$P$58,0)+IF(Q12=8,R12*$P$59,0)+IF(Q12=9,R12*$P$60,0)+IF(Q12=10,R12*$P$61,0),0) -> 0 | AY12: =ROUNDUP(IF(S12=1,T12*$P$52,0)+IF(S12=2,T12*$P$53,0)+IF(S12=3,T12*$P$54,0)+IF(S12=4,T12*$P$55,0)+IF(S12=5,T12*$P$56,0)+IF(S12=6,T12*$P$57,0)+IF(S12=7,T12*$P$58,0)+IF(S12=8,T12*$P$59,0)+IF(S12=9,T12*$P$60,0)+IF(S12=10,T12*$P$61,0),0) -> 0 | AZ12: =ROUNDUP(IF(U12=1,V12*$P$52,0)+IF(U12=2,V12*$P$53,0)+IF(U12=3,V12*$P$54,0)+IF(U12=4,V12*$P$55,0)+IF(U12=5,V12*$P$56,0)+IF(U12=6,V12*$P$57,0)+IF(U12=7,V12*$P$58,0)+IF(U12=8,V12*$P$59,0)+IF(U12=9,V12*$P$60,0)+IF(U12=10,V12*$P$61,0),0) -> 0 | BA12: =ROUNDUP(IF(W12=1,X12*$P$52,0)+IF(W12=2,X12*$P$53,0)+IF(W12=3,X12*$P$54,0)+IF(W12=4,X12*$P$55,0)+IF(W12=5,X12*$P$56,0)+IF(W12=6,X12*$P$57,0)+IF(W12=7,X12*$P$58,0)+IF(W12=8,X12*$P$59,0)+IF(W12=9,X12*$P$60,0)+IF(W12=10,X12*$P$61,0),0) -> 0 | BB12: =ROUNDUP(IF(Y12=1,Z12*$P$52,0)+IF(Y12=2,Z12*$P$53,0)+IF(Y12=3,Z12*$P$54,0)+IF(Y12=4,Z12*$P$55,0)+IF(Y12=5,Z12*$P$56,0)+IF(Y12=6,Z12*$P$57,0)+IF(Y12=7,Z12*$P$58,0)+IF(Y12=8,Z12*$P$59,0)+IF(Y12=9,Z12*$P$60,0)+IF(Y12=10,Z12*$P$61,0),0) -> 0 | BC12: =ROUNDUP(IF(AA12=1,AB12*$P$52,0)+IF(AA12=2,AB12*$P$53,0)+IF(AA12=3,AB12*$P$54,0)+IF(AA12=4,AB12*$P$55,0)+IF(AA12=5,AB12*$P$56,0)+IF(AA12=6,AB12*$P$57,0)+IF(AA12=7,AB12*$P$58,0)+IF(AA12=8,AB12*$P$59,0)+IF(AA12=9,AB12*$P$60,0)+IF(AA12=10,AB12*$P$61,0),0) -> 0 | BD12: =SUM(AW12:BC12)*BG12 -> 0 | BE12: =IF(M12=0,0,(M12/12+M12/12)/(M12/12*M12/12)*D12*((L12/16*L12/16)*10.6870159))*(1+K$74)*BG12 -> 0 | BF12: =IF(N12="Y",D12*(1+K$75)*BG12,0) -> 0 | BG12: =G12 -> 0 | BH12: =IF(N12="y",D12,0) -> 0 | BI12: =IF($I12=1,$AD12,0)*BG12 -> 0 | BJ12: =IF($I12=2,$AD12,0)*BG12 -> 0 | BK12: =IF($I12=3,$AD12,0)*BG12 -> 0 | BL12: =IF($I12=4,$AD12,0)*BG12 -> 0 | BM12: =IF($I12=5,$AD12,0)*BG12 -> 0 | BN12: =IF($I12=6,$AD12,0)*BG12 -> 0 | BO12: =SUM(BI12:BN12) -> 0 | BP12: =IF(H12="N",0,D12)*BG12 -> 0 | BQ12: =K12*BG12 -> 0 | BR12: =IF(O12=1,D$52*P12/12,IF(O12=2,D$53*P12/12,IF(O12=3,D$54*P12/12,IF(O12=4,D$55*P12/12,IF(O12=5,D$56*P12/12,IF(O12=6,D$57*P12/12,IF(O12=7,D$58*P12/12,IF(O12=8,D$59*P12/12,IF(O12=9,D$60*P12/12,IF(O12=10,D$61*P12/12,0))))))*BG12)))) -> 0 | BS12: =IF(Q12=1,D$52*R12/12,IF(Q12=2,D$53*R12/12,IF(Q12=3,D$54*R12/12,IF(Q12=4,D$55*R12/12,IF(Q12=5,D$56*R12/12,IF(Q12=6,D$57*R12/12,IF(Q12=7,D$58*R12/12,IF(Q12=8,D$59*R12/12,IF(Q12=9,D$60*R12/12,IF(Q12=10,D$61*R12/12,0))))))*BG12)))) -> 0 | BT12: =D12*BG12 -> 0 | BU12: =D12*J12/324*(1+K$77)*BG12 -> 0 | BV12: =AC12*BG12 -> 0 | BW12: =IF(BG12=0,0,SUM(BX12:CM12)/BG12) -> 0 | BX12: =(BI12*Pricing!F$2+BJ12*Pricing!G$2+BK12*Pricing!H$2+BL12*Pricing!I$2+BM12*Pricing!J$2+BN12*Pricing!K$2)*IF(AC$63="N",(1+AE$63),1) -> 0 | BY12: =AC12*G$74*IF(AC$63="n",1+AE$63,1)*BG12 -> 0 | BZ12: =IF(I$83=0,0,D12*(SUM(L$83:M$86)+L$88)/I$83*BG12) -> 0 | CA12: =IF(I$83=0,0,D12*(SUM(O$83:P$86)+O$88)/I$83*BG12) -> 0 | CB12: =BR12+BS12*E$87 -> 0 | CD12: =BD12/2000*E$89 -> 0 | CE12: =IF(D$49=0,0,SUM(O$92:P$96)/D$49*D12)*BG12 -> 0 | CF12: =IF(D$49=0,0,SUM(AF$72:AF$99)/D$49*D12*BG12) -> 0 | CG12: =IF(D$49=0,0,SUM(O$98:P$103)/D$49*D12)*BG12 -> 0 | CH12: =IF(D$49=0,0,SUM(O$105:O$111)/D$49)*D12*BG12 -> 0 | CI12: =IF(D$49=0,0,SUM(AF$100:AF$111)/D$49*D12*BG12) -> 0 | CJ12: =IF(J$76>0,J$76/D$49*D12*G12,BP12*(G$76*(1+AE$63))) -> 0 | CK12: =IF(L$78=0,0,O$78/L$78)*AW12+IF(L$79=0,0,O$79/L$79)*BC12+IF(L$80=0,0,O$80/L$80)*BC12 -> 0 | CL12: =BF12*G$75*IF(AC$63="Y",1,1+AE$63) -> 0 | CM12: =BU12*G$77*IF(AC$63="Y",1,1+AE$63) -> 0 | CO12: =IF(O12=1,P12*$AM$52,0)+IF(O12=2,P12*$AM$53,0)+IF(O12=3,P12*$AM$54,0)+IF(O12=4,P12*$AM$55,0)+IF(O12=5,P12*$AM$56,0)+IF(O12=6,P12*$AM$57,0)+IF(O12=7,P12*$AM$58,0)+IF(O12=8,P12*$AM$59,0)+IF(O12=9,P12*$AM$60,0)+IF(O12=10,P12*$AM$61,0) -> 0 | CP12: =IF(Q12=1,R12*$AM$52,0)+IF(Q12=2,R12*$AM$53,0)+IF(Q12=3,R12*$AM$54,0)+IF(Q12=4,R12*$AM$55,0)+IF(Q12=5,R12*$AM$56,0)+IF(Q12=6,R12*$AM$57,0)+IF(Q12=7,R12*$AM$58,0)+IF(Q12=8,R12*$AM$59,0)+IF(Q12=9,R12*$AM$60,0)+IF(Q12=10,R12*$AM$61,0) -> 0 | CQ12: =IF(S12=1,T12*$AM$52,0)+IF(S12=2,T12*$AM$53,0)+IF(S12=3,T12*$AM$54,0)+IF(S12=4,T12*$AM$55,0)+IF(S12=5,T12*$AM$56,0)+IF(S12=6,T12*$AM$57,0)+IF(S12=7,T12*$AM$58,0)+IF(S12=8,T12*$AM$59,0)+IF(S12=9,T12*$AM$60,0)+IF(S12=10,T12*$AM$61,0) -> 0 | CR12: =IF(U12=1,V12*$AM$52,0)+IF(U12=2,V12*$AM$53,0)+IF(U12=3,V12*$AM$54,0)+IF(U12=4,V12*$AM$55,0)+IF(U12=5,V12*$AM$56,0)+IF(U12=6,V12*$AM$57,0)+IF(U12=7,V12*$AM$58,0)+IF(U12=8,V12*$AM$59,0)+IF(U12=9,V12*$AM$60,0)+IF(U12=10,V12*$AM$61,0) -> 0 | CS12: =IF(W12=1,X12*$AM$52,0)+IF(W12=2,X12*$AM$53,0)+IF(W12=3,X12*$AM$54,0)+IF(W12=4,X12*$AM$55,0)+IF(W12=5,X12*$AM$56,0)+IF(W12=6,X12*$AM$57,0)+IF(W12=7,X12*$AM$58,0)+IF(W12=8,X12*$AM$59,0)+IF(W12=9,X12*$AM$60,0)+IF(W12=10,X12*$AM$61,0) -> 0 | CT12: =IF(Y12=1,Z12*$AM$52,0)+IF(Y12=2,Z12*$AM$53,0)+IF(Y12=3,Z12*$AM$54,0)+IF(Y12=4,Z12*$AM$55,0)+IF(Y12=5,Z12*$AM$56,0)+IF(Y12=6,Z12*$AM$57,0)+IF(Y12=7,Z12*$AM$58,0)+IF(Y12=8,Z12*$AM$59,0)+IF(Y12=9,Z12*$AM$60,0)+IF(Y12=10,Z12*$AM$61,0) -> 0 | CU12: =IF(AA12=1,AB12*$AM$52,0)+IF(AA12=2,AB12*$AM$53,0)+IF(AA12=3,AB12*$AM$54,0)+IF(AA12=4,AB12*$AM$55,0)+IF(AA12=5,AB12*$AM$56,0)+IF(AA12=6,AB12*$AM$57,0)+IF(AA12=7,AB12*$AM$58,0)+IF(AA12=8,AB12*$AM$59,0)+IF(AA12=9,AB12*$AM$60,0)+IF(AA12=10,AB12*$AM$61,0) -> 0 | CV12: =D12 -> 0 | CW12: =SUM(CO12:CV12)*BG12 -> 0
O13: 9 | Q13: 10 | S13: 1 | T13: =K13 -> 0 | U13: 2 | W13: 3 | Y13: 4 | AA13: 5 | AC13: =IF(BG13=0,0,SUM(BD13:BE13)/BG13) -> 0 | AD13: =(D13*F13/324)*(1+K$71)+AV13 -> 0 | AE13: =IF(D13=0,0,AF13/D13) -> 0 | AF13: =SUM(BW13)*(1+M$64+Summary!P$64) -> 0 | AG13: =D13/AD13 -> #DIV/0! | AH13: =AF13*G13 -> 0 | AO13: =IF(O13=1,P13*$T$52,0)+IF(O13=2,P13*$T$53,0)+IF(O13=3,P13*$T$54,0)+IF(O13=4,P13*$T$55,0)+IF(O13=5,P13*$T$56,0)+IF(O13=6,P13*$T$57,0)+IF(O13=7,P13*$T$58,0)+IF(O13=8,P13*$T$59,0)+IF(O13=9,P13*$T$60,0)+IF(O13=10,P13*$T$61,0) -> 0 | AP13: =IF(Q13=1,R13*$T$52,0)+IF(Q13=2,R13*$T$53,0)+IF(Q13=3,R13*$T$54,0)+IF(Q13=4,R13*$T$55,0)+IF(Q13=5,R13*$T$56,0)+IF(Q13=6,R13*$T$57,0)+IF(Q13=7,R13*$T$58,0)+IF(Q13=8,R13*$T$59,0)+IF(Q13=9,R13*$T$60,0)+IF(Q13=10,R13*$T$61,0) -> 0 | AQ13: =IF(S13=1,T13*$T$52,0)+IF(S13=2,T13*$T$53,0)+IF(S13=3,T13*$T$54,0)+IF(S13=4,T13*$T$55,0)+IF(S13=5,T13*$T$56,0)+IF(S13=6,T13*$T$57,0)+IF(S13=7,T13*$T$58,0)+IF(S13=8,T13*$T$59,0)+IF(S13=9,T13*$T$60,0)+IF(S13=10,T13*$T$61,0) -> 0 | AR13: =IF(U13=1,V13*$T$52,0)+IF(U13=2,V13*$T$53,0)+IF(U13=3,V13*$T$54,0)+IF(U13=4,V13*$T$55,0)+IF(U13=5,V13*$T$56,0)+IF(U13=6,V13*$T$57,0)+IF(U13=7,V13*$T$58,0)+IF(U13=8,V13*$T$59,0)+IF(U13=9,V13*$T$60,0)+IF(U13=10,V13*$T$61,0) -> 0 | AS13: =IF(W13=1,X13*$T$52,0)+IF(W13=2,X13*$T$53,0)+IF(W13=3,X13*$T$54,0)+IF(W13=4,X13*$T$55,0)+IF(W13=5,X13*$T$56,0)+IF(W13=6,X13*$T$57,0)+IF(W13=7,X13*$T$58,0)+IF(W13=8,X13*$T$59,0)+IF(W13=9,X13*$T$60,0)+IF(W13=10,X13*$T$61,0) -> 0 | AT13: =IF(Y13=1,Z13*$T$52,0)+IF(Y13=2,Z13*$T$53,0)+IF(Y13=3,Z13*$T$54,0)+IF(Y13=4,Z13*$T$55,0)+IF(Y13=5,Z13*$T$56,0)+IF(Y13=6,Z13*$T$57,0)+IF(Y13=7,Z13*$T$58,0)+IF(Y13=8,Z13*$T$59,0)+IF(Y13=9,Z13*$T$60,0)+IF(Y13=10,Z13*$T$61,0) -> 0 | AU13: =IF(AA13=1,AB13*$T$52,0)+IF(AA13=2,AB13*$T$53,0)+IF(AA13=3,AB13*$T$54,0)+IF(AA13=4,AB13*$T$55,0)+IF(AA13=5,AB13*$T$56,0)+IF(AA13=6,AB13*$T$57,0)+IF(AA13=7,AB13*$T$58,0)+IF(AA13=8,AB13*$T$59,0)+IF(AA13=9,AB13*$T$60,0)+IF(AA13=10,AB13*$T$61,0) -> 0 | AV13: =SUM(AO13:AU13) -> 0 | AW13: =ROUNDUP(IF(O13=1,P13*$P$52,0)+IF(O13=2,P13*$P$53,0)+IF(O13=3,P13*$P$54,0)+IF(O13=4,P13*$P$55,0)+IF(O13=5,P13*$P$56,0)+IF(O13=6,P13*$P$57,0)+IF(O13=7,P13*$P$58,0)+IF(O13=8,P13*$P$59,0)+IF(O13=9,P13*$P$60,0)+IF(O13=10,P13*$P$61,0),0)*BG13 -> 0 | AX13: =ROUNDUP(IF(Q13=1,R13*$P$52,0)+IF(Q13=2,R13*$P$53,0)+IF(Q13=3,R13*$P$54,0)+IF(Q13=4,R13*$P$55,0)+IF(Q13=5,R13*$P$56,0)+IF(Q13=6,R13*$P$57,0)+IF(Q13=7,R13*$P$58,0)+IF(Q13=8,R13*$P$59,0)+IF(Q13=9,R13*$P$60,0)+IF(Q13=10,R13*$P$61,0),0) -> 0 | AY13: =ROUNDUP(IF(S13=1,T13*$P$52,0)+IF(S13=2,T13*$P$53,0)+IF(S13=3,T13*$P$54,0)+IF(S13=4,T13*$P$55,0)+IF(S13=5,T13*$P$56,0)+IF(S13=6,T13*$P$57,0)+IF(S13=7,T13*$P$58,0)+IF(S13=8,T13*$P$59,0)+IF(S13=9,T13*$P$60,0)+IF(S13=10,T13*$P$61,0),0) -> 0 | AZ13: =ROUNDUP(IF(U13=1,V13*$P$52,0)+IF(U13=2,V13*$P$53,0)+IF(U13=3,V13*$P$54,0)+IF(U13=4,V13*$P$55,0)+IF(U13=5,V13*$P$56,0)+IF(U13=6,V13*$P$57,0)+IF(U13=7,V13*$P$58,0)+IF(U13=8,V13*$P$59,0)+IF(U13=9,V13*$P$60,0)+IF(U13=10,V13*$P$61,0),0) -> 0 | BA13: =ROUNDUP(IF(W13=1,X13*$P$52,0)+IF(W13=2,X13*$P$53,0)+IF(W13=3,X13*$P$54,0)+IF(W13=4,X13*$P$55,0)+IF(W13=5,X13*$P$56,0)+IF(W13=6,X13*$P$57,0)+IF(W13=7,X13*$P$58,0)+IF(W13=8,X13*$P$59,0)+IF(W13=9,X13*$P$60,0)+IF(W13=10,X13*$P$61,0),0) -> 0 | BB13: =ROUNDUP(IF(Y13=1,Z13*$P$52,0)+IF(Y13=2,Z13*$P$53,0)+IF(Y13=3,Z13*$P$54,0)+IF(Y13=4,Z13*$P$55,0)+IF(Y13=5,Z13*$P$56,0)+IF(Y13=6,Z13*$P$57,0)+IF(Y13=7,Z13*$P$58,0)+IF(Y13=8,Z13*$P$59,0)+IF(Y13=9,Z13*$P$60,0)+IF(Y13=10,Z13*$P$61,0),0) -> 0 | BC13: =ROUNDUP(IF(AA13=1,AB13*$P$52,0)+IF(AA13=2,AB13*$P$53,0)+IF(AA13=3,AB13*$P$54,0)+IF(AA13=4,AB13*$P$55,0)+IF(AA13=5,AB13*$P$56,0)+IF(AA13=6,AB13*$P$57,0)+IF(AA13=7,AB13*$P$58,0)+IF(AA13=8,AB13*$P$59,0)+IF(AA13=9,AB13*$P$60,0)+IF(AA13=10,AB13*$P$61,0),0) -> 0 | BD13: =SUM(AW13:BC13)*BG13 -> 0 | BE13: =IF(M13=0,0,(M13/12+M13/12)/(M13/12*M13/12)*D13*((L13/16*L13/16)*10.6870159))*(1+K$74)*BG13 -> 0 | BF13: =IF(N13="Y",D13*(1+K$75)*BG13,0) -> 0 | BG13: =G13 -> 0 | BH13: =IF(N13="y",D13,0) -> 0 | BI13: =IF($I13=1,$AD13,0)*BG13 -> 0 | BJ13: =IF($I13=2,$AD13,0)*BG13 -> 0 | BK13: =IF($I13=3,$AD13,0)*BG13 -> 0 | BL13: =IF($I13=4,$AD13,0)*BG13 -> 0 | BM13: =IF($I13=5,$AD13,0)*BG13 -> 0 | BN13: =IF($I13=6,$AD13,0)*BG13 -> 0 | BO13: =SUM(BI13:BN13) -> 0 | BP13: =IF(H13="N",0,D13)*BG13 -> 0 | BQ13: =K13*BG13 -> 0 | BR13: =IF(O13=1,D$52*P13/12,IF(O13=2,D$53*P13/12,IF(O13=3,D$54*P13/12,IF(O13=4,D$55*P13/12,IF(O13=5,D$56*P13/12,IF(O13=6,D$57*P13/12,IF(O13=7,D$58*P13/12,IF(O13=8,D$59*P13/12,IF(O13=9,D$60*P13/12,IF(O13=10,D$61*P13/12,0))))))*BG13)))) -> 0 | BS13: =IF(Q13=1,D$52*R13/12,IF(Q13=2,D$53*R13/12,IF(Q13=3,D$54*R13/12,IF(Q13=4,D$55*R13/12,IF(Q13=5,D$56*R13/12,IF(Q13=6,D$57*R13/12,IF(Q13=7,D$58*R13/12,IF(Q13=8,D$59*R13/12,IF(Q13=9,D$60*R13/12,IF(Q13=10,D$61*R13/12,0))))))*BG13)))) -> 0 | BT13: =D13*BG13 -> 0 | BU13: =D13*J13/324*(1+K$77)*BG13 -> 0 | BV13: =AC13*BG13 -> 0 | BW13: =IF(BG13=0,0,SUM(BX13:CM13)/BG13) -> 0 | BX13: =(BI13*Pricing!F$2+BJ13*Pricing!G$2+BK13*Pricing!H$2+BL13*Pricing!I$2+BM13*Pricing!J$2+BN13*Pricing!K$2)*IF(AC$63="N",(1+AE$63),1) -> 0 | BY13: =AC13*G$74*IF(AC$63="n",1+AE$63,1)*BG13 -> 0 | BZ13: =IF(I$83=0,0,D13*(SUM(L$83:M$86)+L$88)/I$83*BG13) -> 0 | CA13: =IF(I$83=0,0,D13*(SUM(O$83:P$86)+O$88)/I$83*BG13) -> 0 | CB13: =BR13+BS13*E$87 -> 0 | CD13: =BD13/2000*E$89 -> 0 | CE13: =IF(D$49=0,0,SUM(O$92:P$96)/D$49*D13)*BG13 -> 0 | CF13: =IF(D$49=0,0,SUM(AF$72:AF$99)/D$49*D13*BG13) -> 0 | CG13: =IF(D$49=0,0,SUM(O$98:P$103)/D$49*D13)*BG13 -> 0 | CH13: =IF(D$49=0,0,SUM(O$105:O$111)/D$49)*D13*BG13 -> 0 | CI13: =IF(D$49=0,0,SUM(AF$100:AF$111)/D$49*D13*BG13) -> 0 | CJ13: =IF(J$76>0,J$76/D$49*D13*G13,BP13*(G$76*(1+AE$63))) -> 0 | CK13: =IF(L$78=0,0,O$78/L$78)*AW13+IF(L$79=0,0,O$79/L$79)*BC13+IF(L$80=0,0,O$80/L$80)*BC13 -> 0 | CL13: =BF13*G$75*IF(AC$63="Y",1,1+AE$63) -> 0 | CM13: =BU13*G$77*IF(AC$63="Y",1,1+AE$63) -> 0 | CO13: =IF(O13=1,P13*$AM$52,0)+IF(O13=2,P13*$AM$53,0)+IF(O13=3,P13*$AM$54,0)+IF(O13=4,P13*$AM$55,0)+IF(O13=5,P13*$AM$56,0)+IF(O13=6,P13*$AM$57,0)+IF(O13=7,P13*$AM$58,0)+IF(O13=8,P13*$AM$59,0)+IF(O13=9,P13*$AM$60,0)+IF(O13=10,P13*$AM$61,0) -> 0 | CP13: =IF(Q13=1,R13*$AM$52,0)+IF(Q13=2,R13*$AM$53,0)+IF(Q13=3,R13*$AM$54,0)+IF(Q13=4,R13*$AM$55,0)+IF(Q13=5,R13*$AM$56,0)+IF(Q13=6,R13*$AM$57,0)+IF(Q13=7,R13*$AM$58,0)+IF(Q13=8,R13*$AM$59,0)+IF(Q13=9,R13*$AM$60,0)+IF(Q13=10,R13*$AM$61,0) -> 0 | CQ13: =IF(S13=1,T13*$AM$52,0)+IF(S13=2,T13*$AM$53,0)+IF(S13=3,T13*$AM$54,0)+IF(S13=4,T13*$AM$55,0)+IF(S13=5,T13*$AM$56,0)+IF(S13=6,T13*$AM$57,0)+IF(S13=7,T13*$AM$58,0)+IF(S13=8,T13*$AM$59,0)+IF(S13=9,T13*$AM$60,0)+IF(S13=10,T13*$AM$61,0) -> 0 | CR13: =IF(U13=1,V13*$AM$52,0)+IF(U13=2,V13*$AM$53,0)+IF(U13=3,V13*$AM$54,0)+IF(U13=4,V13*$AM$55,0)+IF(U13=5,V13*$AM$56,0)+IF(U13=6,V13*$AM$57,0)+IF(U13=7,V13*$AM$58,0)+IF(U13=8,V13*$AM$59,0)+IF(U13=9,V13*$AM$60,0)+IF(U13=10,V13*$AM$61,0) -> 0 | CS13: =IF(W13=1,X13*$AM$52,0)+IF(W13=2,X13*$AM$53,0)+IF(W13=3,X13*$AM$54,0)+IF(W13=4,X13*$AM$55,0)+IF(W13=5,X13*$AM$56,0)+IF(W13=6,X13*$AM$57,0)+IF(W13=7,X13*$AM$58,0)+IF(W13=8,X13*$AM$59,0)+IF(W13=9,X13*$AM$60,0)+IF(W13=10,X13*$AM$61,0) -> 0 | CT13: =IF(Y13=1,Z13*$AM$52,0)+IF(Y13=2,Z13*$AM$53,0)+IF(Y13=3,Z13*$AM$54,0)+IF(Y13=4,Z13*$AM$55,0)+IF(Y13=5,Z13*$AM$56,0)+IF(Y13=6,Z13*$AM$57,0)+IF(Y13=7,Z13*$AM$58,0)+IF(Y13=8,Z13*$AM$59,0)+IF(Y13=9,Z13*$AM$60,0)+IF(Y13=10,Z13*$AM$61,0) -> 0 | CU13: =IF(AA13=1,AB13*$AM$52,0)+IF(AA13=2,AB13*$AM$53,0)+IF(AA13=3,AB13*$AM$54,0)+IF(AA13=4,AB13*$AM$55,0)+IF(AA13=5,AB13*$AM$56,0)+IF(AA13=6,AB13*$AM$57,0)+IF(AA13=7,AB13*$AM$58,0)+IF(AA13=8,AB13*$AM$59,0)+IF(AA13=9,AB13*$AM$60,0)+IF(AA13=10,AB13*$AM$61,0) -> 0 | CV13: =D13 -> 0 | CW13: =SUM(CO13:CV13)*BG13 -> 0
O14: 9 | Q14: 10 | S14: 1 | T14: =K14 -> 0 | U14: 2 | W14: 3 | Y14: 4 | AA14: 5 | AC14: =IF(BG14=0,0,SUM(BD14:BE14)/BG14) -> 0 | AD14: =(D14*F14/324)*(1+K$71)+AV14 -> 0 | AE14: =IF(D14=0,0,AF14/D14) -> 0 | AF14: =SUM(BW14)*(1+M$64+Summary!P$64) -> 0 | AG14: =D14/AD14 -> #DIV/0! | AH14: =AF14*G14 -> 0 | AO14: =IF(O14=1,P14*$T$52,0)+IF(O14=2,P14*$T$53,0)+IF(O14=3,P14*$T$54,0)+IF(O14=4,P14*$T$55,0)+IF(O14=5,P14*$T$56,0)+IF(O14=6,P14*$T$57,0)+IF(O14=7,P14*$T$58,0)+IF(O14=8,P14*$T$59,0)+IF(O14=9,P14*$T$60,0)+IF(O14=10,P14*$T$61,0) -> 0 | AP14: =IF(Q14=1,R14*$T$52,0)+IF(Q14=2,R14*$T$53,0)+IF(Q14=3,R14*$T$54,0)+IF(Q14=4,R14*$T$55,0)+IF(Q14=5,R14*$T$56,0)+IF(Q14=6,R14*$T$57,0)+IF(Q14=7,R14*$T$58,0)+IF(Q14=8,R14*$T$59,0)+IF(Q14=9,R14*$T$60,0)+IF(Q14=10,R14*$T$61,0) -> 0 | AQ14: =IF(S14=1,T14*$T$52,0)+IF(S14=2,T14*$T$53,0)+IF(S14=3,T14*$T$54,0)+IF(S14=4,T14*$T$55,0)+IF(S14=5,T14*$T$56,0)+IF(S14=6,T14*$T$57,0)+IF(S14=7,T14*$T$58,0)+IF(S14=8,T14*$T$59,0)+IF(S14=9,T14*$T$60,0)+IF(S14=10,T14*$T$61,0) -> 0 | AR14: =IF(U14=1,V14*$T$52,0)+IF(U14=2,V14*$T$53,0)+IF(U14=3,V14*$T$54,0)+IF(U14=4,V14*$T$55,0)+IF(U14=5,V14*$T$56,0)+IF(U14=6,V14*$T$57,0)+IF(U14=7,V14*$T$58,0)+IF(U14=8,V14*$T$59,0)+IF(U14=9,V14*$T$60,0)+IF(U14=10,V14*$T$61,0) -> 0 | AS14: =IF(W14=1,X14*$T$52,0)+IF(W14=2,X14*$T$53,0)+IF(W14=3,X14*$T$54,0)+IF(W14=4,X14*$T$55,0)+IF(W14=5,X14*$T$56,0)+IF(W14=6,X14*$T$57,0)+IF(W14=7,X14*$T$58,0)+IF(W14=8,X14*$T$59,0)+IF(W14=9,X14*$T$60,0)+IF(W14=10,X14*$T$61,0) -> 0 | AT14: =IF(Y14=1,Z14*$T$52,0)+IF(Y14=2,Z14*$T$53,0)+IF(Y14=3,Z14*$T$54,0)+IF(Y14=4,Z14*$T$55,0)+IF(Y14=5,Z14*$T$56,0)+IF(Y14=6,Z14*$T$57,0)+IF(Y14=7,Z14*$T$58,0)+IF(Y14=8,Z14*$T$59,0)+IF(Y14=9,Z14*$T$60,0)+IF(Y14=10,Z14*$T$61,0) -> 0 | AU14: =IF(AA14=1,AB14*$T$52,0)+IF(AA14=2,AB14*$T$53,0)+IF(AA14=3,AB14*$T$54,0)+IF(AA14=4,AB14*$T$55,0)+IF(AA14=5,AB14*$T$56,0)+IF(AA14=6,AB14*$T$57,0)+IF(AA14=7,AB14*$T$58,0)+IF(AA14=8,AB14*$T$59,0)+IF(AA14=9,AB14*$T$60,0)+IF(AA14=10,AB14*$T$61,0) -> 0 | AV14: =SUM(AO14:AU14) -> 0 | AW14: =ROUNDUP(IF(O14=1,P14*$P$52,0)+IF(O14=2,P14*$P$53,0)+IF(O14=3,P14*$P$54,0)+IF(O14=4,P14*$P$55,0)+IF(O14=5,P14*$P$56,0)+IF(O14=6,P14*$P$57,0)+IF(O14=7,P14*$P$58,0)+IF(O14=8,P14*$P$59,0)+IF(O14=9,P14*$P$60,0)+IF(O14=10,P14*$P$61,0),0)*BG14 -> 0 | AX14: =ROUNDUP(IF(Q14=1,R14*$P$52,0)+IF(Q14=2,R14*$P$53,0)+IF(Q14=3,R14*$P$54,0)+IF(Q14=4,R14*$P$55,0)+IF(Q14=5,R14*$P$56,0)+IF(Q14=6,R14*$P$57,0)+IF(Q14=7,R14*$P$58,0)+IF(Q14=8,R14*$P$59,0)+IF(Q14=9,R14*$P$60,0)+IF(Q14=10,R14*$P$61,0),0) -> 0 | AY14: =ROUNDUP(IF(S14=1,T14*$P$52,0)+IF(S14=2,T14*$P$53,0)+IF(S14=3,T14*$P$54,0)+IF(S14=4,T14*$P$55,0)+IF(S14=5,T14*$P$56,0)+IF(S14=6,T14*$P$57,0)+IF(S14=7,T14*$P$58,0)+IF(S14=8,T14*$P$59,0)+IF(S14=9,T14*$P$60,0)+IF(S14=10,T14*$P$61,0),0) -> 0 | AZ14: =ROUNDUP(IF(U14=1,V14*$P$52,0)+IF(U14=2,V14*$P$53,0)+IF(U14=3,V14*$P$54,0)+IF(U14=4,V14*$P$55,0)+IF(U14=5,V14*$P$56,0)+IF(U14=6,V14*$P$57,0)+IF(U14=7,V14*$P$58,0)+IF(U14=8,V14*$P$59,0)+IF(U14=9,V14*$P$60,0)+IF(U14=10,V14*$P$61,0),0) -> 0 | BA14: =ROUNDUP(IF(W14=1,X14*$P$52,0)+IF(W14=2,X14*$P$53,0)+IF(W14=3,X14*$P$54,0)+IF(W14=4,X14*$P$55,0)+IF(W14=5,X14*$P$56,0)+IF(W14=6,X14*$P$57,0)+IF(W14=7,X14*$P$58,0)+IF(W14=8,X14*$P$59,0)+IF(W14=9,X14*$P$60,0)+IF(W14=10,X14*$P$61,0),0) -> 0 | BB14: =ROUNDUP(IF(Y14=1,Z14*$P$52,0)+IF(Y14=2,Z14*$P$53,0)+IF(Y14=3,Z14*$P$54,0)+IF(Y14=4,Z14*$P$55,0)+IF(Y14=5,Z14*$P$56,0)+IF(Y14=6,Z14*$P$57,0)+IF(Y14=7,Z14*$P$58,0)+IF(Y14=8,Z14*$P$59,0)+IF(Y14=9,Z14*$P$60,0)+IF(Y14=10,Z14*$P$61,0),0) -> 0 | BC14: =ROUNDUP(IF(AA14=1,AB14*$P$52,0)+IF(AA14=2,AB14*$P$53,0)+IF(AA14=3,AB14*$P$54,0)+IF(AA14=4,AB14*$P$55,0)+IF(AA14=5,AB14*$P$56,0)+IF(AA14=6,AB14*$P$57,0)+IF(AA14=7,AB14*$P$58,0)+IF(AA14=8,AB14*$P$59,0)+IF(AA14=9,AB14*$P$60,0)+IF(AA14=10,AB14*$P$61,0),0) -> 0 | BD14: =SUM(AW14:BC14)*BG14 -> 0 | BE14: =IF(M14=0,0,(M14/12+M14/12)/(M14/12*M14/12)*D14*((L14/16*L14/16)*10.6870159))*(1+K$74)*BG14 -> 0 | BF14: =IF(N14="Y",D14*(1+K$75)*BG14,0) -> 0 | BG14: =G14 -> 0 | BH14: =IF(N14="y",D14,0) -> 0 | BI14: =IF($I14=1,$AD14,0)*BG14 -> 0 | BJ14: =IF($I14=2,$AD14,0)*BG14 -> 0 | BK14: =IF($I14=3,$AD14,0)*BG14 -> 0 | BL14: =IF($I14=4,$AD14,0)*BG14 -> 0 | BM14: =IF($I14=5,$AD14,0)*BG14 -> 0 | BN14: =IF($I14=6,$AD14,0)*BG14 -> 0 | BO14: =SUM(BI14:BN14) -> 0 | BP14: =IF(H14="N",0,D14)*BG14 -> 0 | BQ14: =K14*BG14 -> 0 | BR14: =IF(O14=1,D$52*P14/12,IF(O14=2,D$53*P14/12,IF(O14=3,D$54*P14/12,IF(O14=4,D$55*P14/12,IF(O14=5,D$56*P14/12,IF(O14=6,D$57*P14/12,IF(O14=7,D$58*P14/12,IF(O14=8,D$59*P14/12,IF(O14=9,D$60*P14/12,IF(O14=10,D$61*P14/12,0))))))*BG14)))) -> 0 | BS14: =IF(Q14=1,D$52*R14/12,IF(Q14=2,D$53*R14/12,IF(Q14=3,D$54*R14/12,IF(Q14=4,D$55*R14/12,IF(Q14=5,D$56*R14/12,IF(Q14=6,D$57*R14/12,IF(Q14=7,D$58*R14/12,IF(Q14=8,D$59*R14/12,IF(Q14=9,D$60*R14/12,IF(Q14=10,D$61*R14/12,0))))))*BG14)))) -> 0 | BT14: =D14*BG14 -> 0 | BU14: =D14*J14/324*(1+K$77)*BG14 -> 0 | BV14: =AC14*BG14 -> 0 | BW14: =IF(BG14=0,0,SUM(BX14:CM14)/BG14) -> 0 | BX14: =(BI14*Pricing!F$2+BJ14*Pricing!G$2+BK14*Pricing!H$2+BL14*Pricing!I$2+BM14*Pricing!J$2+BN14*Pricing!K$2)*IF(AC$63="N",(1+AE$63),1) -> 0 | BY14: =AC14*G$74*IF(AC$63="n",1+AE$63,1)*BG14 -> 0 | BZ14: =IF(I$83=0,0,D14*(SUM(L$83:M$86)+L$88)/I$83*BG14) -> 0 | CA14: =IF(I$83=0,0,D14*(SUM(O$83:P$86)+O$88)/I$83*BG14) -> 0 | CB14: =BR14+BS14*E$87 -> 0 | CD14: =BD14/2000*E$89 -> 0 | CE14: =IF(D$49=0,0,SUM(O$92:P$96)/D$49*D14)*BG14 -> 0 | CF14: =IF(D$49=0,0,SUM(AF$72:AF$99)/D$49*D14*BG14) -> 0 | CG14: =IF(D$49=0,0,SUM(O$98:P$103)/D$49*D14)*BG14 -> 0 | CH14: =IF(D$49=0,0,SUM(O$105:O$111)/D$49)*D14*BG14 -> 0 | CI14: =IF(D$49=0,0,SUM(AF$100:AF$111)/D$49*D14*BG14) -> 0 | CJ14: =IF(J$76>0,J$76/D$49*D14*G14,BP14*(G$76*(1+AE$63))) -> 0 | CK14: =IF(L$78=0,0,O$78/L$78)*AW14+IF(L$79=0,0,O$79/L$79)*BC14+IF(L$80=0,0,O$80/L$80)*BC14 -> 0 | CL14: =BF14*G$75*IF(AC$63="Y",1,1+AE$63) -> 0 | CM14: =BU14*G$77*IF(AC$63="Y",1,1+AE$63) -> 0 | CO14: =IF(O14=1,P14*$AM$52,0)+IF(O14=2,P14*$AM$53,0)+IF(O14=3,P14*$AM$54,0)+IF(O14=4,P14*$AM$55,0)+IF(O14=5,P14*$AM$56,0)+IF(O14=6,P14*$AM$57,0)+IF(O14=7,P14*$AM$58,0)+IF(O14=8,P14*$AM$59,0)+IF(O14=9,P14*$AM$60,0)+IF(O14=10,P14*$AM$61,0) -> 0 | CP14: =IF(Q14=1,R14*$AM$52,0)+IF(Q14=2,R14*$AM$53,0)+IF(Q14=3,R14*$AM$54,0)+IF(Q14=4,R14*$AM$55,0)+IF(Q14=5,R14*$AM$56,0)+IF(Q14=6,R14*$AM$57,0)+IF(Q14=7,R14*$AM$58,0)+IF(Q14=8,R14*$AM$59,0)+IF(Q14=9,R14*$AM$60,0)+IF(Q14=10,R14*$AM$61,0) -> 0 | CQ14: =IF(S14=1,T14*$AM$52,0)+IF(S14=2,T14*$AM$53,0)+IF(S14=3,T14*$AM$54,0)+IF(S14=4,T14*$AM$55,0)+IF(S14=5,T14*$AM$56,0)+IF(S14=6,T14*$AM$57,0)+IF(S14=7,T14*$AM$58,0)+IF(S14=8,T14*$AM$59,0)+IF(S14=9,T14*$AM$60,0)+IF(S14=10,T14*$AM$61,0) -> 0 | CR14: =IF(U14=1,V14*$AM$52,0)+IF(U14=2,V14*$AM$53,0)+IF(U14=3,V14*$AM$54,0)+IF(U14=4,V14*$AM$55,0)+IF(U14=5,V14*$AM$56,0)+IF(U14=6,V14*$AM$57,0)+IF(U14=7,V14*$AM$58,0)+IF(U14=8,V14*$AM$59,0)+IF(U14=9,V14*$AM$60,0)+IF(U14=10,V14*$AM$61,0) -> 0 | CS14: =IF(W14=1,X14*$AM$52,0)+IF(W14=2,X14*$AM$53,0)+IF(W14=3,X14*$AM$54,0)+IF(W14=4,X14*$AM$55,0)+IF(W14=5,X14*$AM$56,0)+IF(W14=6,X14*$AM$57,0)+IF(W14=7,X14*$AM$58,0)+IF(W14=8,X14*$AM$59,0)+IF(W14=9,X14*$AM$60,0)+IF(W14=10,X14*$AM$61,0) -> 0 | CT14: =IF(Y14=1,Z14*$AM$52,0)+IF(Y14=2,Z14*$AM$53,0)+IF(Y14=3,Z14*$AM$54,0)+IF(Y14=4,Z14*$AM$55,0)+IF(Y14=5,Z14*$AM$56,0)+IF(Y14=6,Z14*$AM$57,0)+IF(Y14=7,Z14*$AM$58,0)+IF(Y14=8,Z14*$AM$59,0)+IF(Y14=9,Z14*$AM$60,0)+IF(Y14=10,Z14*$AM$61,0) -> 0 | CU14: =IF(AA14=1,AB14*$AM$52,0)+IF(AA14=2,AB14*$AM$53,0)+IF(AA14=3,AB14*$AM$54,0)+IF(AA14=4,AB14*$AM$55,0)+IF(AA14=5,AB14*$AM$56,0)+IF(AA14=6,AB14*$AM$57,0)+IF(AA14=7,AB14*$AM$58,0)+IF(AA14=8,AB14*$AM$59,0)+IF(AA14=9,AB14*$AM$60,0)+IF(AA14=10,AB14*$AM$61,0) -> 0 | CV14: =D14 -> 0 | CW14: =SUM(CO14:CV14)*BG14 -> 0
O15: 9 | Q15: 10 | S15: 1 | T15: =K15 -> 0 | U15: 2 | W15: 3 | Y15: 4 | AA15: 5 | AC15: =IF(BG15=0,0,SUM(BD15:BE15)/BG15) -> 0 | AD15: =(D15*F15/324)*(1+K$71)+AV15 -> 0 | AE15: =IF(D15=0,0,AF15/D15) -> 0 | AF15: =SUM(BW15)*(1+M$64+Summary!P$64) -> 0 | AG15: =D15/AD15 -> #DIV/0! | AH15: =AF15*G15 -> 0 | AO15: =IF(O15=1,P15*$T$52,0)+IF(O15=2,P15*$T$53,0)+IF(O15=3,P15*$T$54,0)+IF(O15=4,P15*$T$55,0)+IF(O15=5,P15*$T$56,0)+IF(O15=6,P15*$T$57,0)+IF(O15=7,P15*$T$58,0)+IF(O15=8,P15*$T$59,0)+IF(O15=9,P15*$T$60,0)+IF(O15=10,P15*$T$61,0) -> 0 | AP15: =IF(Q15=1,R14*$T$52,0)+IF(Q15=2,R14*$T$53,0)+IF(Q15=3,R14*$T$54,0)+IF(Q15=4,R14*$T$55,0)+IF(Q15=5,R14*$T$56,0)+IF(Q15=6,R14*$T$57,0)+IF(Q15=7,R14*$T$58,0)+IF(Q15=8,R14*$T$59,0)+IF(Q15=9,R14*$T$60,0)+IF(Q15=10,R14*$T$61,0) -> 0 | AQ15: =IF(S15=1,T15*$T$52,0)+IF(S15=2,T15*$T$53,0)+IF(S15=3,T15*$T$54,0)+IF(S15=4,T15*$T$55,0)+IF(S15=5,T15*$T$56,0)+IF(S15=6,T15*$T$57,0)+IF(S15=7,T15*$T$58,0)+IF(S15=8,T15*$T$59,0)+IF(S15=9,T15*$T$60,0)+IF(S15=10,T15*$T$61,0) -> 0 | AR15: =IF(U15=1,V15*$T$52,0)+IF(U15=2,V15*$T$53,0)+IF(U15=3,V15*$T$54,0)+IF(U15=4,V15*$T$55,0)+IF(U15=5,V15*$T$56,0)+IF(U15=6,V15*$T$57,0)+IF(U15=7,V15*$T$58,0)+IF(U15=8,V15*$T$59,0)+IF(U15=9,V15*$T$60,0)+IF(U15=10,V15*$T$61,0) -> 0 | AS15: =IF(W15=1,X15*$T$52,0)+IF(W15=2,X15*$T$53,0)+IF(W15=3,X15*$T$54,0)+IF(W15=4,X15*$T$55,0)+IF(W15=5,X15*$T$56,0)+IF(W15=6,X15*$T$57,0)+IF(W15=7,X15*$T$58,0)+IF(W15=8,X15*$T$59,0)+IF(W15=9,X15*$T$60,0)+IF(W15=10,X15*$T$61,0) -> 0 | AT15: =IF(Y15=1,Z15*$T$52,0)+IF(Y15=2,Z15*$T$53,0)+IF(Y15=3,Z15*$T$54,0)+IF(Y15=4,Z15*$T$55,0)+IF(Y15=5,Z15*$T$56,0)+IF(Y15=6,Z15*$T$57,0)+IF(Y15=7,Z15*$T$58,0)+IF(Y15=8,Z15*$T$59,0)+IF(Y15=9,Z15*$T$60,0)+IF(Y15=10,Z15*$T$61,0) -> 0 | AU15: =IF(AA15=1,AB15*$T$52,0)+IF(AA15=2,AB15*$T$53,0)+IF(AA15=3,AB15*$T$54,0)+IF(AA15=4,AB15*$T$55,0)+IF(AA15=5,AB15*$T$56,0)+IF(AA15=6,AB15*$T$57,0)+IF(AA15=7,AB15*$T$58,0)+IF(AA15=8,AB15*$T$59,0)+IF(AA15=9,AB15*$T$60,0)+IF(AA15=10,AB15*$T$61,0) -> 0 | AV15: =SUM(AO15:AU15) -> 0 | AW15: =ROUNDUP(IF(O15=1,P15*$P$52,0)+IF(O15=2,P15*$P$53,0)+IF(O15=3,P15*$P$54,0)+IF(O15=4,P15*$P$55,0)+IF(O15=5,P15*$P$56,0)+IF(O15=6,P15*$P$57,0)+IF(O15=7,P15*$P$58,0)+IF(O15=8,P15*$P$59,0)+IF(O15=9,P15*$P$60,0)+IF(O15=10,P15*$P$61,0),0)*BG15 -> 0 | AX15: =ROUNDUP(IF(Q15=1,R14*$P$52,0)+IF(Q15=2,R14*$P$53,0)+IF(Q15=3,R14*$P$54,0)+IF(Q15=4,R14*$P$55,0)+IF(Q15=5,R14*$P$56,0)+IF(Q15=6,R14*$P$57,0)+IF(Q15=7,R14*$P$58,0)+IF(Q15=8,R14*$P$59,0)+IF(Q15=9,R14*$P$60,0)+IF(Q15=10,R14*$P$61,0),0) -> 0 | AY15: =ROUNDUP(IF(S15=1,T15*$P$52,0)+IF(S15=2,T15*$P$53,0)+IF(S15=3,T15*$P$54,0)+IF(S15=4,T15*$P$55,0)+IF(S15=5,T15*$P$56,0)+IF(S15=6,T15*$P$57,0)+IF(S15=7,T15*$P$58,0)+IF(S15=8,T15*$P$59,0)+IF(S15=9,T15*$P$60,0)+IF(S15=10,T15*$P$61,0),0) -> 0 | AZ15: =ROUNDUP(IF(U15=1,V15*$P$52,0)+IF(U15=2,V15*$P$53,0)+IF(U15=3,V15*$P$54,0)+IF(U15=4,V15*$P$55,0)+IF(U15=5,V15*$P$56,0)+IF(U15=6,V15*$P$57,0)+IF(U15=7,V15*$P$58,0)+IF(U15=8,V15*$P$59,0)+IF(U15=9,V15*$P$60,0)+IF(U15=10,V15*$P$61,0),0) -> 0 | BA15: =ROUNDUP(IF(W15=1,X15*$P$52,0)+IF(W15=2,X15*$P$53,0)+IF(W15=3,X15*$P$54,0)+IF(W15=4,X15*$P$55,0)+IF(W15=5,X15*$P$56,0)+IF(W15=6,X15*$P$57,0)+IF(W15=7,X15*$P$58,0)+IF(W15=8,X15*$P$59,0)+IF(W15=9,X15*$P$60,0)+IF(W15=10,X15*$P$61,0),0) -> 0 | BB15: =ROUNDUP(IF(Y15=1,Z15*$P$52,0)+IF(Y15=2,Z15*$P$53,0)+IF(Y15=3,Z15*$P$54,0)+IF(Y15=4,Z15*$P$55,0)+IF(Y15=5,Z15*$P$56,0)+IF(Y15=6,Z15*$P$57,0)+IF(Y15=7,Z15*$P$58,0)+IF(Y15=8,Z15*$P$59,0)+IF(Y15=9,Z15*$P$60,0)+IF(Y15=10,Z15*$P$61,0),0) -> 0 | BC15: =ROUNDUP(IF(AA15=1,AB15*$P$52,0)+IF(AA15=2,AB15*$P$53,0)+IF(AA15=3,AB15*$P$54,0)+IF(AA15=4,AB15*$P$55,0)+IF(AA15=5,AB15*$P$56,0)+IF(AA15=6,AB15*$P$57,0)+IF(AA15=7,AB15*$P$58,0)+IF(AA15=8,AB15*$P$59,0)+IF(AA15=9,AB15*$P$60,0)+IF(AA15=10,AB15*$P$61,0),0) -> 0 | BD15: =SUM(AW15:BC15)*BG15 -> 0 | BE15: =IF(M15=0,0,(M15/12+M15/12)/(M15/12*M15/12)*D15*((L15/16*L15/16)*10.6870159))*(1+K$74)*BG15 -> 0 | BF15: =IF(N15="Y",D15*(1+K$75)*BG15,0) -> 0 | BG15: =G15 -> 0 | BH15: =IF(N15="y",D15,0) -> 0 | BI15: =IF($I15=1,$AD15,0)*BG15 -> 0 | BJ15: =IF($I15=2,$AD15,0)*BG15 -> 0 | BK15: =IF($I15=3,$AD15,0)*BG15 -> 0 | BL15: =IF($I15=4,$AD15,0)*BG15 -> 0 | BM15: =IF($I15=5,$AD15,0)*BG15 -> 0 | BN15: =IF($I15=6,$AD15,0)*BG15 -> 0 | BO15: =SUM(BI15:BN15) -> 0 | BP15: =IF(H15="N",0,D15)*BG15 -> 0 | BQ15: =K15*BG15 -> 0 | BR15: =IF(O15=1,D$52*P15/12,IF(O15=2,D$53*P15/12,IF(O15=3,D$54*P15/12,IF(O15=4,D$55*P15/12,IF(O15=5,D$56*P15/12,IF(O15=6,D$57*P15/12,IF(O15=7,D$58*P15/12,IF(O15=8,D$59*P15/12,IF(O15=9,D$60*P15/12,IF(O15=10,D$61*P15/12,0))))))*BG15)))) -> 0 | BS15: =IF(Q15=1,D$52*R14/12,IF(Q15=2,D$53*R14/12,IF(Q15=3,D$54*R14/12,IF(Q15=4,D$55*R14/12,IF(Q15=5,D$56*R14/12,IF(Q15=6,D$57*R14/12,IF(Q15=7,D$58*R14/12,IF(Q15=8,D$59*R14/12,IF(Q15=9,D$60*R14/12,IF(Q15=10,D$61*R14/12,0))))))*BG15)))) -> 0 | BT15: =D15*BG15 -> 0 | BU15: =D15*J15/324*(1+K$77)*BG15 -> 0 | BV15: =AC15*BG15 -> 0 | BW15: =IF(BG15=0,0,SUM(BX15:CM15)/BG15) -> 0 | BX15: =(BI15*Pricing!F$2+BJ15*Pricing!G$2+BK15*Pricing!H$2+BL15*Pricing!I$2+BM15*Pricing!J$2+BN15*Pricing!K$2)*IF(AC$63="N",(1+AE$63),1) -> 0 | BY15: =AC15*G$74*IF(AC$63="n",1+AE$63,1)*BG15 -> 0 | BZ15: =IF(I$83=0,0,D15*(SUM(L$83:M$86)+L$88)/I$83*BG15) -> 0 | CA15: =IF(I$83=0,0,D15*(SUM(O$83:P$86)+O$88)/I$83*BG15) -> 0 | CB15: =BR15+BS15*E$87 -> 0 | CD15: =BD15/2000*E$89 -> 0 | CE15: =IF(D$49=0,0,SUM(O$92:P$96)/D$49*D15)*BG15 -> 0 | CF15: =IF(D$49=0,0,SUM(AF$72:AF$99)/D$49*D15*BG15) -> 0 | CG15: =IF(D$49=0,0,SUM(O$98:P$103)/D$49*D15)*BG15 -> 0 | CH15: =IF(D$49=0,0,SUM(O$105:O$111)/D$49)*D15*BG15 -> 0 | CI15: =IF(D$49=0,0,SUM(AF$100:AF$111)/D$49*D15*BG15) -> 0 | CJ15: =IF(J$76>0,J$76/D$49*D15*G15,BP15*(G$76*(1+AE$63))) -> 0 | CK15: =IF(L$78=0,0,O$78/L$78)*AW15+IF(L$79=0,0,O$79/L$79)*BC15+IF(L$80=0,0,O$80/L$80)*BC15 -> 0 | CL15: =BF15*G$75*IF(AC$63="Y",1,1+AE$63) -> 0 | CM15: =BU15*G$77*IF(AC$63="Y",1,1+AE$63) -> 0 | CO15: =IF(O15=1,P15*$AM$52,0)+IF(O15=2,P15*$AM$53,0)+IF(O15=3,P15*$AM$54,0)+IF(O15=4,P15*$AM$55,0)+IF(O15=5,P15*$AM$56,0)+IF(O15=6,P15*$AM$57,0)+IF(O15=7,P15*$AM$58,0)+IF(O15=8,P15*$AM$59,0)+IF(O15=9,P15*$AM$60,0)+IF(O15=10,P15*$AM$61,0) -> 0 | CP15: =IF(Q15=1,R14*$AM$52,0)+IF(Q15=2,R14*$AM$53,0)+IF(Q15=3,R14*$AM$54,0)+IF(Q15=4,R14*$AM$55,0)+IF(Q15=5,R14*$AM$56,0)+IF(Q15=6,R14*$AM$57,0)+IF(Q15=7,R14*$AM$58,0)+IF(Q15=8,R14*$AM$59,0)+IF(Q15=9,R14*$AM$60,0)+IF(Q15=10,R14*$AM$61,0) -> 0 | CQ15: =IF(S15=1,T15*$AM$52,0)+IF(S15=2,T15*$AM$53,0)+IF(S15=3,T15*$AM$54,0)+IF(S15=4,T15*$AM$55,0)+IF(S15=5,T15*$AM$56,0)+IF(S15=6,T15*$AM$57,0)+IF(S15=7,T15*$AM$58,0)+IF(S15=8,T15*$AM$59,0)+IF(S15=9,T15*$AM$60,0)+IF(S15=10,T15*$AM$61,0) -> 0 | CR15: =IF(U15=1,V15*$AM$52,0)+IF(U15=2,V15*$AM$53,0)+IF(U15=3,V15*$AM$54,0)+IF(U15=4,V15*$AM$55,0)+IF(U15=5,V15*$AM$56,0)+IF(U15=6,V15*$AM$57,0)+IF(U15=7,V15*$AM$58,0)+IF(U15=8,V15*$AM$59,0)+IF(U15=9,V15*$AM$60,0)+IF(U15=10,V15*$AM$61,0) -> 0 | CS15: =IF(W15=1,X15*$AM$52,0)+IF(W15=2,X15*$AM$53,0)+IF(W15=3,X15*$AM$54,0)+IF(W15=4,X15*$AM$55,0)+IF(W15=5,X15*$AM$56,0)+IF(W15=6,X15*$AM$57,0)+IF(W15=7,X15*$AM$58,0)+IF(W15=8,X15*$AM$59,0)+IF(W15=9,X15*$AM$60,0)+IF(W15=10,X15*$AM$61,0) -> 0 | CT15: =IF(Y15=1,Z15*$AM$52,0)+IF(Y15=2,Z15*$AM$53,0)+IF(Y15=3,Z15*$AM$54,0)+IF(Y15=4,Z15*$AM$55,0)+IF(Y15=5,Z15*$AM$56,0)+IF(Y15=6,Z15*$AM$57,0)+IF(Y15=7,Z15*$AM$58,0)+IF(Y15=8,Z15*$AM$59,0)+IF(Y15=9,Z15*$AM$60,0)+IF(Y15=10,Z15*$AM$61,0) -> 0 | CU15: =IF(AA15=1,AB15*$AM$52,0)+IF(AA15=2,AB15*$AM$53,0)+IF(AA15=3,AB15*$AM$54,0)+IF(AA15=4,AB15*$AM$55,0)+IF(AA15=5,AB15*$AM$56,0)+IF(AA15=6,AB15*$AM$57,0)+IF(AA15=7,AB15*$AM$58,0)+IF(AA15=8,AB15*$AM$59,0)+IF(AA15=9,AB15*$AM$60,0)+IF(AA15=10,AB15*$AM$61,0) -> 0 | CV15: =D15 -> 0 | CW15: =SUM(CO15:CV15)*BG15 -> 0
O16: 9 | Q16: 10 | S16: 1 | T16: =K16 -> 0 | U16: 2 | W16: 3 | Y16: 4 | AA16: 5 | AC16: =IF(BG16=0,0,SUM(BD16:BE16)/BG16) -> 0 | AD16: =(D16*F16/324)*(1+K$71)+AV16 -> 0 | AE16: =IF(D16=0,0,AF16/D16) -> 0 | AF16: =SUM(BW16)*(1+M$64+Summary!P$64) -> 0 | AG16: =D16/AD16 -> #DIV/0! | AH16: =AF16*G16 -> 0 | AO16: =IF(O16=1,P16*$T$52,0)+IF(O16=2,P16*$T$53,0)+IF(O16=3,P16*$T$54,0)+IF(O16=4,P16*$T$55,0)+IF(O16=5,P16*$T$56,0)+IF(O16=6,P16*$T$57,0)+IF(O16=7,P16*$T$58,0)+IF(O16=8,P16*$T$59,0)+IF(O16=9,P16*$T$60,0)+IF(O16=10,P16*$T$61,0) -> 0 | AP16: =IF(Q16=1,R16*$T$52,0)+IF(Q16=2,R16*$T$53,0)+IF(Q16=3,R16*$T$54,0)+IF(Q16=4,R16*$T$55,0)+IF(Q16=5,R16*$T$56,0)+IF(Q16=6,R16*$T$57,0)+IF(Q16=7,R16*$T$58,0)+IF(Q16=8,R16*$T$59,0)+IF(Q16=9,R16*$T$60,0)+IF(Q16=10,R16*$T$61,0) -> 0 | AQ16: =IF(S16=1,T16*$T$52,0)+IF(S16=2,T16*$T$53,0)+IF(S16=3,T16*$T$54,0)+IF(S16=4,T16*$T$55,0)+IF(S16=5,T16*$T$56,0)+IF(S16=6,T16*$T$57,0)+IF(S16=7,T16*$T$58,0)+IF(S16=8,T16*$T$59,0)+IF(S16=9,T16*$T$60,0)+IF(S16=10,T16*$T$61,0) -> 0 | AR16: =IF(U16=1,V16*$T$52,0)+IF(U16=2,V16*$T$53,0)+IF(U16=3,V16*$T$54,0)+IF(U16=4,V16*$T$55,0)+IF(U16=5,V16*$T$56,0)+IF(U16=6,V16*$T$57,0)+IF(U16=7,V16*$T$58,0)+IF(U16=8,V16*$T$59,0)+IF(U16=9,V16*$T$60,0)+IF(U16=10,V16*$T$61,0) -> 0 | AS16: =IF(W16=1,X16*$T$52,0)+IF(W16=2,X16*$T$53,0)+IF(W16=3,X16*$T$54,0)+IF(W16=4,X16*$T$55,0)+IF(W16=5,X16*$T$56,0)+IF(W16=6,X16*$T$57,0)+IF(W16=7,X16*$T$58,0)+IF(W16=8,X16*$T$59,0)+IF(W16=9,X16*$T$60,0)+IF(W16=10,X16*$T$61,0) -> 0 | AT16: =IF(Y16=1,Z16*$T$52,0)+IF(Y16=2,Z16*$T$53,0)+IF(Y16=3,Z16*$T$54,0)+IF(Y16=4,Z16*$T$55,0)+IF(Y16=5,Z16*$T$56,0)+IF(Y16=6,Z16*$T$57,0)+IF(Y16=7,Z16*$T$58,0)+IF(Y16=8,Z16*$T$59,0)+IF(Y16=9,Z16*$T$60,0)+IF(Y16=10,Z16*$T$61,0) -> 0 | AU16: =IF(AA16=1,AB16*$T$52,0)+IF(AA16=2,AB16*$T$53,0)+IF(AA16=3,AB16*$T$54,0)+IF(AA16=4,AB16*$T$55,0)+IF(AA16=5,AB16*$T$56,0)+IF(AA16=6,AB16*$T$57,0)+IF(AA16=7,AB16*$T$58,0)+IF(AA16=8,AB16*$T$59,0)+IF(AA16=9,AB16*$T$60,0)+IF(AA16=10,AB16*$T$61,0) -> 0 | AV16: =SUM(AO16:AU16) -> 0 | AW16: =ROUNDUP(IF(O16=1,P16*$P$52,0)+IF(O16=2,P16*$P$53,0)+IF(O16=3,P16*$P$54,0)+IF(O16=4,P16*$P$55,0)+IF(O16=5,P16*$P$56,0)+IF(O16=6,P16*$P$57,0)+IF(O16=7,P16*$P$58,0)+IF(O16=8,P16*$P$59,0)+IF(O16=9,P16*$P$60,0)+IF(O16=10,P16*$P$61,0),0)*BG16 -> 0 | AX16: =ROUNDUP(IF(Q16=1,R16*$P$52,0)+IF(Q16=2,R16*$P$53,0)+IF(Q16=3,R16*$P$54,0)+IF(Q16=4,R16*$P$55,0)+IF(Q16=5,R16*$P$56,0)+IF(Q16=6,R16*$P$57,0)+IF(Q16=7,R16*$P$58,0)+IF(Q16=8,R16*$P$59,0)+IF(Q16=9,R16*$P$60,0)+IF(Q16=10,R16*$P$61,0),0) -> 0 | AY16: =ROUNDUP(IF(S16=1,T16*$P$52,0)+IF(S16=2,T16*$P$53,0)+IF(S16=3,T16*$P$54,0)+IF(S16=4,T16*$P$55,0)+IF(S16=5,T16*$P$56,0)+IF(S16=6,T16*$P$57,0)+IF(S16=7,T16*$P$58,0)+IF(S16=8,T16*$P$59,0)+IF(S16=9,T16*$P$60,0)+IF(S16=10,T16*$P$61,0),0) -> 0 | AZ16: =ROUNDUP(IF(U16=1,V16*$P$52,0)+IF(U16=2,V16*$P$53,0)+IF(U16=3,V16*$P$54,0)+IF(U16=4,V16*$P$55,0)+IF(U16=5,V16*$P$56,0)+IF(U16=6,V16*$P$57,0)+IF(U16=7,V16*$P$58,0)+IF(U16=8,V16*$P$59,0)+IF(U16=9,V16*$P$60,0)+IF(U16=10,V16*$P$61,0),0) -> 0 | BA16: =ROUNDUP(IF(W16=1,X16*$P$52,0)+IF(W16=2,X16*$P$53,0)+IF(W16=3,X16*$P$54,0)+IF(W16=4,X16*$P$55,0)+IF(W16=5,X16*$P$56,0)+IF(W16=6,X16*$P$57,0)+IF(W16=7,X16*$P$58,0)+IF(W16=8,X16*$P$59,0)+IF(W16=9,X16*$P$60,0)+IF(W16=10,X16*$P$61,0),0) -> 0 | BB16: =ROUNDUP(IF(Y16=1,Z16*$P$52,0)+IF(Y16=2,Z16*$P$53,0)+IF(Y16=3,Z16*$P$54,0)+IF(Y16=4,Z16*$P$55,0)+IF(Y16=5,Z16*$P$56,0)+IF(Y16=6,Z16*$P$57,0)+IF(Y16=7,Z16*$P$58,0)+IF(Y16=8,Z16*$P$59,0)+IF(Y16=9,Z16*$P$60,0)+IF(Y16=10,Z16*$P$61,0),0) -> 0 | BC16: =ROUNDUP(IF(AA16=1,AB16*$P$52,0)+IF(AA16=2,AB16*$P$53,0)+IF(AA16=3,AB16*$P$54,0)+IF(AA16=4,AB16*$P$55,0)+IF(AA16=5,AB16*$P$56,0)+IF(AA16=6,AB16*$P$57,0)+IF(AA16=7,AB16*$P$58,0)+IF(AA16=8,AB16*$P$59,0)+IF(AA16=9,AB16*$P$60,0)+IF(AA16=10,AB16*$P$61,0),0) -> 0 | BD16: =SUM(AW16:BC16)*BG16 -> 0 | BE16: =IF(M16=0,0,(M16/12+M16/12)/(M16/12*M16/12)*D16*((L16/16*L16/16)*10.6870159))*(1+K$74)*BG16 -> 0 | BF16: =IF(N16="Y",D16*(1+K$75)*BG16,0) -> 0 | BG16: =G16 -> 0 | BH16: =IF(N16="y",D16,0) -> 0 | BI16: =IF($I16=1,$AD16,0)*BG16 -> 0 | BJ16: =IF($I16=2,$AD16,0)*BG16 -> 0 | BK16: =IF($I16=3,$AD16,0)*BG16 -> 0 | BL16: =IF($I16=4,$AD16,0)*BG16 -> 0 | BM16: =IF($I16=5,$AD16,0)*BG16 -> 0 | BN16: =IF($I16=6,$AD16,0)*BG16 -> 0 | BO16: =SUM(BI16:BN16) -> 0 | BP16: =IF(H16="N",0,D16)*BG16 -> 0 | BQ16: =K16*BG16 -> 0 | BR16: =IF(O16=1,D$52*P16/12,IF(O16=2,D$53*P16/12,IF(O16=3,D$54*P16/12,IF(O16=4,D$55*P16/12,IF(O16=5,D$56*P16/12,IF(O16=6,D$57*P16/12,IF(O16=7,D$58*P16/12,IF(O16=8,D$59*P16/12,IF(O16=9,D$60*P16/12,IF(O16=10,D$61*P16/12,0))))))*BG16)))) -> 0 | BS16: =IF(Q16=1,D$52*R16/12,IF(Q16=2,D$53*R16/12,IF(Q16=3,D$54*R16/12,IF(Q16=4,D$55*R16/12,IF(Q16=5,D$56*R16/12,IF(Q16=6,D$57*R16/12,IF(Q16=7,D$58*R16/12,IF(Q16=8,D$59*R16/12,IF(Q16=9,D$60*R16/12,IF(Q16=10,D$61*R16/12,0))))))*BG16)))) -> 0 | BT16: =D16*BG16 -> 0 | BU16: =D16*J16/324*(1+K$77)*BG16 -> 0 | BV16: =AC16*BG16 -> 0 | BW16: =IF(BG16=0,0,SUM(BX16:CM16)/BG16) -> 0 | BX16: =(BI16*Pricing!F$2+BJ16*Pricing!G$2+BK16*Pricing!H$2+BL16*Pricing!I$2+BM16*Pricing!J$2+BN16*Pricing!K$2)*IF(AC$63="N",(1+AE$63),1) -> 0 | BY16: =AC16*G$74*IF(AC$63="n",1+AE$63,1)*BG16 -> 0 | BZ16: =IF(I$83=0,0,D16*(SUM(L$83:M$86)+L$88)/I$83*BG16) -> 0 | CA16: =IF(I$83=0,0,D16*(SUM(O$83:P$86)+O$88)/I$83*BG16) -> 0 | CB16: =BR16+BS16*E$87 -> 0 | CD16: =BD16/2000*E$89 -> 0 | CE16: =IF(D$49=0,0,SUM(O$92:P$96)/D$49*D16)*BG16 -> 0 | CF16: =IF(D$49=0,0,SUM(AF$72:AF$99)/D$49*D16*BG16) -> 0 | CG16: =IF(D$49=0,0,SUM(O$98:P$103)/D$49*D16)*BG16 -> 0 | CH16: =IF(D$49=0,0,SUM(O$105:O$111)/D$49)*D16*BG16 -> 0 | CI16: =IF(D$49=0,0,SUM(AF$100:AF$111)/D$49*D16*BG16) -> 0 | CJ16: =IF(J$76>0,J$76/D$49*D16*G16,BP16*(G$76*(1+AE$63))) -> 0 | CK16: =IF(L$78=0,0,O$78/L$78)*AW16+IF(L$79=0,0,O$79/L$79)*BC16+IF(L$80=0,0,O$80/L$80)*BC16 -> 0 | CL16: =BF16*G$75*IF(AC$63="Y",1,1+AE$63) -> 0 | CM16: =BU16*G$77*IF(AC$63="Y",1,1+AE$63) -> 0 | CO16: =IF(O16=1,P16*$AM$52,0)+IF(O16=2,P16*$AM$53,0)+IF(O16=3,P16*$AM$54,0)+IF(O16=4,P16*$AM$55,0)+IF(O16=5,P16*$AM$56,0)+IF(O16=6,P16*$AM$57,0)+IF(O16=7,P16*$AM$58,0)+IF(O16=8,P16*$AM$59,0)+IF(O16=9,P16*$AM$60,0)+IF(O16=10,P16*$AM$61,0) -> 0 | CP16: =IF(Q16=1,R16*$AM$52,0)+IF(Q16=2,R16*$AM$53,0)+IF(Q16=3,R16*$AM$54,0)+IF(Q16=4,R16*$AM$55,0)+IF(Q16=5,R16*$AM$56,0)+IF(Q16=6,R16*$AM$57,0)+IF(Q16=7,R16*$AM$58,0)+IF(Q16=8,R16*$AM$59,0)+IF(Q16=9,R16*$AM$60,0)+IF(Q16=10,R16*$AM$61,0) -> 0 | CQ16: =IF(S16=1,T16*$AM$52,0)+IF(S16=2,T16*$AM$53,0)+IF(S16=3,T16*$AM$54,0)+IF(S16=4,T16*$AM$55,0)+IF(S16=5,T16*$AM$56,0)+IF(S16=6,T16*$AM$57,0)+IF(S16=7,T16*$AM$58,0)+IF(S16=8,T16*$AM$59,0)+IF(S16=9,T16*$AM$60,0)+IF(S16=10,T16*$AM$61,0) -> 0 | CR16: =IF(U16=1,V16*$AM$52,0)+IF(U16=2,V16*$AM$53,0)+IF(U16=3,V16*$AM$54,0)+IF(U16=4,V16*$AM$55,0)+IF(U16=5,V16*$AM$56,0)+IF(U16=6,V16*$AM$57,0)+IF(U16=7,V16*$AM$58,0)+IF(U16=8,V16*$AM$59,0)+IF(U16=9,V16*$AM$60,0)+IF(U16=10,V16*$AM$61,0) -> 0 | CS16: =IF(W16=1,X16*$AM$52,0)+IF(W16=2,X16*$AM$53,0)+IF(W16=3,X16*$AM$54,0)+IF(W16=4,X16*$AM$55,0)+IF(W16=5,X16*$AM$56,0)+IF(W16=6,X16*$AM$57,0)+IF(W16=7,X16*$AM$58,0)+IF(W16=8,X16*$AM$59,0)+IF(W16=9,X16*$AM$60,0)+IF(W16=10,X16*$AM$61,0) -> 0 | CT16: =IF(Y16=1,Z16*$AM$52,0)+IF(Y16=2,Z16*$AM$53,0)+IF(Y16=3,Z16*$AM$54,0)+IF(Y16=4,Z16*$AM$55,0)+IF(Y16=5,Z16*$AM$56,0)+IF(Y16=6,Z16*$AM$57,0)+IF(Y16=7,Z16*$AM$58,0)+IF(Y16=8,Z16*$AM$59,0)+IF(Y16=9,Z16*$AM$60,0)+IF(Y16=10,Z16*$AM$61,0) -> 0 | CU16: =IF(AA16=1,AB16*$AM$52,0)+IF(AA16=2,AB16*$AM$53,0)+IF(AA16=3,AB16*$AM$54,0)+IF(AA16=4,AB16*$AM$55,0)+IF(AA16=5,AB16*$AM$56,0)+IF(AA16=6,AB16*$AM$57,0)+IF(AA16=7,AB16*$AM$58,0)+IF(AA16=8,AB16*$AM$59,0)+IF(AA16=9,AB16*$AM$60,0)+IF(AA16=10,AB16*$AM$61,0) -> 0 | CV16: =D16 -> 0 | CW16: =SUM(CO16:CV16)*BG16 -> 0
O17: 9 | Q17: 10 | S17: 1 | T17: =K17 -> 0 | U17: 2 | W17: 3 | Y17: 4 | AA17: 5 | AC17: =IF(BG17=0,0,SUM(BD17:BE17)/BG17) -> 0 | AD17: =(D17*F17/324)*(1+K$71)+AV17 -> 0 | AE17: =IF(D17=0,0,AF17/D17) -> 0 | AF17: =SUM(BW17)*(1+M$64+Summary!P$64) -> 0 | AG17: =D17/AD17 -> #DIV/0! | AH17: =AF17*G17 -> 0 | AO17: =IF(O17=1,P17*$T$52,0)+IF(O17=2,P17*$T$53,0)+IF(O17=3,P17*$T$54,0)+IF(O17=4,P17*$T$55,0)+IF(O17=5,P17*$T$56,0)+IF(O17=6,P17*$T$57,0)+IF(O17=7,P17*$T$58,0)+IF(O17=8,P17*$T$59,0)+IF(O17=9,P17*$T$60,0)+IF(O17=10,P17*$T$61,0) -> 0 | AP17: =IF(Q17=1,R17*$T$52,0)+IF(Q17=2,R17*$T$53,0)+IF(Q17=3,R17*$T$54,0)+IF(Q17=4,R17*$T$55,0)+IF(Q17=5,R17*$T$56,0)+IF(Q17=6,R17*$T$57,0)+IF(Q17=7,R17*$T$58,0)+IF(Q17=8,R17*$T$59,0)+IF(Q17=9,R17*$T$60,0)+IF(Q17=10,R17*$T$61,0) -> 0 | AQ17: =IF(S17=1,T17*$T$52,0)+IF(S17=2,T17*$T$53,0)+IF(S17=3,T17*$T$54,0)+IF(S17=4,T17*$T$55,0)+IF(S17=5,T17*$T$56,0)+IF(S17=6,T17*$T$57,0)+IF(S17=7,T17*$T$58,0)+IF(S17=8,T17*$T$59,0)+IF(S17=9,T17*$T$60,0)+IF(S17=10,T17*$T$61,0) -> 0 | AR17: =IF(U17=1,V17*$T$52,0)+IF(U17=2,V17*$T$53,0)+IF(U17=3,V17*$T$54,0)+IF(U17=4,V17*$T$55,0)+IF(U17=5,V17*$T$56,0)+IF(U17=6,V17*$T$57,0)+IF(U17=7,V17*$T$58,0)+IF(U17=8,V17*$T$59,0)+IF(U17=9,V17*$T$60,0)+IF(U17=10,V17*$T$61,0) -> 0 | AS17: =IF(W17=1,X17*$T$52,0)+IF(W17=2,X17*$T$53,0)+IF(W17=3,X17*$T$54,0)+IF(W17=4,X17*$T$55,0)+IF(W17=5,X17*$T$56,0)+IF(W17=6,X17*$T$57,0)+IF(W17=7,X17*$T$58,0)+IF(W17=8,X17*$T$59,0)+IF(W17=9,X17*$T$60,0)+IF(W17=10,X17*$T$61,0) -> 0 | AT17: =IF(Y17=1,Z17*$T$52,0)+IF(Y17=2,Z17*$T$53,0)+IF(Y17=3,Z17*$T$54,0)+IF(Y17=4,Z17*$T$55,0)+IF(Y17=5,Z17*$T$56,0)+IF(Y17=6,Z17*$T$57,0)+IF(Y17=7,Z17*$T$58,0)+IF(Y17=8,Z17*$T$59,0)+IF(Y17=9,Z17*$T$60,0)+IF(Y17=10,Z17*$T$61,0) -> 0 | AU17: =IF(AA17=1,AB17*$T$52,0)+IF(AA17=2,AB17*$T$53,0)+IF(AA17=3,AB17*$T$54,0)+IF(AA17=4,AB17*$T$55,0)+IF(AA17=5,AB17*$T$56,0)+IF(AA17=6,AB17*$T$57,0)+IF(AA17=7,AB17*$T$58,0)+IF(AA17=8,AB17*$T$59,0)+IF(AA17=9,AB17*$T$60,0)+IF(AA17=10,AB17*$T$61,0) -> 0 | AV17: =SUM(AO17:AU17) -> 0 | AW17: =ROUNDUP(IF(O17=1,P17*$P$52,0)+IF(O17=2,P17*$P$53,0)+IF(O17=3,P17*$P$54,0)+IF(O17=4,P17*$P$55,0)+IF(O17=5,P17*$P$56,0)+IF(O17=6,P17*$P$57,0)+IF(O17=7,P17*$P$58,0)+IF(O17=8,P17*$P$59,0)+IF(O17=9,P17*$P$60,0)+IF(O17=10,P17*$P$61,0),0)*BG17 -> 0 | AX17: =ROUNDUP(IF(Q17=1,R17*$P$52,0)+IF(Q17=2,R17*$P$53,0)+IF(Q17=3,R17*$P$54,0)+IF(Q17=4,R17*$P$55,0)+IF(Q17=5,R17*$P$56,0)+IF(Q17=6,R17*$P$57,0)+IF(Q17=7,R17*$P$58,0)+IF(Q17=8,R17*$P$59,0)+IF(Q17=9,R17*$P$60,0)+IF(Q17=10,R17*$P$61,0),0) -> 0 | AY17: =ROUNDUP(IF(S17=1,T17*$P$52,0)+IF(S17=2,T17*$P$53,0)+IF(S17=3,T17*$P$54,0)+IF(S17=4,T17*$P$55,0)+IF(S17=5,T17*$P$56,0)+IF(S17=6,T17*$P$57,0)+IF(S17=7,T17*$P$58,0)+IF(S17=8,T17*$P$59,0)+IF(S17=9,T17*$P$60,0)+IF(S17=10,T17*$P$61,0),0) -> 0 | AZ17: =ROUNDUP(IF(U17=1,V17*$P$52,0)+IF(U17=2,V17*$P$53,0)+IF(U17=3,V17*$P$54,0)+IF(U17=4,V17*$P$55,0)+IF(U17=5,V17*$P$56,0)+IF(U17=6,V17*$P$57,0)+IF(U17=7,V17*$P$58,0)+IF(U17=8,V17*$P$59,0)+IF(U17=9,V17*$P$60,0)+IF(U17=10,V17*$P$61,0),0) -> 0 | BA17: =ROUNDUP(IF(W17=1,X17*$P$52,0)+IF(W17=2,X17*$P$53,0)+IF(W17=3,X17*$P$54,0)+IF(W17=4,X17*$P$55,0)+IF(W17=5,X17*$P$56,0)+IF(W17=6,X17*$P$57,0)+IF(W17=7,X17*$P$58,0)+IF(W17=8,X17*$P$59,0)+IF(W17=9,X17*$P$60,0)+IF(W17=10,X17*$P$61,0),0) -> 0 | BB17: =ROUNDUP(IF(Y17=1,Z17*$P$52,0)+IF(Y17=2,Z17*$P$53,0)+IF(Y17=3,Z17*$P$54,0)+IF(Y17=4,Z17*$P$55,0)+IF(Y17=5,Z17*$P$56,0)+IF(Y17=6,Z17*$P$57,0)+IF(Y17=7,Z17*$P$58,0)+IF(Y17=8,Z17*$P$59,0)+IF(Y17=9,Z17*$P$60,0)+IF(Y17=10,Z17*$P$61,0),0) -> 0 | BC17: =ROUNDUP(IF(AA17=1,AB17*$P$52,0)+IF(AA17=2,AB17*$P$53,0)+IF(AA17=3,AB17*$P$54,0)+IF(AA17=4,AB17*$P$55,0)+IF(AA17=5,AB17*$P$56,0)+IF(AA17=6,AB17*$P$57,0)+IF(AA17=7,AB17*$P$58,0)+IF(AA17=8,AB17*$P$59,0)+IF(AA17=9,AB17*$P$60,0)+IF(AA17=10,AB17*$P$61,0),0) -> 0 | BD17: =SUM(AW17:BC17)*BG17 -> 0 | BE17: =IF(M17=0,0,(M17/12+M17/12)/(M17/12*M17/12)*D17*((L17/16*L17/16)*10.6870159))*(1+K$74)*BG17 -> 0 | BF17: =IF(N17="Y",D17*(1+K$75)*BG17,0) -> 0 | BG17: =G17 -> 0 | BH17: =IF(N17="y",D17,0) -> 0 | BI17: =IF($I17=1,$AD17,0)*BG17 -> 0 | BJ17: =IF($I17=2,$AD17,0)*BG17 -> 0 | BK17: =IF($I17=3,$AD17,0)*BG17 -> 0 | BL17: =IF($I17=4,$AD17,0)*BG17 -> 0 | BM17: =IF($I17=5,$AD17,0)*BG17 -> 0 | BN17: =IF($I17=6,$AD17,0)*BG17 -> 0 | BO17: =SUM(BI17:BN17) -> 0 | BP17: =IF(H17="N",0,D17)*BG17 -> 0 | BQ17: =K17*BG17 -> 0 | BR17: =IF(O17=1,D$52*P17/12,IF(O17=2,D$53*P17/12,IF(O17=3,D$54*P17/12,IF(O17=4,D$55*P17/12,IF(O17=5,D$56*P17/12,IF(O17=6,D$57*P17/12,IF(O17=7,D$58*P17/12,IF(O17=8,D$59*P17/12,IF(O17=9,D$60*P17/12,IF(O17=10,D$61*P17/12,0))))))*BG17)))) -> 0 | BS17: =IF(Q17=1,D$52*R17/12,IF(Q17=2,D$53*R17/12,IF(Q17=3,D$54*R17/12,IF(Q17=4,D$55*R17/12,IF(Q17=5,D$56*R17/12,IF(Q17=6,D$57*R17/12,IF(Q17=7,D$58*R17/12,IF(Q17=8,D$59*R17/12,IF(Q17=9,D$60*R17/12,IF(Q17=10,D$61*R17/12,0))))))*BG17)))) -> 0 | BT17: =D17*BG17 -> 0 | BU17: =D17*J17/324*(1+K$77)*BG17 -> 0 | BV17: =AC17*BG17 -> 0 | BW17: =IF(BG17=0,0,SUM(BX17:CM17)/BG17) -> 0 | BX17: =(BI17*Pricing!F$2+BJ17*Pricing!G$2+BK17*Pricing!H$2+BL17*Pricing!I$2+BM17*Pricing!J$2+BN17*Pricing!K$2)*IF(AC$63="N",(1+AE$63),1) -> 0 | BY17: =AC17*G$74*IF(AC$63="n",1+AE$63,1)*BG17 -> 0 | BZ17: =IF(I$83=0,0,D17*(SUM(L$83:M$86)+L$88)/I$83*BG17) -> 0 | CA17: =IF(I$83=0,0,D17*(SUM(O$83:P$86)+O$88)/I$83*BG17) -> 0 | CB17: =BR17+BS17*E$87 -> 0 | CD17: =BD17/2000*E$89 -> 0 | CE17: =IF(D$49=0,0,SUM(O$92:P$96)/D$49*D17)*BG17 -> 0 | CF17: =IF(D$49=0,0,SUM(AF$72:AF$99)/D$49*D17*BG17) -> 0 | CG17: =IF(D$49=0,0,SUM(O$98:P$103)/D$49*D17)*BG17 -> 0 | CH17: =IF(D$49=0,0,SUM(O$105:O$111)/D$49)*D17*BG17 -> 0 | CI17: =IF(D$49=0,0,SUM(AF$100:AF$111)/D$49*D17*BG17) -> 0 | CJ17: =IF(J$76>0,J$76/D$49*D17*G17,BP17*(G$76*(1+AE$63))) -> 0 | CK17: =IF(L$78=0,0,O$78/L$78)*AW17+IF(L$79=0,0,O$79/L$79)*BC17+IF(L$80=0,0,O$80/L$80)*BC17 -> 0 | CL17: =BF17*G$75*IF(AC$63="Y",1,1+AE$63) -> 0 | CM17: =BU17*G$77*IF(AC$63="Y",1,1+AE$63) -> 0 | CO17: =IF(O17=1,P17*$AM$52,0)+IF(O17=2,P17*$AM$53,0)+IF(O17=3,P17*$AM$54,0)+IF(O17=4,P17*$AM$55,0)+IF(O17=5,P17*$AM$56,0)+IF(O17=6,P17*$AM$57,0)+IF(O17=7,P17*$AM$58,0)+IF(O17=8,P17*$AM$59,0)+IF(O17=9,P17*$AM$60,0)+IF(O17=10,P17*$AM$61,0) -> 0 | CP17: =IF(Q17=1,R17*$AM$52,0)+IF(Q17=2,R17*$AM$53,0)+IF(Q17=3,R17*$AM$54,0)+IF(Q17=4,R17*$AM$55,0)+IF(Q17=5,R17*$AM$56,0)+IF(Q17=6,R17*$AM$57,0)+IF(Q17=7,R17*$AM$58,0)+IF(Q17=8,R17*$AM$59,0)+IF(Q17=9,R17*$AM$60,0)+IF(Q17=10,R17*$AM$61,0) -> 0 | CQ17: =IF(S17=1,T17*$AM$52,0)+IF(S17=2,T17*$AM$53,0)+IF(S17=3,T17*$AM$54,0)+IF(S17=4,T17*$AM$55,0)+IF(S17=5,T17*$AM$56,0)+IF(S17=6,T17*$AM$57,0)+IF(S17=7,T17*$AM$58,0)+IF(S17=8,T17*$AM$59,0)+IF(S17=9,T17*$AM$60,0)+IF(S17=10,T17*$AM$61,0) -> 0 | CR17: =IF(U17=1,V17*$AM$52,0)+IF(U17=2,V17*$AM$53,0)+IF(U17=3,V17*$AM$54,0)+IF(U17=4,V17*$AM$55,0)+IF(U17=5,V17*$AM$56,0)+IF(U17=6,V17*$AM$57,0)+IF(U17=7,V17*$AM$58,0)+IF(U17=8,V17*$AM$59,0)+IF(U17=9,V17*$AM$60,0)+IF(U17=10,V17*$AM$61,0) -> 0 | CS17: =IF(W17=1,X17*$AM$52,0)+IF(W17=2,X17*$AM$53,0)+IF(W17=3,X17*$AM$54,0)+IF(W17=4,X17*$AM$55,0)+IF(W17=5,X17*$AM$56,0)+IF(W17=6,X17*$AM$57,0)+IF(W17=7,X17*$AM$58,0)+IF(W17=8,X17*$AM$59,0)+IF(W17=9,X17*$AM$60,0)+IF(W17=10,X17*$AM$61,0) -> 0 | CT17: =IF(Y17=1,Z17*$AM$52,0)+IF(Y17=2,Z17*$AM$53,0)+IF(Y17=3,Z17*$AM$54,0)+IF(Y17=4,Z17*$AM$55,0)+IF(Y17=5,Z17*$AM$56,0)+IF(Y17=6,Z17*$AM$57,0)+IF(Y17=7,Z17*$AM$58,0)+IF(Y17=8,Z17*$AM$59,0)+IF(Y17=9,Z17*$AM$60,0)+IF(Y17=10,Z17*$AM$61,0) -> 0 | CU17: =IF(AA17=1,AB17*$AM$52,0)+IF(AA17=2,AB17*$AM$53,0)+IF(AA17=3,AB17*$AM$54,0)+IF(AA17=4,AB17*$AM$55,0)+IF(AA17=5,AB17*$AM$56,0)+IF(AA17=6,AB17*$AM$57,0)+IF(AA17=7,AB17*$AM$58,0)+IF(AA17=8,AB17*$AM$59,0)+IF(AA17=9,AB17*$AM$60,0)+IF(AA17=10,AB17*$AM$61,0) -> 0 | CV17: =D17 -> 0 | CW17: =SUM(CO17:CV17)*BG17 -> 0
O18: 9 | Q18: 10 | S18: 1 | T18: =K18 -> 0 | U18: 2 | W18: 3 | Y18: 4 | AA18: 5 | AC18: =IF(BG18=0,0,SUM(BD18:BE18)/BG18) -> 0 | AD18: =(D18*F18/324)*(1+K$71)+AV18 -> 0 | AE18: =IF(D18=0,0,AF18/D18) -> 0 | AF18: =SUM(BW18)*(1+M$64+Summary!P$64) -> 0 | AG18: =D18/AD18 -> #DIV/0! | AH18: =AF18*G18 -> 0 | AO18: =IF(O18=1,P18*$T$52,0)+IF(O18=2,P18*$T$53,0)+IF(O18=3,P18*$T$54,0)+IF(O18=4,P18*$T$55,0)+IF(O18=5,P18*$T$56,0)+IF(O18=6,P18*$T$57,0)+IF(O18=7,P18*$T$58,0)+IF(O18=8,P18*$T$59,0)+IF(O18=9,P18*$T$60,0)+IF(O18=10,P18*$T$61,0) -> 0 | AP18: =IF(Q18=1,R18*$T$52,0)+IF(Q18=2,R18*$T$53,0)+IF(Q18=3,R18*$T$54,0)+IF(Q18=4,R18*$T$55,0)+IF(Q18=5,R18*$T$56,0)+IF(Q18=6,R18*$T$57,0)+IF(Q18=7,R18*$T$58,0)+IF(Q18=8,R18*$T$59,0)+IF(Q18=9,R18*$T$60,0)+IF(Q18=10,R18*$T$61,0) -> 0 | AQ18: =IF(S18=1,T18*$T$52,0)+IF(S18=2,T18*$T$53,0)+IF(S18=3,T18*$T$54,0)+IF(S18=4,T18*$T$55,0)+IF(S18=5,T18*$T$56,0)+IF(S18=6,T18*$T$57,0)+IF(S18=7,T18*$T$58,0)+IF(S18=8,T18*$T$59,0)+IF(S18=9,T18*$T$60,0)+IF(S18=10,T18*$T$61,0) -> 0 | AR18: =IF(U18=1,V18*$T$52,0)+IF(U18=2,V18*$T$53,0)+IF(U18=3,V18*$T$54,0)+IF(U18=4,V18*$T$55,0)+IF(U18=5,V18*$T$56,0)+IF(U18=6,V18*$T$57,0)+IF(U18=7,V18*$T$58,0)+IF(U18=8,V18*$T$59,0)+IF(U18=9,V18*$T$60,0)+IF(U18=10,V18*$T$61,0) -> 0 | AS18: =IF(W18=1,X18*$T$52,0)+IF(W18=2,X18*$T$53,0)+IF(W18=3,X18*$T$54,0)+IF(W18=4,X18*$T$55,0)+IF(W18=5,X18*$T$56,0)+IF(W18=6,X18*$T$57,0)+IF(W18=7,X18*$T$58,0)+IF(W18=8,X18*$T$59,0)+IF(W18=9,X18*$T$60,0)+IF(W18=10,X18*$T$61,0) -> 0 | AT18: =IF(Y18=1,Z18*$T$52,0)+IF(Y18=2,Z18*$T$53,0)+IF(Y18=3,Z18*$T$54,0)+IF(Y18=4,Z18*$T$55,0)+IF(Y18=5,Z18*$T$56,0)+IF(Y18=6,Z18*$T$57,0)+IF(Y18=7,Z18*$T$58,0)+IF(Y18=8,Z18*$T$59,0)+IF(Y18=9,Z18*$T$60,0)+IF(Y18=10,Z18*$T$61,0) -> 0 | AU18: =IF(AA18=1,AB18*$T$52,0)+IF(AA18=2,AB18*$T$53,0)+IF(AA18=3,AB18*$T$54,0)+IF(AA18=4,AB18*$T$55,0)+IF(AA18=5,AB18*$T$56,0)+IF(AA18=6,AB18*$T$57,0)+IF(AA18=7,AB18*$T$58,0)+IF(AA18=8,AB18*$T$59,0)+IF(AA18=9,AB18*$T$60,0)+IF(AA18=10,AB18*$T$61,0) -> 0 | AV18: =SUM(AO18:AU18) -> 0 | AW18: =ROUNDUP(IF(O18=1,P18*$P$52,0)+IF(O18=2,P18*$P$53,0)+IF(O18=3,P18*$P$54,0)+IF(O18=4,P18*$P$55,0)+IF(O18=5,P18*$P$56,0)+IF(O18=6,P18*$P$57,0)+IF(O18=7,P18*$P$58,0)+IF(O18=8,P18*$P$59,0)+IF(O18=9,P18*$P$60,0)+IF(O18=10,P18*$P$61,0),0)*BG18 -> 0 | AX18: =ROUNDUP(IF(Q18=1,R18*$P$52,0)+IF(Q18=2,R18*$P$53,0)+IF(Q18=3,R18*$P$54,0)+IF(Q18=4,R18*$P$55,0)+IF(Q18=5,R18*$P$56,0)+IF(Q18=6,R18*$P$57,0)+IF(Q18=7,R18*$P$58,0)+IF(Q18=8,R18*$P$59,0)+IF(Q18=9,R18*$P$60,0)+IF(Q18=10,R18*$P$61,0),0) -> 0 | AY18: =ROUNDUP(IF(S18=1,T18*$P$52,0)+IF(S18=2,T18*$P$53,0)+IF(S18=3,T18*$P$54,0)+IF(S18=4,T18*$P$55,0)+IF(S18=5,T18*$P$56,0)+IF(S18=6,T18*$P$57,0)+IF(S18=7,T18*$P$58,0)+IF(S18=8,T18*$P$59,0)+IF(S18=9,T18*$P$60,0)+IF(S18=10,T18*$P$61,0),0) -> 0 | AZ18: =ROUNDUP(IF(U18=1,V18*$P$52,0)+IF(U18=2,V18*$P$53,0)+IF(U18=3,V18*$P$54,0)+IF(U18=4,V18*$P$55,0)+IF(U18=5,V18*$P$56,0)+IF(U18=6,V18*$P$57,0)+IF(U18=7,V18*$P$58,0)+IF(U18=8,V18*$P$59,0)+IF(U18=9,V18*$P$60,0)+IF(U18=10,V18*$P$61,0),0) -> 0 | BA18: =ROUNDUP(IF(W18=1,X18*$P$52,0)+IF(W18=2,X18*$P$53,0)+IF(W18=3,X18*$P$54,0)+IF(W18=4,X18*$P$55,0)+IF(W18=5,X18*$P$56,0)+IF(W18=6,X18*$P$57,0)+IF(W18=7,X18*$P$58,0)+IF(W18=8,X18*$P$59,0)+IF(W18=9,X18*$P$60,0)+IF(W18=10,X18*$P$61,0),0) -> 0 | BB18: =ROUNDUP(IF(Y18=1,Z18*$P$52,0)+IF(Y18=2,Z18*$P$53,0)+IF(Y18=3,Z18*$P$54,0)+IF(Y18=4,Z18*$P$55,0)+IF(Y18=5,Z18*$P$56,0)+IF(Y18=6,Z18*$P$57,0)+IF(Y18=7,Z18*$P$58,0)+IF(Y18=8,Z18*$P$59,0)+IF(Y18=9,Z18*$P$60,0)+IF(Y18=10,Z18*$P$61,0),0) -> 0 | BC18: =ROUNDUP(IF(AA18=1,AB18*$P$52,0)+IF(AA18=2,AB18*$P$53,0)+IF(AA18=3,AB18*$P$54,0)+IF(AA18=4,AB18*$P$55,0)+IF(AA18=5,AB18*$P$56,0)+IF(AA18=6,AB18*$P$57,0)+IF(AA18=7,AB18*$P$58,0)+IF(AA18=8,AB18*$P$59,0)+IF(AA18=9,AB18*$P$60,0)+IF(AA18=10,AB18*$P$61,0),0) -> 0 | BD18: =SUM(AW18:BC18)*BG18 -> 0 | BE18: =IF(M18=0,0,(M18/12+M18/12)/(M18/12*M18/12)*D18*((L18/16*L18/16)*10.6870159))*(1+K$74)*BG18 -> 0 | BF18: =IF(N18="Y",D18*(1+K$75)*BG18,0) -> 0 | BG18: =G18 -> 0 | BH18: =IF(N18="y",D18,0) -> 0 | BI18: =IF($I18=1,$AD18,0)*BG18 -> 0 | BJ18: =IF($I18=2,$AD18,0)*BG18 -> 0 | BK18: =IF($I18=3,$AD18,0)*BG18 -> 0 | BL18: =IF($I18=4,$AD18,0)*BG18 -> 0 | BM18: =IF($I18=5,$AD18,0)*BG18 -> 0 | BN18: =IF($I18=6,$AD18,0)*BG18 -> 0 | BO18: =SUM(BI18:BN18) -> 0 | BP18: =IF(H18="N",0,D18)*BG18 -> 0 | BQ18: =K18*BG18 -> 0 | BR18: =IF(O18=1,D$52*P18/12,IF(O18=2,D$53*P18/12,IF(O18=3,D$54*P18/12,IF(O18=4,D$55*P18/12,IF(O18=5,D$56*P18/12,IF(O18=6,D$57*P18/12,IF(O18=7,D$58*P18/12,IF(O18=8,D$59*P18/12,IF(O18=9,D$60*P18/12,IF(O18=10,D$61*P18/12,0))))))*BG18)))) -> 0 | BS18: =IF(Q18=1,D$52*R18/12,IF(Q18=2,D$53*R18/12,IF(Q18=3,D$54*R18/12,IF(Q18=4,D$55*R18/12,IF(Q18=5,D$56*R18/12,IF(Q18=6,D$57*R18/12,IF(Q18=7,D$58*R18/12,IF(Q18=8,D$59*R18/12,IF(Q18=9,D$60*R18/12,IF(Q18=10,D$61*R18/12,0))))))*BG18)))) -> 0 | BT18: =D18*BG18 -> 0 | BU18: =D18*J18/324*(1+K$77)*BG18 -> 0 | BV18: =AC18*BG18 -> 0 | BW18: =IF(BG18=0,0,SUM(BX18:CM18)/BG18) -> 0 | BX18: =(BI18*Pricing!F$2+BJ18*Pricing!G$2+BK18*Pricing!H$2+BL18*Pricing!I$2+BM18*Pricing!J$2+BN18*Pricing!K$2)*IF(AC$63="N",(1+AE$63),1) -> 0 | BY18: =AC18*G$74*IF(AC$63="n",1+AE$63,1)*BG18 -> 0 | BZ18: =IF(I$83=0,0,D18*(SUM(L$83:M$86)+L$88)/I$83*BG18) -> 0 | CA18: =IF(I$83=0,0,D18*(SUM(O$83:P$86)+O$88)/I$83*BG18) -> 0 | CB18: =BR18+BS18*E$87 -> 0 | CD18: =BD18/2000*E$89 -> 0 | CE18: =IF(D$49=0,0,SUM(O$92:P$96)/D$49*D18)*BG18 -> 0 | CF18: =IF(D$49=0,0,SUM(AF$72:AF$99)/D$49*D18*BG18) -> 0 | CG18: =IF(D$49=0,0,SUM(O$98:P$103)/D$49*D18)*BG18 -> 0 | CH18: =IF(D$49=0,0,SUM(O$105:O$111)/D$49)*D18*BG18 -> 0 | CI18: =IF(D$49=0,0,SUM(AF$100:AF$111)/D$49*D18*BG18) -> 0 | CJ18: =IF(J$76>0,J$76/D$49*D18*G18,BP18*(G$76*(1+AE$63))) -> 0 | CK18: =IF(L$78=0,0,O$78/L$78)*AW18+IF(L$79=0,0,O$79/L$79)*BC18+IF(L$80=0,0,O$80/L$80)*BC18 -> 0 | CL18: =BF18*G$75*IF(AC$63="Y",1,1+AE$63) -> 0 | CM18: =BU18*G$77*IF(AC$63="Y",1,1+AE$63) -> 0 | CO18: =IF(O18=1,P18*$AM$52,0)+IF(O18=2,P18*$AM$53,0)+IF(O18=3,P18*$AM$54,0)+IF(O18=4,P18*$AM$55,0)+IF(O18=5,P18*$AM$56,0)+IF(O18=6,P18*$AM$57,0)+IF(O18=7,P18*$AM$58,0)+IF(O18=8,P18*$AM$59,0)+IF(O18=9,P18*$AM$60,0)+IF(O18=10,P18*$AM$61,0) -> 0 | CP18: =IF(Q18=1,R18*$AM$52,0)+IF(Q18=2,R18*$AM$53,0)+IF(Q18=3,R18*$AM$54,0)+IF(Q18=4,R18*$AM$55,0)+IF(Q18=5,R18*$AM$56,0)+IF(Q18=6,R18*$AM$57,0)+IF(Q18=7,R18*$AM$58,0)+IF(Q18=8,R18*$AM$59,0)+IF(Q18=9,R18*$AM$60,0)+IF(Q18=10,R18*$AM$61,0) -> 0 | CQ18: =IF(S18=1,T18*$AM$52,0)+IF(S18=2,T18*$AM$53,0)+IF(S18=3,T18*$AM$54,0)+IF(S18=4,T18*$AM$55,0)+IF(S18=5,T18*$AM$56,0)+IF(S18=6,T18*$AM$57,0)+IF(S18=7,T18*$AM$58,0)+IF(S18=8,T18*$AM$59,0)+IF(S18=9,T18*$AM$60,0)+IF(S18=10,T18*$AM$61,0) -> 0 | CR18: =IF(U18=1,V18*$AM$52,0)+IF(U18=2,V18*$AM$53,0)+IF(U18=3,V18*$AM$54,0)+IF(U18=4,V18*$AM$55,0)+IF(U18=5,V18*$AM$56,0)+IF(U18=6,V18*$AM$57,0)+IF(U18=7,V18*$AM$58,0)+IF(U18=8,V18*$AM$59,0)+IF(U18=9,V18*$AM$60,0)+IF(U18=10,V18*$AM$61,0) -> 0 | CS18: =IF(W18=1,X18*$AM$52,0)+IF(W18=2,X18*$AM$53,0)+IF(W18=3,X18*$AM$54,0)+IF(W18=4,X18*$AM$55,0)+IF(W18=5,X18*$AM$56,0)+IF(W18=6,X18*$AM$57,0)+IF(W18=7,X18*$AM$58,0)+IF(W18=8,X18*$AM$59,0)+IF(W18=9,X18*$AM$60,0)+IF(W18=10,X18*$AM$61,0) -> 0 | CT18: =IF(Y18=1,Z18*$AM$52,0)+IF(Y18=2,Z18*$AM$53,0)+IF(Y18=3,Z18*$AM$54,0)+IF(Y18=4,Z18*$AM$55,0)+IF(Y18=5,Z18*$AM$56,0)+IF(Y18=6,Z18*$AM$57,0)+IF(Y18=7,Z18*$AM$58,0)+IF(Y18=8,Z18*$AM$59,0)+IF(Y18=9,Z18*$AM$60,0)+IF(Y18=10,Z18*$AM$61,0) -> 0 | CU18: =IF(AA18=1,AB18*$AM$52,0)+IF(AA18=2,AB18*$AM$53,0)+IF(AA18=3,AB18*$AM$54,0)+IF(AA18=4,AB18*$AM$55,0)+IF(AA18=5,AB18*$AM$56,0)+IF(AA18=6,AB18*$AM$57,0)+IF(AA18=7,AB18*$AM$58,0)+IF(AA18=8,AB18*$AM$59,0)+IF(AA18=9,AB18*$AM$60,0)+IF(AA18=10,AB18*$AM$61,0) -> 0 | CV18: =D18 -> 0 | CW18: =SUM(CO18:CV18)*BG18 -> 0
O19: 9 | Q19: 10 | S19: 1 | T19: =K19 -> 0 | U19: 2 | W19: 3 | Y19: 4 | AA19: 5 | AC19: =IF(BG19=0,0,SUM(BD19:BE19)/BG19) -> 0 | AD19: =(D19*F19/324)*(1+K$71)+AV19 -> 0 | AE19: =IF(D19=0,0,AF19/D19) -> 0 | AF19: =SUM(BW19)*(1+M$64+Summary!P$64) -> 0 | AG19: =D19/AD19 -> #DIV/0! | AH19: =AF19*G19 -> 0 | AO19: =IF(O19=1,P19*$T$52,0)+IF(O19=2,P19*$T$53,0)+IF(O19=3,P19*$T$54,0)+IF(O19=4,P19*$T$55,0)+IF(O19=5,P19*$T$56,0)+IF(O19=6,P19*$T$57,0)+IF(O19=7,P19*$T$58,0)+IF(O19=8,P19*$T$59,0)+IF(O19=9,P19*$T$60,0)+IF(O19=10,P19*$T$61,0) -> 0 | AP19: =IF(Q19=1,R19*$T$52,0)+IF(Q19=2,R19*$T$53,0)+IF(Q19=3,R19*$T$54,0)+IF(Q19=4,R19*$T$55,0)+IF(Q19=5,R19*$T$56,0)+IF(Q19=6,R19*$T$57,0)+IF(Q19=7,R19*$T$58,0)+IF(Q19=8,R19*$T$59,0)+IF(Q19=9,R19*$T$60,0)+IF(Q19=10,R19*$T$61,0) -> 0 | AQ19: =IF(S19=1,T19*$T$52,0)+IF(S19=2,T19*$T$53,0)+IF(S19=3,T19*$T$54,0)+IF(S19=4,T19*$T$55,0)+IF(S19=5,T19*$T$56,0)+IF(S19=6,T19*$T$57,0)+IF(S19=7,T19*$T$58,0)+IF(S19=8,T19*$T$59,0)+IF(S19=9,T19*$T$60,0)+IF(S19=10,T19*$T$61,0) -> 0 | AR19: =IF(U19=1,V19*$T$52,0)+IF(U19=2,V19*$T$53,0)+IF(U19=3,V19*$T$54,0)+IF(U19=4,V19*$T$55,0)+IF(U19=5,V19*$T$56,0)+IF(U19=6,V19*$T$57,0)+IF(U19=7,V19*$T$58,0)+IF(U19=8,V19*$T$59,0)+IF(U19=9,V19*$T$60,0)+IF(U19=10,V19*$T$61,0) -> 0 | AS19: =IF(W19=1,X19*$T$52,0)+IF(W19=2,X19*$T$53,0)+IF(W19=3,X19*$T$54,0)+IF(W19=4,X19*$T$55,0)+IF(W19=5,X19*$T$56,0)+IF(W19=6,X19*$T$57,0)+IF(W19=7,X19*$T$58,0)+IF(W19=8,X19*$T$59,0)+IF(W19=9,X19*$T$60,0)+IF(W19=10,X19*$T$61,0) -> 0 | AT19: =IF(Y19=1,Z19*$T$52,0)+IF(Y19=2,Z19*$T$53,0)+IF(Y19=3,Z19*$T$54,0)+IF(Y19=4,Z19*$T$55,0)+IF(Y19=5,Z19*$T$56,0)+IF(Y19=6,Z19*$T$57,0)+IF(Y19=7,Z19*$T$58,0)+IF(Y19=8,Z19*$T$59,0)+IF(Y19=9,Z19*$T$60,0)+IF(Y19=10,Z19*$T$61,0) -> 0 | AU19: =IF(AA19=1,AB19*$T$52,0)+IF(AA19=2,AB19*$T$53,0)+IF(AA19=3,AB19*$T$54,0)+IF(AA19=4,AB19*$T$55,0)+IF(AA19=5,AB19*$T$56,0)+IF(AA19=6,AB19*$T$57,0)+IF(AA19=7,AB19*$T$58,0)+IF(AA19=8,AB19*$T$59,0)+IF(AA19=9,AB19*$T$60,0)+IF(AA19=10,AB19*$T$61,0) -> 0 | AV19: =SUM(AO19:AU19) -> 0 | AW19: =ROUNDUP(IF(O19=1,P19*$P$52,0)+IF(O19=2,P19*$P$53,0)+IF(O19=3,P19*$P$54,0)+IF(O19=4,P19*$P$55,0)+IF(O19=5,P19*$P$56,0)+IF(O19=6,P19*$P$57,0)+IF(O19=7,P19*$P$58,0)+IF(O19=8,P19*$P$59,0)+IF(O19=9,P19*$P$60,0)+IF(O19=10,P19*$P$61,0),0)*BG19 -> 0 | AX19: =ROUNDUP(IF(Q19=1,R19*$P$52,0)+IF(Q19=2,R19*$P$53,0)+IF(Q19=3,R19*$P$54,0)+IF(Q19=4,R19*$P$55,0)+IF(Q19=5,R19*$P$56,0)+IF(Q19=6,R19*$P$57,0)+IF(Q19=7,R19*$P$58,0)+IF(Q19=8,R19*$P$59,0)+IF(Q19=9,R19*$P$60,0)+IF(Q19=10,R19*$P$61,0),0) -> 0 | AY19: =ROUNDUP(IF(S19=1,T19*$P$52,0)+IF(S19=2,T19*$P$53,0)+IF(S19=3,T19*$P$54,0)+IF(S19=4,T19*$P$55,0)+IF(S19=5,T19*$P$56,0)+IF(S19=6,T19*$P$57,0)+IF(S19=7,T19*$P$58,0)+IF(S19=8,T19*$P$59,0)+IF(S19=9,T19*$P$60,0)+IF(S19=10,T19*$P$61,0),0) -> 0 | AZ19: =ROUNDUP(IF(U19=1,V19*$P$52,0)+IF(U19=2,V19*$P$53,0)+IF(U19=3,V19*$P$54,0)+IF(U19=4,V19*$P$55,0)+IF(U19=5,V19*$P$56,0)+IF(U19=6,V19*$P$57,0)+IF(U19=7,V19*$P$58,0)+IF(U19=8,V19*$P$59,0)+IF(U19=9,V19*$P$60,0)+IF(U19=10,V19*$P$61,0),0) -> 0 | BA19: =ROUNDUP(IF(W19=1,X19*$P$52,0)+IF(W19=2,X19*$P$53,0)+IF(W19=3,X19*$P$54,0)+IF(W19=4,X19*$P$55,0)+IF(W19=5,X19*$P$56,0)+IF(W19=6,X19*$P$57,0)+IF(W19=7,X19*$P$58,0)+IF(W19=8,X19*$P$59,0)+IF(W19=9,X19*$P$60,0)+IF(W19=10,X19*$P$61,0),0) -> 0 | BB19: =ROUNDUP(IF(Y19=1,Z19*$P$52,0)+IF(Y19=2,Z19*$P$53,0)+IF(Y19=3,Z19*$P$54,0)+IF(Y19=4,Z19*$P$55,0)+IF(Y19=5,Z19*$P$56,0)+IF(Y19=6,Z19*$P$57,0)+IF(Y19=7,Z19*$P$58,0)+IF(Y19=8,Z19*$P$59,0)+IF(Y19=9,Z19*$P$60,0)+IF(Y19=10,Z19*$P$61,0),0) -> 0 | BC19: =ROUNDUP(IF(AA19=1,AB19*$P$52,0)+IF(AA19=2,AB19*$P$53,0)+IF(AA19=3,AB19*$P$54,0)+IF(AA19=4,AB19*$P$55,0)+IF(AA19=5,AB19*$P$56,0)+IF(AA19=6,AB19*$P$57,0)+IF(AA19=7,AB19*$P$58,0)+IF(AA19=8,AB19*$P$59,0)+IF(AA19=9,AB19*$P$60,0)+IF(AA19=10,AB19*$P$61,0),0) -> 0 | BD19: =SUM(AW19:BC19)*BG19 -> 0 | BE19: =IF(M19=0,0,(M19/12+M19/12)/(M19/12*M19/12)*D19*((L19/16*L19/16)*10.6870159))*(1+K$74)*BG19 -> 0 | BF19: =IF(N19="Y",D19*(1+K$75)*BG19,0) -> 0 | BG19: =G19 -> 0 | BH19: =IF(N19="y",D19,0) -> 0 | BI19: =IF($I19=1,$AD19,0)*BG19 -> 0 | BJ19: =IF($I19=2,$AD19,0)*BG19 -> 0 | BK19: =IF($I19=3,$AD19,0)*BG19 -> 0 | BL19: =IF($I19=4,$AD19,0)*BG19 -> 0 | BM19: =IF($I19=5,$AD19,0)*BG19 -> 0 | BN19: =IF($I19=6,$AD19,0)*BG19 -> 0 | BO19: =SUM(BI19:BN19) -> 0 | BP19: =IF(H19="N",0,D19)*BG19 -> 0 | BQ19: =K19*BG19 -> 0 | BR19: =IF(O19=1,D$52*P19/12,IF(O19=2,D$53*P19/12,IF(O19=3,D$54*P19/12,IF(O19=4,D$55*P19/12,IF(O19=5,D$56*P19/12,IF(O19=6,D$57*P19/12,IF(O19=7,D$58*P19/12,IF(O19=8,D$59*P19/12,IF(O19=9,D$60*P19/12,IF(O19=10,D$61*P19/12,0))))))*BG19)))) -> 0 | BS19: =IF(Q19=1,D$52*R19/12,IF(Q19=2,D$53*R19/12,IF(Q19=3,D$54*R19/12,IF(Q19=4,D$55*R19/12,IF(Q19=5,D$56*R19/12,IF(Q19=6,D$57*R19/12,IF(Q19=7,D$58*R19/12,IF(Q19=8,D$59*R19/12,IF(Q19=9,D$60*R19/12,IF(Q19=10,D$61*R19/12,0))))))*BG19)))) -> 0 | BT19: =D19*BG19 -> 0 | BU19: =D19*J19/324*(1+K$77)*BG19 -> 0 | BV19: =AC19*BG19 -> 0 | BW19: =IF(BG19=0,0,SUM(BX19:CM19)/BG19) -> 0 | BX19: =(BI19*Pricing!F$2+BJ19*Pricing!G$2+BK19*Pricing!H$2+BL19*Pricing!I$2+BM19*Pricing!J$2+BN19*Pricing!K$2)*IF(AC$63="N",(1+AE$63),1) -> 0 | BY19: =AC19*G$74*IF(AC$63="n",1+AE$63,1)*BG19 -> 0 | BZ19: =IF(I$83=0,0,D19*(SUM(L$83:M$86)+L$88)/I$83*BG19) -> 0 | CA19: =IF(I$83=0,0,D19*(SUM(O$83:P$86)+O$88)/I$83*BG19) -> 0 | CB19: =BR19+BS19*E$87 -> 0 | CD19: =BD19/2000*E$89 -> 0 | CE19: =IF(D$49=0,0,SUM(O$92:P$96)/D$49*D19)*BG19 -> 0 | CF19: =IF(D$49=0,0,SUM(AF$72:AF$99)/D$49*D19*BG19) -> 0 | CG19: =IF(D$49=0,0,SUM(O$98:P$103)/D$49*D19)*BG19 -> 0 | CH19: =IF(D$49=0,0,SUM(O$105:O$111)/D$49)*D19*BG19 -> 0 | CI19: =IF(D$49=0,0,SUM(AF$100:AF$111)/D$49*D19*BG19) -> 0 | CJ19: =IF(J$76>0,J$76/D$49*D19*G19,BP19*(G$76*(1+AE$63))) -> 0 | CK19: =IF(L$78=0,0,O$78/L$78)*AW19+IF(L$79=0,0,O$79/L$79)*BC19+IF(L$80=0,0,O$80/L$80)*BC19 -> 0 | CL19: =BF19*G$75*IF(AC$63="Y",1,1+AE$63) -> 0 | CM19: =BU19*G$77*IF(AC$63="Y",1,1+AE$63) -> 0 | CO19: =IF(O19=1,P19*$AM$52,0)+IF(O19=2,P19*$AM$53,0)+IF(O19=3,P19*$AM$54,0)+IF(O19=4,P19*$AM$55,0)+IF(O19=5,P19*$AM$56,0)+IF(O19=6,P19*$AM$57,0)+IF(O19=7,P19*$AM$58,0)+IF(O19=8,P19*$AM$59,0)+IF(O19=9,P19*$AM$60,0)+IF(O19=10,P19*$AM$61,0) -> 0 | CP19: =IF(Q19=1,R19*$AM$52,0)+IF(Q19=2,R19*$AM$53,0)+IF(Q19=3,R19*$AM$54,0)+IF(Q19=4,R19*$AM$55,0)+IF(Q19=5,R19*$AM$56,0)+IF(Q19=6,R19*$AM$57,0)+IF(Q19=7,R19*$AM$58,0)+IF(Q19=8,R19*$AM$59,0)+IF(Q19=9,R19*$AM$60,0)+IF(Q19=10,R19*$AM$61,0) -> 0 | CQ19: =IF(S19=1,T19*$AM$52,0)+IF(S19=2,T19*$AM$53,0)+IF(S19=3,T19*$AM$54,0)+IF(S19=4,T19*$AM$55,0)+IF(S19=5,T19*$AM$56,0)+IF(S19=6,T19*$AM$57,0)+IF(S19=7,T19*$AM$58,0)+IF(S19=8,T19*$AM$59,0)+IF(S19=9,T19*$AM$60,0)+IF(S19=10,T19*$AM$61,0) -> 0 | CR19: =IF(U19=1,V19*$AM$52,0)+IF(U19=2,V19*$AM$53,0)+IF(U19=3,V19*$AM$54,0)+IF(U19=4,V19*$AM$55,0)+IF(U19=5,V19*$AM$56,0)+IF(U19=6,V19*$AM$57,0)+IF(U19=7,V19*$AM$58,0)+IF(U19=8,V19*$AM$59,0)+IF(U19=9,V19*$AM$60,0)+IF(U19=10,V19*$AM$61,0) -> 0 | CS19: =IF(W19=1,X19*$AM$52,0)+IF(W19=2,X19*$AM$53,0)+IF(W19=3,X19*$AM$54,0)+IF(W19=4,X19*$AM$55,0)+IF(W19=5,X19*$AM$56,0)+IF(W19=6,X19*$AM$57,0)+IF(W19=7,X19*$AM$58,0)+IF(W19=8,X19*$AM$59,0)+IF(W19=9,X19*$AM$60,0)+IF(W19=10,X19*$AM$61,0) -> 0 | CT19: =IF(Y19=1,Z19*$AM$52,0)+IF(Y19=2,Z19*$AM$53,0)+IF(Y19=3,Z19*$AM$54,0)+IF(Y19=4,Z19*$AM$55,0)+IF(Y19=5,Z19*$AM$56,0)+IF(Y19=6,Z19*$AM$57,0)+IF(Y19=7,Z19*$AM$58,0)+IF(Y19=8,Z19*$AM$59,0)+IF(Y19=9,Z19*$AM$60,0)+IF(Y19=10,Z19*$AM$61,0) -> 0 | CU19: =IF(AA19=1,AB19*$AM$52,0)+IF(AA19=2,AB19*$AM$53,0)+IF(AA19=3,AB19*$AM$54,0)+IF(AA19=4,AB19*$AM$55,0)+IF(AA19=5,AB19*$AM$56,0)+IF(AA19=6,AB19*$AM$57,0)+IF(AA19=7,AB19*$AM$58,0)+IF(AA19=8,AB19*$AM$59,0)+IF(AA19=9,AB19*$AM$60,0)+IF(AA19=10,AB19*$AM$61,0) -> 0 | CV19: =D19 -> 0 | CW19: =SUM(CO19:CV19)*BG19 -> 0
O20: 9 | Q20: 10 | S20: 1 | T20: =K20 -> 0 | U20: 2 | W20: 3 | Y20: 4 | AA20: 5 | AC20: =IF(BG20=0,0,SUM(BD20:BE20)/BG20) -> 0 | AD20: =(D20*F20/324)*(1+K$71)+AV20 -> 0 | AE20: =IF(D20=0,0,AF20/D20) -> 0 | AF20: =SUM(BW20)*(1+M$64+Summary!P$64) -> 0 | AG20: =D20/AD20 -> #DIV/0! | AH20: =AF20*G20 -> 0 | AO20: =IF(O20=1,P20*$T$52,0)+IF(O20=2,P20*$T$53,0)+IF(O20=3,P20*$T$54,0)+IF(O20=4,P20*$T$55,0)+IF(O20=5,P20*$T$56,0)+IF(O20=6,P20*$T$57,0)+IF(O20=7,P20*$T$58,0)+IF(O20=8,P20*$T$59,0)+IF(O20=9,P20*$T$60,0)+IF(O20=10,P20*$T$61,0) -> 0 | AP20: =IF(Q20=1,R20*$T$52,0)+IF(Q20=2,R20*$T$53,0)+IF(Q20=3,R20*$T$54,0)+IF(Q20=4,R20*$T$55,0)+IF(Q20=5,R20*$T$56,0)+IF(Q20=6,R20*$T$57,0)+IF(Q20=7,R20*$T$58,0)+IF(Q20=8,R20*$T$59,0)+IF(Q20=9,R20*$T$60,0)+IF(Q20=10,R20*$T$61,0) -> 0 | AQ20: =IF(S20=1,T20*$T$52,0)+IF(S20=2,T20*$T$53,0)+IF(S20=3,T20*$T$54,0)+IF(S20=4,T20*$T$55,0)+IF(S20=5,T20*$T$56,0)+IF(S20=6,T20*$T$57,0)+IF(S20=7,T20*$T$58,0)+IF(S20=8,T20*$T$59,0)+IF(S20=9,T20*$T$60,0)+IF(S20=10,T20*$T$61,0) -> 0 | AR20: =IF(U20=1,V20*$T$52,0)+IF(U20=2,V20*$T$53,0)+IF(U20=3,V20*$T$54,0)+IF(U20=4,V20*$T$55,0)+IF(U20=5,V20*$T$56,0)+IF(U20=6,V20*$T$57,0)+IF(U20=7,V20*$T$58,0)+IF(U20=8,V20*$T$59,0)+IF(U20=9,V20*$T$60,0)+IF(U20=10,V20*$T$61,0) -> 0 | AS20: =IF(W20=1,X20*$T$52,0)+IF(W20=2,X20*$T$53,0)+IF(W20=3,X20*$T$54,0)+IF(W20=4,X20*$T$55,0)+IF(W20=5,X20*$T$56,0)+IF(W20=6,X20*$T$57,0)+IF(W20=7,X20*$T$58,0)+IF(W20=8,X20*$T$59,0)+IF(W20=9,X20*$T$60,0)+IF(W20=10,X20*$T$61,0) -> 0 | AT20: =IF(Y20=1,Z20*$T$52,0)+IF(Y20=2,Z20*$T$53,0)+IF(Y20=3,Z20*$T$54,0)+IF(Y20=4,Z20*$T$55,0)+IF(Y20=5,Z20*$T$56,0)+IF(Y20=6,Z20*$T$57,0)+IF(Y20=7,Z20*$T$58,0)+IF(Y20=8,Z20*$T$59,0)+IF(Y20=9,Z20*$T$60,0)+IF(Y20=10,Z20*$T$61,0) -> 0 | AU20: =IF(AA20=1,AB20*$T$52,0)+IF(AA20=2,AB20*$T$53,0)+IF(AA20=3,AB20*$T$54,0)+IF(AA20=4,AB20*$T$55,0)+IF(AA20=5,AB20*$T$56,0)+IF(AA20=6,AB20*$T$57,0)+IF(AA20=7,AB20*$T$58,0)+IF(AA20=8,AB20*$T$59,0)+IF(AA20=9,AB20*$T$60,0)+IF(AA20=10,AB20*$T$61,0) -> 0 | AV20: =SUM(AO20:AU20) -> 0 | AW20: =ROUNDUP(IF(O20=1,P20*$P$52,0)+IF(O20=2,P20*$P$53,0)+IF(O20=3,P20*$P$54,0)+IF(O20=4,P20*$P$55,0)+IF(O20=5,P20*$P$56,0)+IF(O20=6,P20*$P$57,0)+IF(O20=7,P20*$P$58,0)+IF(O20=8,P20*$P$59,0)+IF(O20=9,P20*$P$60,0)+IF(O20=10,P20*$P$61,0),0)*BG20 -> 0 | AX20: =ROUNDUP(IF(Q20=1,R20*$P$52,0)+IF(Q20=2,R20*$P$53,0)+IF(Q20=3,R20*$P$54,0)+IF(Q20=4,R20*$P$55,0)+IF(Q20=5,R20*$P$56,0)+IF(Q20=6,R20*$P$57,0)+IF(Q20=7,R20*$P$58,0)+IF(Q20=8,R20*$P$59,0)+IF(Q20=9,R20*$P$60,0)+IF(Q20=10,R20*$P$61,0),0) -> 0 | AY20: =ROUNDUP(IF(S20=1,T20*$P$52,0)+IF(S20=2,T20*$P$53,0)+IF(S20=3,T20*$P$54,0)+IF(S20=4,T20*$P$55,0)+IF(S20=5,T20*$P$56,0)+IF(S20=6,T20*$P$57,0)+IF(S20=7,T20*$P$58,0)+IF(S20=8,T20*$P$59,0)+IF(S20=9,T20*$P$60,0)+IF(S20=10,T20*$P$61,0),0) -> 0 | AZ20: =ROUNDUP(IF(U20=1,V20*$P$52,0)+IF(U20=2,V20*$P$53,0)+IF(U20=3,V20*$P$54,0)+IF(U20=4,V20*$P$55,0)+IF(U20=5,V20*$P$56,0)+IF(U20=6,V20*$P$57,0)+IF(U20=7,V20*$P$58,0)+IF(U20=8,V20*$P$59,0)+IF(U20=9,V20*$P$60,0)+IF(U20=10,V20*$P$61,0),0) -> 0 | BA20: =ROUNDUP(IF(W20=1,X20*$P$52,0)+IF(W20=2,X20*$P$53,0)+IF(W20=3,X20*$P$54,0)+IF(W20=4,X20*$P$55,0)+IF(W20=5,X20*$P$56,0)+IF(W20=6,X20*$P$57,0)+IF(W20=7,X20*$P$58,0)+IF(W20=8,X20*$P$59,0)+IF(W20=9,X20*$P$60,0)+IF(W20=10,X20*$P$61,0),0) -> 0 | BB20: =ROUNDUP(IF(Y20=1,Z20*$P$52,0)+IF(Y20=2,Z20*$P$53,0)+IF(Y20=3,Z20*$P$54,0)+IF(Y20=4,Z20*$P$55,0)+IF(Y20=5,Z20*$P$56,0)+IF(Y20=6,Z20*$P$57,0)+IF(Y20=7,Z20*$P$58,0)+IF(Y20=8,Z20*$P$59,0)+IF(Y20=9,Z20*$P$60,0)+IF(Y20=10,Z20*$P$61,0),0) -> 0 | BC20: =ROUNDUP(IF(AA20=1,AB20*$P$52,0)+IF(AA20=2,AB20*$P$53,0)+IF(AA20=3,AB20*$P$54,0)+IF(AA20=4,AB20*$P$55,0)+IF(AA20=5,AB20*$P$56,0)+IF(AA20=6,AB20*$P$57,0)+IF(AA20=7,AB20*$P$58,0)+IF(AA20=8,AB20*$P$59,0)+IF(AA20=9,AB20*$P$60,0)+IF(AA20=10,AB20*$P$61,0),0) -> 0 | BD20: =SUM(AW20:BC20)*BG20 -> 0 | BE20: =IF(M20=0,0,(M20/12+M20/12)/(M20/12*M20/12)*D20*((L20/16*L20/16)*10.6870159))*(1+K$74)*BG20 -> 0 | BF20: =IF(N20="Y",D20*(1+K$75)*BG20,0) -> 0 | BG20: =G20 -> 0 | BH20: =IF(N20="y",D20,0) -> 0 | BI20: =IF($I20=1,$AD20,0)*BG20 -> 0 | BJ20: =IF($I20=2,$AD20,0)*BG20 -> 0 | BK20: =IF($I20=3,$AD20,0)*BG20 -> 0 | BL20: =IF($I20=4,$AD20,0)*BG20 -> 0 | BM20: =IF($I20=5,$AD20,0)*BG20 -> 0 | BN20: =IF($I20=6,$AD20,0)*BG20 -> 0 | BO20: =SUM(BI20:BN20) -> 0 | BP20: =IF(H20="N",0,D20)*BG20 -> 0 | BQ20: =K20*BG20 -> 0 | BR20: =IF(O20=1,D$52*P20/12,IF(O20=2,D$53*P20/12,IF(O20=3,D$54*P20/12,IF(O20=4,D$55*P20/12,IF(O20=5,D$56*P20/12,IF(O20=6,D$57*P20/12,IF(O20=7,D$58*P20/12,IF(O20=8,D$59*P20/12,IF(O20=9,D$60*P20/12,IF(O20=10,D$61*P20/12,0))))))*BG20)))) -> 0 | BS20: =IF(Q20=1,D$52*R20/12,IF(Q20=2,D$53*R20/12,IF(Q20=3,D$54*R20/12,IF(Q20=4,D$55*R20/12,IF(Q20=5,D$56*R20/12,IF(Q20=6,D$57*R20/12,IF(Q20=7,D$58*R20/12,IF(Q20=8,D$59*R20/12,IF(Q20=9,D$60*R20/12,IF(Q20=10,D$61*R20/12,0))))))*BG20)))) -> 0 | BT20: =D20*BG20 -> 0 | BU20: =D20*J20/324*(1+K$77)*BG20 -> 0 | BV20: =AC20*BG20 -> 0 | BW20: =IF(BG20=0,0,SUM(BX20:CM20)/BG20) -> 0 | BX20: =(BI20*Pricing!F$2+BJ20*Pricing!G$2+BK20*Pricing!H$2+BL20*Pricing!I$2+BM20*Pricing!J$2+BN20*Pricing!K$2)*IF(AC$63="N",(1+AE$63),1) -> 0 | BY20: =AC20*G$74*IF(AC$63="n",1+AE$63,1)*BG20 -> 0 | BZ20: =IF(I$83=0,0,D20*(SUM(L$83:M$86)+L$88)/I$83*BG20) -> 0 | CA20: =IF(I$83=0,0,D20*(SUM(O$83:P$86)+O$88)/I$83*BG20) -> 0 | CB20: =BR20+BS20*E$87 -> 0 | CD20: =BD20/2000*E$89 -> 0 | CE20: =IF(D$49=0,0,SUM(O$92:P$96)/D$49*D20)*BG20 -> 0 | CF20: =IF(D$49=0,0,SUM(AF$72:AF$99)/D$49*D20*BG20) -> 0 | CG20: =IF(D$49=0,0,SUM(O$98:P$103)/D$49*D20)*BG20 -> 0 | CH20: =IF(D$49=0,0,SUM(O$105:O$111)/D$49)*D20*BG20 -> 0 | CI20: =IF(D$49=0,0,SUM(AF$100:AF$111)/D$49*D20*BG20) -> 0 | CJ20: =IF(J$76>0,J$76/D$49*D20*G20,BP20*(G$76*(1+AE$63))) -> 0 | CK20: =IF(L$78=0,0,O$78/L$78)*AW20+IF(L$79=0,0,O$79/L$79)*BC20+IF(L$80=0,0,O$80/L$80)*BC20 -> 0 | CL20: =BF20*G$75*IF(AC$63="Y",1,1+AE$63) -> 0 | CM20: =BU20*G$77*IF(AC$63="Y",1,1+AE$63) -> 0 | CO20: =IF(O20=1,P20*$AM$52,0)+IF(O20=2,P20*$AM$53,0)+IF(O20=3,P20*$AM$54,0)+IF(O20=4,P20*$AM$55,0)+IF(O20=5,P20*$AM$56,0)+IF(O20=6,P20*$AM$57,0)+IF(O20=7,P20*$AM$58,0)+IF(O20=8,P20*$AM$59,0)+IF(O20=9,P20*$AM$60,0)+IF(O20=10,P20*$AM$61,0) -> 0 | CP20: =IF(Q20=1,R20*$AM$52,0)+IF(Q20=2,R20*$AM$53,0)+IF(Q20=3,R20*$AM$54,0)+IF(Q20=4,R20*$AM$55,0)+IF(Q20=5,R20*$AM$56,0)+IF(Q20=6,R20*$AM$57,0)+IF(Q20=7,R20*$AM$58,0)+IF(Q20=8,R20*$AM$59,0)+IF(Q20=9,R20*$AM$60,0)+IF(Q20=10,R20*$AM$61,0) -> 0 | CQ20: =IF(S20=1,T20*$AM$52,0)+IF(S20=2,T20*$AM$53,0)+IF(S20=3,T20*$AM$54,0)+IF(S20=4,T20*$AM$55,0)+IF(S20=5,T20*$AM$56,0)+IF(S20=6,T20*$AM$57,0)+IF(S20=7,T20*$AM$58,0)+IF(S20=8,T20*$AM$59,0)+IF(S20=9,T20*$AM$60,0)+IF(S20=10,T20*$AM$61,0) -> 0 | CR20: =IF(U20=1,V20*$AM$52,0)+IF(U20=2,V20*$AM$53,0)+IF(U20=3,V20*$AM$54,0)+IF(U20=4,V20*$AM$55,0)+IF(U20=5,V20*$AM$56,0)+IF(U20=6,V20*$AM$57,0)+IF(U20=7,V20*$AM$58,0)+IF(U20=8,V20*$AM$59,0)+IF(U20=9,V20*$AM$60,0)+IF(U20=10,V20*$AM$61,0) -> 0 | CS20: =IF(W20=1,X20*$AM$52,0)+IF(W20=2,X20*$AM$53,0)+IF(W20=3,X20*$AM$54,0)+IF(W20=4,X20*$AM$55,0)+IF(W20=5,X20*$AM$56,0)+IF(W20=6,X20*$AM$57,0)+IF(W20=7,X20*$AM$58,0)+IF(W20=8,X20*$AM$59,0)+IF(W20=9,X20*$AM$60,0)+IF(W20=10,X20*$AM$61,0) -> 0 | CT20: =IF(Y20=1,Z20*$AM$52,0)+IF(Y20=2,Z20*$AM$53,0)+IF(Y20=3,Z20*$AM$54,0)+IF(Y20=4,Z20*$AM$55,0)+IF(Y20=5,Z20*$AM$56,0)+IF(Y20=6,Z20*$AM$57,0)+IF(Y20=7,Z20*$AM$58,0)+IF(Y20=8,Z20*$AM$59,0)+IF(Y20=9,Z20*$AM$60,0)+IF(Y20=10,Z20*$AM$61,0) -> 0 | CU20: =IF(AA20=1,AB20*$AM$52,0)+IF(AA20=2,AB20*$AM$53,0)+IF(AA20=3,AB20*$AM$54,0)+IF(AA20=4,AB20*$AM$55,0)+IF(AA20=5,AB20*$AM$56,0)+IF(AA20=6,AB20*$AM$57,0)+IF(AA20=7,AB20*$AM$58,0)+IF(AA20=8,AB20*$AM$59,0)+IF(AA20=9,AB20*$AM$60,0)+IF(AA20=10,AB20*$AM$61,0) -> 0 | CV20: =D20 -> 0 | CW20: =SUM(CO20:CV20)*BG20 -> 0
O21: 9 | Q21: 10 | S21: 1 | T21: =K21 -> 0 | U21: 2 | W21: 3 | Y21: 4 | AA21: 5 | AC21: =IF(BG21=0,0,SUM(BD21:BE21)/BG21) -> 0 | AD21: =(D21*F21/324)*(1+K$71)+AV21 -> 0 | AE21: =IF(D21=0,0,AF21/D21) -> 0 | AF21: =SUM(BW21)*(1+M$64+Summary!P$64) -> 0 | AG21: =D21/AD21 -> #DIV/0! | AH21: =AF21*G21 -> 0 | AO21: =IF(O21=1,P21*$T$52,0)+IF(O21=2,P21*$T$53,0)+IF(O21=3,P21*$T$54,0)+IF(O21=4,P21*$T$55,0)+IF(O21=5,P21*$T$56,0)+IF(O21=6,P21*$T$57,0)+IF(O21=7,P21*$T$58,0)+IF(O21=8,P21*$T$59,0)+IF(O21=9,P21*$T$60,0)+IF(O21=10,P21*$T$61,0) -> 0 | AP21: =IF(Q21=1,R21*$T$52,0)+IF(Q21=2,R21*$T$53,0)+IF(Q21=3,R21*$T$54,0)+IF(Q21=4,R21*$T$55,0)+IF(Q21=5,R21*$T$56,0)+IF(Q21=6,R21*$T$57,0)+IF(Q21=7,R21*$T$58,0)+IF(Q21=8,R21*$T$59,0)+IF(Q21=9,R21*$T$60,0)+IF(Q21=10,R21*$T$61,0) -> 0 | AQ21: =IF(S21=1,T21*$T$52,0)+IF(S21=2,T21*$T$53,0)+IF(S21=3,T21*$T$54,0)+IF(S21=4,T21*$T$55,0)+IF(S21=5,T21*$T$56,0)+IF(S21=6,T21*$T$57,0)+IF(S21=7,T21*$T$58,0)+IF(S21=8,T21*$T$59,0)+IF(S21=9,T21*$T$60,0)+IF(S21=10,T21*$T$61,0) -> 0 | AR21: =IF(U21=1,V21*$T$52,0)+IF(U21=2,V21*$T$53,0)+IF(U21=3,V21*$T$54,0)+IF(U21=4,V21*$T$55,0)+IF(U21=5,V21*$T$56,0)+IF(U21=6,V21*$T$57,0)+IF(U21=7,V21*$T$58,0)+IF(U21=8,V21*$T$59,0)+IF(U21=9,V21*$T$60,0)+IF(U21=10,V21*$T$61,0) -> 0 | AS21: =IF(W21=1,X21*$T$52,0)+IF(W21=2,X21*$T$53,0)+IF(W21=3,X21*$T$54,0)+IF(W21=4,X21*$T$55,0)+IF(W21=5,X21*$T$56,0)+IF(W21=6,X21*$T$57,0)+IF(W21=7,X21*$T$58,0)+IF(W21=8,X21*$T$59,0)+IF(W21=9,X21*$T$60,0)+IF(W21=10,X21*$T$61,0) -> 0 | AT21: =IF(Y21=1,Z21*$T$52,0)+IF(Y21=2,Z21*$T$53,0)+IF(Y21=3,Z21*$T$54,0)+IF(Y21=4,Z21*$T$55,0)+IF(Y21=5,Z21*$T$56,0)+IF(Y21=6,Z21*$T$57,0)+IF(Y21=7,Z21*$T$58,0)+IF(Y21=8,Z21*$T$59,0)+IF(Y21=9,Z21*$T$60,0)+IF(Y21=10,Z21*$T$61,0) -> 0 | AU21: =IF(AA21=1,AB21*$T$52,0)+IF(AA21=2,AB21*$T$53,0)+IF(AA21=3,AB21*$T$54,0)+IF(AA21=4,AB21*$T$55,0)+IF(AA21=5,AB21*$T$56,0)+IF(AA21=6,AB21*$T$57,0)+IF(AA21=7,AB21*$T$58,0)+IF(AA21=8,AB21*$T$59,0)+IF(AA21=9,AB21*$T$60,0)+IF(AA21=10,AB21*$T$61,0) -> 0 | AV21: =SUM(AO21:AU21) -> 0 | AW21: =ROUNDUP(IF(O21=1,P21*$P$52,0)+IF(O21=2,P21*$P$53,0)+IF(O21=3,P21*$P$54,0)+IF(O21=4,P21*$P$55,0)+IF(O21=5,P21*$P$56,0)+IF(O21=6,P21*$P$57,0)+IF(O21=7,P21*$P$58,0)+IF(O21=8,P21*$P$59,0)+IF(O21=9,P21*$P$60,0)+IF(O21=10,P21*$P$61,0),0)*BG21 -> 0 | AX21: =ROUNDUP(IF(Q21=1,R21*$P$52,0)+IF(Q21=2,R21*$P$53,0)+IF(Q21=3,R21*$P$54,0)+IF(Q21=4,R21*$P$55,0)+IF(Q21=5,R21*$P$56,0)+IF(Q21=6,R21*$P$57,0)+IF(Q21=7,R21*$P$58,0)+IF(Q21=8,R21*$P$59,0)+IF(Q21=9,R21*$P$60,0)+IF(Q21=10,R21*$P$61,0),0) -> 0 | AY21: =ROUNDUP(IF(S21=1,T21*$P$52,0)+IF(S21=2,T21*$P$53,0)+IF(S21=3,T21*$P$54,0)+IF(S21=4,T21*$P$55,0)+IF(S21=5,T21*$P$56,0)+IF(S21=6,T21*$P$57,0)+IF(S21=7,T21*$P$58,0)+IF(S21=8,T21*$P$59,0)+IF(S21=9,T21*$P$60,0)+IF(S21=10,T21*$P$61,0),0) -> 0 | AZ21: =ROUNDUP(IF(U21=1,V21*$P$52,0)+IF(U21=2,V21*$P$53,0)+IF(U21=3,V21*$P$54,0)+IF(U21=4,V21*$P$55,0)+IF(U21=5,V21*$P$56,0)+IF(U21=6,V21*$P$57,0)+IF(U21=7,V21*$P$58,0)+IF(U21=8,V21*$P$59,0)+IF(U21=9,V21*$P$60,0)+IF(U21=10,V21*$P$61,0),0) -> 0 | BA21: =ROUNDUP(IF(W21=1,X21*$P$52,0)+IF(W21=2,X21*$P$53,0)+IF(W21=3,X21*$P$54,0)+IF(W21=4,X21*$P$55,0)+IF(W21=5,X21*$P$56,0)+IF(W21=6,X21*$P$57,0)+IF(W21=7,X21*$P$58,0)+IF(W21=8,X21*$P$59,0)+IF(W21=9,X21*$P$60,0)+IF(W21=10,X21*$P$61,0),0) -> 0 | BB21: =ROUNDUP(IF(Y21=1,Z21*$P$52,0)+IF(Y21=2,Z21*$P$53,0)+IF(Y21=3,Z21*$P$54,0)+IF(Y21=4,Z21*$P$55,0)+IF(Y21=5,Z21*$P$56,0)+IF(Y21=6,Z21*$P$57,0)+IF(Y21=7,Z21*$P$58,0)+IF(Y21=8,Z21*$P$59,0)+IF(Y21=9,Z21*$P$60,0)+IF(Y21=10,Z21*$P$61,0),0) -> 0 | BC21: =ROUNDUP(IF(AA21=1,AB21*$P$52,0)+IF(AA21=2,AB21*$P$53,0)+IF(AA21=3,AB21*$P$54,0)+IF(AA21=4,AB21*$P$55,0)+IF(AA21=5,AB21*$P$56,0)+IF(AA21=6,AB21*$P$57,0)+IF(AA21=7,AB21*$P$58,0)+IF(AA21=8,AB21*$P$59,0)+IF(AA21=9,AB21*$P$60,0)+IF(AA21=10,AB21*$P$61,0),0) -> 0 | BD21: =SUM(AW21:BC21)*BG21 -> 0 | BE21: =IF(M21=0,0,(M21/12+M21/12)/(M21/12*M21/12)*D21*((L21/16*L21/16)*10.6870159))*(1+K$74)*BG21 -> 0 | BF21: =IF(N21="Y",D21*(1+K$75)*BG21,0) -> 0 | BG21: =G21 -> 0 | BH21: =IF(N21="y",D21,0) -> 0 | BI21: =IF($I21=1,$AD21,0)*BG21 -> 0 | BJ21: =IF($I21=2,$AD21,0)*BG21 -> 0 | BK21: =IF($I21=3,$AD21,0)*BG21 -> 0 | BL21: =IF($I21=4,$AD21,0)*BG21 -> 0 | BM21: =IF($I21=5,$AD21,0)*BG21 -> 0 | BN21: =IF($I21=6,$AD21,0)*BG21 -> 0 | BO21: =SUM(BI21:BN21) -> 0 | BP21: =IF(H21="N",0,D21)*BG21 -> 0 | BQ21: =K21*BG21 -> 0 | BR21: =IF(O21=1,D$52*P21/12,IF(O21=2,D$53*P21/12,IF(O21=3,D$54*P21/12,IF(O21=4,D$55*P21/12,IF(O21=5,D$56*P21/12,IF(O21=6,D$57*P21/12,IF(O21=7,D$58*P21/12,IF(O21=8,D$59*P21/12,IF(O21=9,D$60*P21/12,IF(O21=10,D$61*P21/12,0))))))*BG21)))) -> 0 | BS21: =IF(Q21=1,D$52*R21/12,IF(Q21=2,D$53*R21/12,IF(Q21=3,D$54*R21/12,IF(Q21=4,D$55*R21/12,IF(Q21=5,D$56*R21/12,IF(Q21=6,D$57*R21/12,IF(Q21=7,D$58*R21/12,IF(Q21=8,D$59*R21/12,IF(Q21=9,D$60*R21/12,IF(Q21=10,D$61*R21/12,0))))))*BG21)))) -> 0 | BT21: =D21*BG21 -> 0 | BU21: =D21*J21/324*(1+K$77)*BG21 -> 0 | BV21: =AC21*BG21 -> 0 | BW21: =IF(BG21=0,0,SUM(BX21:CM21)/BG21) -> 0 | BX21: =(BI21*Pricing!F$2+BJ21*Pricing!G$2+BK21*Pricing!H$2+BL21*Pricing!I$2+BM21*Pricing!J$2+BN21*Pricing!K$2)*IF(AC$63="N",(1+AE$63),1) -> 0 | BY21: =AC21*G$74*IF(AC$63="n",1+AE$63,1)*BG21 -> 0 | BZ21: =IF(I$83=0,0,D21*(SUM(L$83:M$86)+L$88)/I$83*BG21) -> 0 | CA21: =IF(I$83=0,0,D21*(SUM(O$83:P$86)+O$88)/I$83*BG21) -> 0 | CB21: =BR21+BS21*E$87 -> 0 | CD21: =BD21/2000*E$89 -> 0 | CE21: =IF(D$49=0,0,SUM(O$92:P$96)/D$49*D21)*BG21 -> 0 | CF21: =IF(D$49=0,0,SUM(AF$72:AF$99)/D$49*D21*BG21) -> 0 | CG21: =IF(D$49=0,0,SUM(O$98:P$103)/D$49*D21)*BG21 -> 0 | CH21: =IF(D$49=0,0,SUM(O$105:O$111)/D$49)*D21*BG21 -> 0 | CI21: =IF(D$49=0,0,SUM(AF$100:AF$111)/D$49*D21*BG21) -> 0 | CJ21: =IF(J$76>0,J$76/D$49*D21*G21,BP21*(G$76*(1+AE$63))) -> 0 | CK21: =IF(L$78=0,0,O$78/L$78)*AW21+IF(L$79=0,0,O$79/L$79)*BC21+IF(L$80=0,0,O$80/L$80)*BC21 -> 0 | CL21: =BF21*G$75*IF(AC$63="Y",1,1+AE$63) -> 0 | CM21: =BU21*G$77*IF(AC$63="Y",1,1+AE$63) -> 0 | CO21: =IF(O21=1,P21*$AM$52,0)+IF(O21=2,P21*$AM$53,0)+IF(O21=3,P21*$AM$54,0)+IF(O21=4,P21*$AM$55,0)+IF(O21=5,P21*$AM$56,0)+IF(O21=6,P21*$AM$57,0)+IF(O21=7,P21*$AM$58,0)+IF(O21=8,P21*$AM$59,0)+IF(O21=9,P21*$AM$60,0)+IF(O21=10,P21*$AM$61,0) -> 0 | CP21: =IF(Q21=1,R21*$AM$52,0)+IF(Q21=2,R21*$AM$53,0)+IF(Q21=3,R21*$AM$54,0)+IF(Q21=4,R21*$AM$55,0)+IF(Q21=5,R21*$AM$56,0)+IF(Q21=6,R21*$AM$57,0)+IF(Q21=7,R21*$AM$58,0)+IF(Q21=8,R21*$AM$59,0)+IF(Q21=9,R21*$AM$60,0)+IF(Q21=10,R21*$AM$61,0) -> 0 | CQ21: =IF(S21=1,T21*$AM$52,0)+IF(S21=2,T21*$AM$53,0)+IF(S21=3,T21*$AM$54,0)+IF(S21=4,T21*$AM$55,0)+IF(S21=5,T21*$AM$56,0)+IF(S21=6,T21*$AM$57,0)+IF(S21=7,T21*$AM$58,0)+IF(S21=8,T21*$AM$59,0)+IF(S21=9,T21*$AM$60,0)+IF(S21=10,T21*$AM$61,0) -> 0 | CR21: =IF(U21=1,V21*$AM$52,0)+IF(U21=2,V21*$AM$53,0)+IF(U21=3,V21*$AM$54,0)+IF(U21=4,V21*$AM$55,0)+IF(U21=5,V21*$AM$56,0)+IF(U21=6,V21*$AM$57,0)+IF(U21=7,V21*$AM$58,0)+IF(U21=8,V21*$AM$59,0)+IF(U21=9,V21*$AM$60,0)+IF(U21=10,V21*$AM$61,0) -> 0 | CS21: =IF(W21=1,X21*$AM$52,0)+IF(W21=2,X21*$AM$53,0)+IF(W21=3,X21*$AM$54,0)+IF(W21=4,X21*$AM$55,0)+IF(W21=5,X21*$AM$56,0)+IF(W21=6,X21*$AM$57,0)+IF(W21=7,X21*$AM$58,0)+IF(W21=8,X21*$AM$59,0)+IF(W21=9,X21*$AM$60,0)+IF(W21=10,X21*$AM$61,0) -> 0 | CT21: =IF(Y21=1,Z21*$AM$52,0)+IF(Y21=2,Z21*$AM$53,0)+IF(Y21=3,Z21*$AM$54,0)+IF(Y21=4,Z21*$AM$55,0)+IF(Y21=5,Z21*$AM$56,0)+IF(Y21=6,Z21*$AM$57,0)+IF(Y21=7,Z21*$AM$58,0)+IF(Y21=8,Z21*$AM$59,0)+IF(Y21=9,Z21*$AM$60,0)+IF(Y21=10,Z21*$AM$61,0) -> 0 | CU21: =IF(AA21=1,AB21*$AM$52,0)+IF(AA21=2,AB21*$AM$53,0)+IF(AA21=3,AB21*$AM$54,0)+IF(AA21=4,AB21*$AM$55,0)+IF(AA21=5,AB21*$AM$56,0)+IF(AA21=6,AB21*$AM$57,0)+IF(AA21=7,AB21*$AM$58,0)+IF(AA21=8,AB21*$AM$59,0)+IF(AA21=9,AB21*$AM$60,0)+IF(AA21=10,AB21*$AM$61,0) -> 0 | CV21: =D21 -> 0 | CW21: =SUM(CO21:CV21)*BG21 -> 0
O22: 9 | Q22: 10 | S22: 1 | T22: =K22 -> 0 | U22: 2 | W22: 3 | Y22: 4 | AA22: 5 | AC22: =IF(BG22=0,0,SUM(BD22:BE22)/BG22) -> 0 | AD22: =(D22*F22/324)*(1+K$71)+AV22 -> 0 | AE22: =IF(D22=0,0,AF22/D22) -> 0 | AF22: =SUM(BW22)*(1+M$64+Summary!P$64) -> 0 | AG22: =D22/AD22 -> #DIV/0! | AH22: =AF22*G22 -> 0 | AO22: =IF(O22=1,P22*$T$52,0)+IF(O22=2,P22*$T$53,0)+IF(O22=3,P22*$T$54,0)+IF(O22=4,P22*$T$55,0)+IF(O22=5,P22*$T$56,0)+IF(O22=6,P22*$T$57,0)+IF(O22=7,P22*$T$58,0)+IF(O22=8,P22*$T$59,0)+IF(O22=9,P22*$T$60,0)+IF(O22=10,P22*$T$61,0) -> 0 | AP22: =IF(Q22=1,R22*$T$52,0)+IF(Q22=2,R22*$T$53,0)+IF(Q22=3,R22*$T$54,0)+IF(Q22=4,R22*$T$55,0)+IF(Q22=5,R22*$T$56,0)+IF(Q22=6,R22*$T$57,0)+IF(Q22=7,R22*$T$58,0)+IF(Q22=8,R22*$T$59,0)+IF(Q22=9,R22*$T$60,0)+IF(Q22=10,R22*$T$61,0) -> 0 | AQ22: =IF(S22=1,T22*$T$52,0)+IF(S22=2,T22*$T$53,0)+IF(S22=3,T22*$T$54,0)+IF(S22=4,T22*$T$55,0)+IF(S22=5,T22*$T$56,0)+IF(S22=6,T22*$T$57,0)+IF(S22=7,T22*$T$58,0)+IF(S22=8,T22*$T$59,0)+IF(S22=9,T22*$T$60,0)+IF(S22=10,T22*$T$61,0) -> 0 | AR22: =IF(U22=1,V22*$T$52,0)+IF(U22=2,V22*$T$53,0)+IF(U22=3,V22*$T$54,0)+IF(U22=4,V22*$T$55,0)+IF(U22=5,V22*$T$56,0)+IF(U22=6,V22*$T$57,0)+IF(U22=7,V22*$T$58,0)+IF(U22=8,V22*$T$59,0)+IF(U22=9,V22*$T$60,0)+IF(U22=10,V22*$T$61,0) -> 0 | AS22: =IF(W22=1,X22*$T$52,0)+IF(W22=2,X22*$T$53,0)+IF(W22=3,X22*$T$54,0)+IF(W22=4,X22*$T$55,0)+IF(W22=5,X22*$T$56,0)+IF(W22=6,X22*$T$57,0)+IF(W22=7,X22*$T$58,0)+IF(W22=8,X22*$T$59,0)+IF(W22=9,X22*$T$60,0)+IF(W22=10,X22*$T$61,0) -> 0 | AT22: =IF(Y22=1,Z22*$T$52,0)+IF(Y22=2,Z22*$T$53,0)+IF(Y22=3,Z22*$T$54,0)+IF(Y22=4,Z22*$T$55,0)+IF(Y22=5,Z22*$T$56,0)+IF(Y22=6,Z22*$T$57,0)+IF(Y22=7,Z22*$T$58,0)+IF(Y22=8,Z22*$T$59,0)+IF(Y22=9,Z22*$T$60,0)+IF(Y22=10,Z22*$T$61,0) -> 0 | AU22: =IF(AA22=1,AB22*$T$52,0)+IF(AA22=2,AB22*$T$53,0)+IF(AA22=3,AB22*$T$54,0)+IF(AA22=4,AB22*$T$55,0)+IF(AA22=5,AB22*$T$56,0)+IF(AA22=6,AB22*$T$57,0)+IF(AA22=7,AB22*$T$58,0)+IF(AA22=8,AB22*$T$59,0)+IF(AA22=9,AB22*$T$60,0)+IF(AA22=10,AB22*$T$61,0) -> 0 | AV22: =SUM(AO22:AU22) -> 0 | AW22: =ROUNDUP(IF(O22=1,P22*$P$52,0)+IF(O22=2,P22*$P$53,0)+IF(O22=3,P22*$P$54,0)+IF(O22=4,P22*$P$55,0)+IF(O22=5,P22*$P$56,0)+IF(O22=6,P22*$P$57,0)+IF(O22=7,P22*$P$58,0)+IF(O22=8,P22*$P$59,0)+IF(O22=9,P22*$P$60,0)+IF(O22=10,P22*$P$61,0),0)*BG22 -> 0 | AX22: =ROUNDUP(IF(Q22=1,R22*$P$52,0)+IF(Q22=2,R22*$P$53,0)+IF(Q22=3,R22*$P$54,0)+IF(Q22=4,R22*$P$55,0)+IF(Q22=5,R22*$P$56,0)+IF(Q22=6,R22*$P$57,0)+IF(Q22=7,R22*$P$58,0)+IF(Q22=8,R22*$P$59,0)+IF(Q22=9,R22*$P$60,0)+IF(Q22=10,R22*$P$61,0),0) -> 0 | AY22: =ROUNDUP(IF(S22=1,T22*$P$52,0)+IF(S22=2,T22*$P$53,0)+IF(S22=3,T22*$P$54,0)+IF(S22=4,T22*$P$55,0)+IF(S22=5,T22*$P$56,0)+IF(S22=6,T22*$P$57,0)+IF(S22=7,T22*$P$58,0)+IF(S22=8,T22*$P$59,0)+IF(S22=9,T22*$P$60,0)+IF(S22=10,T22*$P$61,0),0) -> 0 | AZ22: =ROUNDUP(IF(U22=1,V22*$P$52,0)+IF(U22=2,V22*$P$53,0)+IF(U22=3,V22*$P$54,0)+IF(U22=4,V22*$P$55,0)+IF(U22=5,V22*$P$56,0)+IF(U22=6,V22*$P$57,0)+IF(U22=7,V22*$P$58,0)+IF(U22=8,V22*$P$59,0)+IF(U22=9,V22*$P$60,0)+IF(U22=10,V22*$P$61,0),0) -> 0 | BA22: =ROUNDUP(IF(W22=1,X22*$P$52,0)+IF(W22=2,X22*$P$53,0)+IF(W22=3,X22*$P$54,0)+IF(W22=4,X22*$P$55,0)+IF(W22=5,X22*$P$56,0)+IF(W22=6,X22*$P$57,0)+IF(W22=7,X22*$P$58,0)+IF(W22=8,X22*$P$59,0)+IF(W22=9,X22*$P$60,0)+IF(W22=10,X22*$P$61,0),0) -> 0 | BB22: =ROUNDUP(IF(Y22=1,Z22*$P$52,0)+IF(Y22=2,Z22*$P$53,0)+IF(Y22=3,Z22*$P$54,0)+IF(Y22=4,Z22*$P$55,0)+IF(Y22=5,Z22*$P$56,0)+IF(Y22=6,Z22*$P$57,0)+IF(Y22=7,Z22*$P$58,0)+IF(Y22=8,Z22*$P$59,0)+IF(Y22=9,Z22*$P$60,0)+IF(Y22=10,Z22*$P$61,0),0) -> 0 | BC22: =ROUNDUP(IF(AA22=1,AB22*$P$52,0)+IF(AA22=2,AB22*$P$53,0)+IF(AA22=3,AB22*$P$54,0)+IF(AA22=4,AB22*$P$55,0)+IF(AA22=5,AB22*$P$56,0)+IF(AA22=6,AB22*$P$57,0)+IF(AA22=7,AB22*$P$58,0)+IF(AA22=8,AB22*$P$59,0)+IF(AA22=9,AB22*$P$60,0)+IF(AA22=10,AB22*$P$61,0),0) -> 0 | BD22: =SUM(AW22:BC22)*BG22 -> 0 | BE22: =IF(M22=0,0,(M22/12+M22/12)/(M22/12*M22/12)*D22*((L22/16*L22/16)*10.6870159))*(1+K$74)*BG22 -> 0 | BF22: =IF(N22="Y",D22*(1+K$75)*BG22,0) -> 0 | BG22: =G22 -> 0 | BH22: =IF(N22="y",D22,0) -> 0 | BI22: =IF($I22=1,$AD22,0)*BG22 -> 0 | BJ22: =IF($I22=2,$AD22,0)*BG22 -> 0 | BK22: =IF($I22=3,$AD22,0)*BG22 -> 0 | BL22: =IF($I22=4,$AD22,0)*BG22 -> 0 | BM22: =IF($I22=5,$AD22,0)*BG22 -> 0 | BN22: =IF($I22=6,$AD22,0)*BG22 -> 0 | BO22: =SUM(BI22:BN22) -> 0 | BP22: =IF(H22="N",0,D22)*BG22 -> 0 | BQ22: =K22*BG22 -> 0 | BR22: =IF(O22=1,D$52*P22/12,IF(O22=2,D$53*P22/12,IF(O22=3,D$54*P22/12,IF(O22=4,D$55*P22/12,IF(O22=5,D$56*P22/12,IF(O22=6,D$57*P22/12,IF(O22=7,D$58*P22/12,IF(O22=8,D$59*P22/12,IF(O22=9,D$60*P22/12,IF(O22=10,D$61*P22/12,0))))))*BG22)))) -> 0 | BS22: =IF(Q22=1,D$52*R22/12,IF(Q22=2,D$53*R22/12,IF(Q22=3,D$54*R22/12,IF(Q22=4,D$55*R22/12,IF(Q22=5,D$56*R22/12,IF(Q22=6,D$57*R22/12,IF(Q22=7,D$58*R22/12,IF(Q22=8,D$59*R22/12,IF(Q22=9,D$60*R22/12,IF(Q22=10,D$61*R22/12,0))))))*BG22)))) -> 0 | BT22: =D22*BG22 -> 0 | BU22: =D22*J22/324*(1+K$77)*BG22 -> 0 | BV22: =AC22*BG22 -> 0 | BW22: =IF(BG22=0,0,SUM(BX22:CM22)/BG22) -> 0 | BX22: =(BI22*Pricing!F$2+BJ22*Pricing!G$2+BK22*Pricing!H$2+BL22*Pricing!I$2+BM22*Pricing!J$2+BN22*Pricing!K$2)*IF(AC$63="N",(1+AE$63),1) -> 0 | BY22: =AC22*G$74*IF(AC$63="n",1+AE$63,1)*BG22 -> 0 | BZ22: =IF(I$83=0,0,D22*(SUM(L$83:M$86)+L$88)/I$83*BG22) -> 0 | CA22: =IF(I$83=0,0,D22*(SUM(O$83:P$86)+O$88)/I$83*BG22) -> 0 | CB22: =BR22+BS22*E$87 -> 0 | CD22: =BD22/2000*E$89 -> 0 | CE22: =IF(D$49=0,0,SUM(O$92:P$96)/D$49*D22)*BG22 -> 0 | CF22: =IF(D$49=0,0,SUM(AF$72:AF$99)/D$49*D22*BG22) -> 0 | CG22: =IF(D$49=0,0,SUM(O$98:P$103)/D$49*D22)*BG22 -> 0 | CH22: =IF(D$49=0,0,SUM(O$105:O$111)/D$49)*D22*BG22 -> 0 | CI22: =IF(D$49=0,0,SUM(AF$100:AF$111)/D$49*D22*BG22) -> 0 | CJ22: =IF(J$76>0,J$76/D$49*D22*G22,BP22*(G$76*(1+AE$63))) -> 0 | CK22: =IF(L$78=0,0,O$78/L$78)*AW22+IF(L$79=0,0,O$79/L$79)*BC22+IF(L$80=0,0,O$80/L$80)*BC22 -> 0 | CL22: =BF22*G$75*IF(AC$63="Y",1,1+AE$63) -> 0 | CM22: =BU22*G$77*IF(AC$63="Y",1,1+AE$63) -> 0 | CO22: =IF(O22=1,P22*$AM$52,0)+IF(O22=2,P22*$AM$53,0)+IF(O22=3,P22*$AM$54,0)+IF(O22=4,P22*$AM$55,0)+IF(O22=5,P22*$AM$56,0)+IF(O22=6,P22*$AM$57,0)+IF(O22=7,P22*$AM$58,0)+IF(O22=8,P22*$AM$59,0)+IF(O22=9,P22*$AM$60,0)+IF(O22=10,P22*$AM$61,0) -> 0 | CP22: =IF(Q22=1,R22*$AM$52,0)+IF(Q22=2,R22*$AM$53,0)+IF(Q22=3,R22*$AM$54,0)+IF(Q22=4,R22*$AM$55,0)+IF(Q22=5,R22*$AM$56,0)+IF(Q22=6,R22*$AM$57,0)+IF(Q22=7,R22*$AM$58,0)+IF(Q22=8,R22*$AM$59,0)+IF(Q22=9,R22*$AM$60,0)+IF(Q22=10,R22*$AM$61,0) -> 0 | CQ22: =IF(S22=1,T22*$AM$52,0)+IF(S22=2,T22*$AM$53,0)+IF(S22=3,T22*$AM$54,0)+IF(S22=4,T22*$AM$55,0)+IF(S22=5,T22*$AM$56,0)+IF(S22=6,T22*$AM$57,0)+IF(S22=7,T22*$AM$58,0)+IF(S22=8,T22*$AM$59,0)+IF(S22=9,T22*$AM$60,0)+IF(S22=10,T22*$AM$61,0) -> 0 | CR22: =IF(U22=1,V22*$AM$52,0)+IF(U22=2,V22*$AM$53,0)+IF(U22=3,V22*$AM$54,0)+IF(U22=4,V22*$AM$55,0)+IF(U22=5,V22*$AM$56,0)+IF(U22=6,V22*$AM$57,0)+IF(U22=7,V22*$AM$58,0)+IF(U22=8,V22*$AM$59,0)+IF(U22=9,V22*$AM$60,0)+IF(U22=10,V22*$AM$61,0) -> 0 | CS22: =IF(W22=1,X22*$AM$52,0)+IF(W22=2,X22*$AM$53,0)+IF(W22=3,X22*$AM$54,0)+IF(W22=4,X22*$AM$55,0)+IF(W22=5,X22*$AM$56,0)+IF(W22=6,X22*$AM$57,0)+IF(W22=7,X22*$AM$58,0)+IF(W22=8,X22*$AM$59,0)+IF(W22=9,X22*$AM$60,0)+IF(W22=10,X22*$AM$61,0) -> 0 | CT22: =IF(Y22=1,Z22*$AM$52,0)+IF(Y22=2,Z22*$AM$53,0)+IF(Y22=3,Z22*$AM$54,0)+IF(Y22=4,Z22*$AM$55,0)+IF(Y22=5,Z22*$AM$56,0)+IF(Y22=6,Z22*$AM$57,0)+IF(Y22=7,Z22*$AM$58,0)+IF(Y22=8,Z22*$AM$59,0)+IF(Y22=9,Z22*$AM$60,0)+IF(Y22=10,Z22*$AM$61,0) -> 0 | CU22: =IF(AA22=1,AB22*$AM$52,0)+IF(AA22=2,AB22*$AM$53,0)+IF(AA22=3,AB22*$AM$54,0)+IF(AA22=4,AB22*$AM$55,0)+IF(AA22=5,AB22*$AM$56,0)+IF(AA22=6,AB22*$AM$57,0)+IF(AA22=7,AB22*$AM$58,0)+IF(AA22=8,AB22*$AM$59,0)+IF(AA22=9,AB22*$AM$60,0)+IF(AA22=10,AB22*$AM$61,0) -> 0 | CV22: =D22 -> 0 | CW22: =SUM(CO22:CV22)*BG22 -> 0
O23: 9 | Q23: 10 | S23: 1 | T23: =K23 -> 0 | U23: 2 | W23: 3 | Y23: 4 | AA23: 5 | AC23: =IF(BG23=0,0,SUM(BD23:BE23)/BG23) -> 0 | AD23: =(D23*F23/324)*(1+K$71)+AV23 -> 0 | AE23: =IF(D23=0,0,AF23/D23) -> 0 | AF23: =SUM(BW23)*(1+M$64+Summary!P$64) -> 0 | AG23: =D23/AD23 -> #DIV/0! | AH23: =AF23*G23 -> 0 | AO23: =IF(O23=1,P23*$T$52,0)+IF(O23=2,P23*$T$53,0)+IF(O23=3,P23*$T$54,0)+IF(O23=4,P23*$T$55,0)+IF(O23=5,P23*$T$56,0)+IF(O23=6,P23*$T$57,0)+IF(O23=7,P23*$T$58,0)+IF(O23=8,P23*$T$59,0)+IF(O23=9,P23*$T$60,0)+IF(O23=10,P23*$T$61,0) -> 0 | AP23: =IF(Q23=1,R23*$T$52,0)+IF(Q23=2,R23*$T$53,0)+IF(Q23=3,R23*$T$54,0)+IF(Q23=4,R23*$T$55,0)+IF(Q23=5,R23*$T$56,0)+IF(Q23=6,R23*$T$57,0)+IF(Q23=7,R23*$T$58,0)+IF(Q23=8,R23*$T$59,0)+IF(Q23=9,R23*$T$60,0)+IF(Q23=10,R23*$T$61,0) -> 0 | AQ23: =IF(S23=1,T23*$T$52,0)+IF(S23=2,T23*$T$53,0)+IF(S23=3,T23*$T$54,0)+IF(S23=4,T23*$T$55,0)+IF(S23=5,T23*$T$56,0)+IF(S23=6,T23*$T$57,0)+IF(S23=7,T23*$T$58,0)+IF(S23=8,T23*$T$59,0)+IF(S23=9,T23*$T$60,0)+IF(S23=10,T23*$T$61,0) -> 0 | AR23: =IF(U23=1,V23*$T$52,0)+IF(U23=2,V23*$T$53,0)+IF(U23=3,V23*$T$54,0)+IF(U23=4,V23*$T$55,0)+IF(U23=5,V23*$T$56,0)+IF(U23=6,V23*$T$57,0)+IF(U23=7,V23*$T$58,0)+IF(U23=8,V23*$T$59,0)+IF(U23=9,V23*$T$60,0)+IF(U23=10,V23*$T$61,0) -> 0 | AS23: =IF(W23=1,X23*$T$52,0)+IF(W23=2,X23*$T$53,0)+IF(W23=3,X23*$T$54,0)+IF(W23=4,X23*$T$55,0)+IF(W23=5,X23*$T$56,0)+IF(W23=6,X23*$T$57,0)+IF(W23=7,X23*$T$58,0)+IF(W23=8,X23*$T$59,0)+IF(W23=9,X23*$T$60,0)+IF(W23=10,X23*$T$61,0) -> 0 | AT23: =IF(Y23=1,Z23*$T$52,0)+IF(Y23=2,Z23*$T$53,0)+IF(Y23=3,Z23*$T$54,0)+IF(Y23=4,Z23*$T$55,0)+IF(Y23=5,Z23*$T$56,0)+IF(Y23=6,Z23*$T$57,0)+IF(Y23=7,Z23*$T$58,0)+IF(Y23=8,Z23*$T$59,0)+IF(Y23=9,Z23*$T$60,0)+IF(Y23=10,Z23*$T$61,0) -> 0 | AU23: =IF(AA23=1,AB23*$T$52,0)+IF(AA23=2,AB23*$T$53,0)+IF(AA23=3,AB23*$T$54,0)+IF(AA23=4,AB23*$T$55,0)+IF(AA23=5,AB23*$T$56,0)+IF(AA23=6,AB23*$T$57,0)+IF(AA23=7,AB23*$T$58,0)+IF(AA23=8,AB23*$T$59,0)+IF(AA23=9,AB23*$T$60,0)+IF(AA23=10,AB23*$T$61,0) -> 0 | AV23: =SUM(AO23:AU23) -> 0 | AW23: =ROUNDUP(IF(O23=1,P23*$P$52,0)+IF(O23=2,P23*$P$53,0)+IF(O23=3,P23*$P$54,0)+IF(O23=4,P23*$P$55,0)+IF(O23=5,P23*$P$56,0)+IF(O23=6,P23*$P$57,0)+IF(O23=7,P23*$P$58,0)+IF(O23=8,P23*$P$59,0)+IF(O23=9,P23*$P$60,0)+IF(O23=10,P23*$P$61,0),0)*BG23 -> 0 | AX23: =ROUNDUP(IF(Q23=1,R23*$P$52,0)+IF(Q23=2,R23*$P$53,0)+IF(Q23=3,R23*$P$54,0)+IF(Q23=4,R23*$P$55,0)+IF(Q23=5,R23*$P$56,0)+IF(Q23=6,R23*$P$57,0)+IF(Q23=7,R23*$P$58,0)+IF(Q23=8,R23*$P$59,0)+IF(Q23=9,R23*$P$60,0)+IF(Q23=10,R23*$P$61,0),0) -> 0 | AY23: =ROUNDUP(IF(S23=1,T23*$P$52,0)+IF(S23=2,T23*$P$53,0)+IF(S23=3,T23*$P$54,0)+IF(S23=4,T23*$P$55,0)+IF(S23=5,T23*$P$56,0)+IF(S23=6,T23*$P$57,0)+IF(S23=7,T23*$P$58,0)+IF(S23=8,T23*$P$59,0)+IF(S23=9,T23*$P$60,0)+IF(S23=10,T23*$P$61,0),0) -> 0 | AZ23: =ROUNDUP(IF(U23=1,V23*$P$52,0)+IF(U23=2,V23*$P$53,0)+IF(U23=3,V23*$P$54,0)+IF(U23=4,V23*$P$55,0)+IF(U23=5,V23*$P$56,0)+IF(U23=6,V23*$P$57,0)+IF(U23=7,V23*$P$58,0)+IF(U23=8,V23*$P$59,0)+IF(U23=9,V23*$P$60,0)+IF(U23=10,V23*$P$61,0),0) -> 0 | BA23: =ROUNDUP(IF(W23=1,X23*$P$52,0)+IF(W23=2,X23*$P$53,0)+IF(W23=3,X23*$P$54,0)+IF(W23=4,X23*$P$55,0)+IF(W23=5,X23*$P$56,0)+IF(W23=6,X23*$P$57,0)+IF(W23=7,X23*$P$58,0)+IF(W23=8,X23*$P$59,0)+IF(W23=9,X23*$P$60,0)+IF(W23=10,X23*$P$61,0),0) -> 0 | BB23: =ROUNDUP(IF(Y23=1,Z23*$P$52,0)+IF(Y23=2,Z23*$P$53,0)+IF(Y23=3,Z23*$P$54,0)+IF(Y23=4,Z23*$P$55,0)+IF(Y23=5,Z23*$P$56,0)+IF(Y23=6,Z23*$P$57,0)+IF(Y23=7,Z23*$P$58,0)+IF(Y23=8,Z23*$P$59,0)+IF(Y23=9,Z23*$P$60,0)+IF(Y23=10,Z23*$P$61,0),0) -> 0 | BC23: =ROUNDUP(IF(AA23=1,AB23*$P$52,0)+IF(AA23=2,AB23*$P$53,0)+IF(AA23=3,AB23*$P$54,0)+IF(AA23=4,AB23*$P$55,0)+IF(AA23=5,AB23*$P$56,0)+IF(AA23=6,AB23*$P$57,0)+IF(AA23=7,AB23*$P$58,0)+IF(AA23=8,AB23*$P$59,0)+IF(AA23=9,AB23*$P$60,0)+IF(AA23=10,AB23*$P$61,0),0) -> 0 | BD23: =SUM(AW23:BC23)*BG23 -> 0 | BE23: =IF(M23=0,0,(M23/12+M23/12)/(M23/12*M23/12)*D23*((L23/16*L23/16)*10.6870159))*(1+K$74)*BG23 -> 0 | BF23: =IF(N23="Y",D23*(1+K$75)*BG23,0) -> 0 | BG23: =G23 -> 0 | BH23: =IF(N23="y",D23,0) -> 0 | BI23: =IF($I23=1,$AD23,0)*BG23 -> 0 | BJ23: =IF($I23=2,$AD23,0)*BG23 -> 0 | BK23: =IF($I23=3,$AD23,0)*BG23 -> 0 | BL23: =IF($I23=4,$AD23,0)*BG23 -> 0 | BM23: =IF($I23=5,$AD23,0)*BG23 -> 0 | BN23: =IF($I23=6,$AD23,0)*BG23 -> 0 | BO23: =SUM(BI23:BN23) -> 0 | BP23: =IF(H23="N",0,D23)*BG23 -> 0 | BQ23: =K23*BG23 -> 0 | BR23: =IF(O23=1,D$52*P23/12,IF(O23=2,D$53*P23/12,IF(O23=3,D$54*P23/12,IF(O23=4,D$55*P23/12,IF(O23=5,D$56*P23/12,IF(O23=6,D$57*P23/12,IF(O23=7,D$58*P23/12,IF(O23=8,D$59*P23/12,IF(O23=9,D$60*P23/12,IF(O23=10,D$61*P23/12,0))))))*BG23)))) -> 0 | BS23: =IF(Q23=1,D$52*R23/12,IF(Q23=2,D$53*R23/12,IF(Q23=3,D$54*R23/12,IF(Q23=4,D$55*R23/12,IF(Q23=5,D$56*R23/12,IF(Q23=6,D$57*R23/12,IF(Q23=7,D$58*R23/12,IF(Q23=8,D$59*R23/12,IF(Q23=9,D$60*R23/12,IF(Q23=10,D$61*R23/12,0))))))*BG23)))) -> 0 | BT23: =D23*BG23 -> 0 | BU23: =D23*J23/324*(1+K$77)*BG23 -> 0 | BV23: =AC23*BG23 -> 0 | BW23: =IF(BG23=0,0,SUM(BX23:CM23)/BG23) -> 0 | BX23: =(BI23*Pricing!F$2+BJ23*Pricing!G$2+BK23*Pricing!H$2+BL23*Pricing!I$2+BM23*Pricing!J$2+BN23*Pricing!K$2)*IF(AC$63="N",(1+AE$63),1) -> 0 | BY23: =AC23*G$74*IF(AC$63="n",1+AE$63,1)*BG23 -> 0 | BZ23: =IF(I$83=0,0,D23*(SUM(L$83:M$86)+L$88)/I$83*BG23) -> 0 | CA23: =IF(I$83=0,0,D23*(SUM(O$83:P$86)+O$88)/I$83*BG23) -> 0 | CB23: =BR23+BS23*E$87 -> 0 | CD23: =BD23/2000*E$89 -> 0 | CE23: =IF(D$49=0,0,SUM(O$92:P$96)/D$49*D23)*BG23 -> 0 | CF23: =IF(D$49=0,0,SUM(AF$72:AF$99)/D$49*D23*BG23) -> 0 | CG23: =IF(D$49=0,0,SUM(O$98:P$103)/D$49*D23)*BG23 -> 0 | CH23: =IF(D$49=0,0,SUM(O$105:O$111)/D$49)*D23*BG23 -> 0 | CI23: =IF(D$49=0,0,SUM(AF$100:AF$111)/D$49*D23*BG23) -> 0 | CJ23: =IF(J$76>0,J$76/D$49*D23*G23,BP23*(G$76*(1+AE$63))) -> 0 | CK23: =IF(L$78=0,0,O$78/L$78)*AW23+IF(L$79=0,0,O$79/L$79)*BC23+IF(L$80=0,0,O$80/L$80)*BC23 -> 0 | CL23: =BF23*G$75*IF(AC$63="Y",1,1+AE$63) -> 0 | CM23: =BU23*G$77*IF(AC$63="Y",1,1+AE$63) -> 0 | CO23: =IF(O23=1,P23*$AM$52,0)+IF(O23=2,P23*$AM$53,0)+IF(O23=3,P23*$AM$54,0)+IF(O23=4,P23*$AM$55,0)+IF(O23=5,P23*$AM$56,0)+IF(O23=6,P23*$AM$57,0)+IF(O23=7,P23*$AM$58,0)+IF(O23=8,P23*$AM$59,0)+IF(O23=9,P23*$AM$60,0)+IF(O23=10,P23*$AM$61,0) -> 0 | CP23: =IF(Q23=1,R23*$AM$52,0)+IF(Q23=2,R23*$AM$53,0)+IF(Q23=3,R23*$AM$54,0)+IF(Q23=4,R23*$AM$55,0)+IF(Q23=5,R23*$AM$56,0)+IF(Q23=6,R23*$AM$57,0)+IF(Q23=7,R23*$AM$58,0)+IF(Q23=8,R23*$AM$59,0)+IF(Q23=9,R23*$AM$60,0)+IF(Q23=10,R23*$AM$61,0) -> 0 | CQ23: =IF(S23=1,T23*$AM$52,0)+IF(S23=2,T23*$AM$53,0)+IF(S23=3,T23*$AM$54,0)+IF(S23=4,T23*$AM$55,0)+IF(S23=5,T23*$AM$56,0)+IF(S23=6,T23*$AM$57,0)+IF(S23=7,T23*$AM$58,0)+IF(S23=8,T23*$AM$59,0)+IF(S23=9,T23*$AM$60,0)+IF(S23=10,T23*$AM$61,0) -> 0 | CR23: =IF(U23=1,V23*$AM$52,0)+IF(U23=2,V23*$AM$53,0)+IF(U23=3,V23*$AM$54,0)+IF(U23=4,V23*$AM$55,0)+IF(U23=5,V23*$AM$56,0)+IF(U23=6,V23*$AM$57,0)+IF(U23=7,V23*$AM$58,0)+IF(U23=8,V23*$AM$59,0)+IF(U23=9,V23*$AM$60,0)+IF(U23=10,V23*$AM$61,0) -> 0 | CS23: =IF(W23=1,X23*$AM$52,0)+IF(W23=2,X23*$AM$53,0)+IF(W23=3,X23*$AM$54,0)+IF(W23=4,X23*$AM$55,0)+IF(W23=5,X23*$AM$56,0)+IF(W23=6,X23*$AM$57,0)+IF(W23=7,X23*$AM$58,0)+IF(W23=8,X23*$AM$59,0)+IF(W23=9,X23*$AM$60,0)+IF(W23=10,X23*$AM$61,0) -> 0 | CT23: =IF(Y23=1,Z23*$AM$52,0)+IF(Y23=2,Z23*$AM$53,0)+IF(Y23=3,Z23*$AM$54,0)+IF(Y23=4,Z23*$AM$55,0)+IF(Y23=5,Z23*$AM$56,0)+IF(Y23=6,Z23*$AM$57,0)+IF(Y23=7,Z23*$AM$58,0)+IF(Y23=8,Z23*$AM$59,0)+IF(Y23=9,Z23*$AM$60,0)+IF(Y23=10,Z23*$AM$61,0) -> 0 | CU23: =IF(AA23=1,AB23*$AM$52,0)+IF(AA23=2,AB23*$AM$53,0)+IF(AA23=3,AB23*$AM$54,0)+IF(AA23=4,AB23*$AM$55,0)+IF(AA23=5,AB23*$AM$56,0)+IF(AA23=6,AB23*$AM$57,0)+IF(AA23=7,AB23*$AM$58,0)+IF(AA23=8,AB23*$AM$59,0)+IF(AA23=9,AB23*$AM$60,0)+IF(AA23=10,AB23*$AM$61,0) -> 0 | CV23: =D23 -> 0 | CW23: =SUM(CO23:CV23)*BG23 -> 0
O24: 9 | Q24: 10 | S24: 1 | T24: =K24 -> 0 | U24: 2 | W24: 3 | Y24: 4 | AA24: 5 | AC24: =IF(BG24=0,0,SUM(BD24:BE24)/BG24) -> 0 | AD24: =(D24*F24/324)*(1+K$71)+AV24 -> 0 | AE24: =IF(D24=0,0,AF24/D24) -> 0 | AF24: =SUM(BW24)*(1+M$64+Summary!P$64) -> 0 | AG24: =D24/AD24 -> #DIV/0! | AH24: =AF24*G24 -> 0 | AO24: =IF(O24=1,P24*$T$52,0)+IF(O24=2,P24*$T$53,0)+IF(O24=3,P24*$T$54,0)+IF(O24=4,P24*$T$55,0)+IF(O24=5,P24*$T$56,0)+IF(O24=6,P24*$T$57,0)+IF(O24=7,P24*$T$58,0)+IF(O24=8,P24*$T$59,0)+IF(O24=9,P24*$T$60,0)+IF(O24=10,P24*$T$61,0) -> 0 | AP24: =IF(Q24=1,R24*$T$52,0)+IF(Q24=2,R24*$T$53,0)+IF(Q24=3,R24*$T$54,0)+IF(Q24=4,R24*$T$55,0)+IF(Q24=5,R24*$T$56,0)+IF(Q24=6,R24*$T$57,0)+IF(Q24=7,R24*$T$58,0)+IF(Q24=8,R24*$T$59,0)+IF(Q24=9,R24*$T$60,0)+IF(Q24=10,R24*$T$61,0) -> 0 | AQ24: =IF(S24=1,T24*$T$52,0)+IF(S24=2,T24*$T$53,0)+IF(S24=3,T24*$T$54,0)+IF(S24=4,T24*$T$55,0)+IF(S24=5,T24*$T$56,0)+IF(S24=6,T24*$T$57,0)+IF(S24=7,T24*$T$58,0)+IF(S24=8,T24*$T$59,0)+IF(S24=9,T24*$T$60,0)+IF(S24=10,T24*$T$61,0) -> 0 | AR24: =IF(U24=1,V24*$T$52,0)+IF(U24=2,V24*$T$53,0)+IF(U24=3,V24*$T$54,0)+IF(U24=4,V24*$T$55,0)+IF(U24=5,V24*$T$56,0)+IF(U24=6,V24*$T$57,0)+IF(U24=7,V24*$T$58,0)+IF(U24=8,V24*$T$59,0)+IF(U24=9,V24*$T$60,0)+IF(U24=10,V24*$T$61,0) -> 0 | AS24: =IF(W24=1,X24*$T$52,0)+IF(W24=2,X24*$T$53,0)+IF(W24=3,X24*$T$54,0)+IF(W24=4,X24*$T$55,0)+IF(W24=5,X24*$T$56,0)+IF(W24=6,X24*$T$57,0)+IF(W24=7,X24*$T$58,0)+IF(W24=8,X24*$T$59,0)+IF(W24=9,X24*$T$60,0)+IF(W24=10,X24*$T$61,0) -> 0 | AT24: =IF(Y24=1,Z24*$T$52,0)+IF(Y24=2,Z24*$T$53,0)+IF(Y24=3,Z24*$T$54,0)+IF(Y24=4,Z24*$T$55,0)+IF(Y24=5,Z24*$T$56,0)+IF(Y24=6,Z24*$T$57,0)+IF(Y24=7,Z24*$T$58,0)+IF(Y24=8,Z24*$T$59,0)+IF(Y24=9,Z24*$T$60,0)+IF(Y24=10,Z24*$T$61,0) -> 0 | AU24: =IF(AA24=1,AB24*$T$52,0)+IF(AA24=2,AB24*$T$53,0)+IF(AA24=3,AB24*$T$54,0)+IF(AA24=4,AB24*$T$55,0)+IF(AA24=5,AB24*$T$56,0)+IF(AA24=6,AB24*$T$57,0)+IF(AA24=7,AB24*$T$58,0)+IF(AA24=8,AB24*$T$59,0)+IF(AA24=9,AB24*$T$60,0)+IF(AA24=10,AB24*$T$61,0) -> 0 | AV24: =SUM(AO24:AU24) -> 0 | AW24: =ROUNDUP(IF(O24=1,P24*$P$52,0)+IF(O24=2,P24*$P$53,0)+IF(O24=3,P24*$P$54,0)+IF(O24=4,P24*$P$55,0)+IF(O24=5,P24*$P$56,0)+IF(O24=6,P24*$P$57,0)+IF(O24=7,P24*$P$58,0)+IF(O24=8,P24*$P$59,0)+IF(O24=9,P24*$P$60,0)+IF(O24=10,P24*$P$61,0),0)*BG24 -> 0 | AX24: =ROUNDUP(IF(Q24=1,R24*$P$52,0)+IF(Q24=2,R24*$P$53,0)+IF(Q24=3,R24*$P$54,0)+IF(Q24=4,R24*$P$55,0)+IF(Q24=5,R24*$P$56,0)+IF(Q24=6,R24*$P$57,0)+IF(Q24=7,R24*$P$58,0)+IF(Q24=8,R24*$P$59,0)+IF(Q24=9,R24*$P$60,0)+IF(Q24=10,R24*$P$61,0),0) -> 0 | AY24: =ROUNDUP(IF(S24=1,T24*$P$52,0)+IF(S24=2,T24*$P$53,0)+IF(S24=3,T24*$P$54,0)+IF(S24=4,T24*$P$55,0)+IF(S24=5,T24*$P$56,0)+IF(S24=6,T24*$P$57,0)+IF(S24=7,T24*$P$58,0)+IF(S24=8,T24*$P$59,0)+IF(S24=9,T24*$P$60,0)+IF(S24=10,T24*$P$61,0),0) -> 0 | AZ24: =ROUNDUP(IF(U24=1,V24*$P$52,0)+IF(U24=2,V24*$P$53,0)+IF(U24=3,V24*$P$54,0)+IF(U24=4,V24*$P$55,0)+IF(U24=5,V24*$P$56,0)+IF(U24=6,V24*$P$57,0)+IF(U24=7,V24*$P$58,0)+IF(U24=8,V24*$P$59,0)+IF(U24=9,V24*$P$60,0)+IF(U24=10,V24*$P$61,0),0) -> 0 | BA24: =ROUNDUP(IF(W24=1,X24*$P$52,0)+IF(W24=2,X24*$P$53,0)+IF(W24=3,X24*$P$54,0)+IF(W24=4,X24*$P$55,0)+IF(W24=5,X24*$P$56,0)+IF(W24=6,X24*$P$57,0)+IF(W24=7,X24*$P$58,0)+IF(W24=8,X24*$P$59,0)+IF(W24=9,X24*$P$60,0)+IF(W24=10,X24*$P$61,0),0) -> 0 | BB24: =ROUNDUP(IF(Y24=1,Z24*$P$52,0)+IF(Y24=2,Z24*$P$53,0)+IF(Y24=3,Z24*$P$54,0)+IF(Y24=4,Z24*$P$55,0)+IF(Y24=5,Z24*$P$56,0)+IF(Y24=6,Z24*$P$57,0)+IF(Y24=7,Z24*$P$58,0)+IF(Y24=8,Z24*$P$59,0)+IF(Y24=9,Z24*$P$60,0)+IF(Y24=10,Z24*$P$61,0),0) -> 0 | BC24: =ROUNDUP(IF(AA24=1,AB24*$P$52,0)+IF(AA24=2,AB24*$P$53,0)+IF(AA24=3,AB24*$P$54,0)+IF(AA24=4,AB24*$P$55,0)+IF(AA24=5,AB24*$P$56,0)+IF(AA24=6,AB24*$P$57,0)+IF(AA24=7,AB24*$P$58,0)+IF(AA24=8,AB24*$P$59,0)+IF(AA24=9,AB24*$P$60,0)+IF(AA24=10,AB24*$P$61,0),0) -> 0 | BD24: =SUM(AW24:BC24)*BG24 -> 0 | BE24: =IF(M24=0,0,(M24/12+M24/12)/(M24/12*M24/12)*D24*((L24/16*L24/16)*10.6870159))*(1+K$74)*BG24 -> 0 | BF24: =IF(N24="Y",D24*(1+K$75)*BG24,0) -> 0 | BG24: =G24 -> 0 | BH24: =IF(N24="y",D24,0) -> 0 | BI24: =IF($I24=1,$AD24,0)*BG24 -> 0 | BJ24: =IF($I24=2,$AD24,0)*BG24 -> 0 | BK24: =IF($I24=3,$AD24,0)*BG24 -> 0 | BL24: =IF($I24=4,$AD24,0)*BG24 -> 0 | BM24: =IF($I24=5,$AD24,0)*BG24 -> 0 | BN24: =IF($I24=6,$AD24,0)*BG24 -> 0 | BO24: =SUM(BI24:BN24) -> 0 | BP24: =IF(H24="N",0,D24)*BG24 -> 0 | BQ24: =K24*BG24 -> 0 | BR24: =IF(O24=1,D$52*P24/12,IF(O24=2,D$53*P24/12,IF(O24=3,D$54*P24/12,IF(O24=4,D$55*P24/12,IF(O24=5,D$56*P24/12,IF(O24=6,D$57*P24/12,IF(O24=7,D$58*P24/12,IF(O24=8,D$59*P24/12,IF(O24=9,D$60*P24/12,IF(O24=10,D$61*P24/12,0))))))*BG24)))) -> 0 | BS24: =IF(Q24=1,D$52*R24/12,IF(Q24=2,D$53*R24/12,IF(Q24=3,D$54*R24/12,IF(Q24=4,D$55*R24/12,IF(Q24=5,D$56*R24/12,IF(Q24=6,D$57*R24/12,IF(Q24=7,D$58*R24/12,IF(Q24=8,D$59*R24/12,IF(Q24=9,D$60*R24/12,IF(Q24=10,D$61*R24/12,0))))))*BG24)))) -> 0 | BT24: =D24*BG24 -> 0 | BU24: =D24*J24/324*(1+K$77)*BG24 -> 0 | BV24: =AC24*BG24 -> 0 | BW24: =IF(BG24=0,0,SUM(BX24:CM24)/BG24) -> 0 | BX24: =(BI24*Pricing!F$2+BJ24*Pricing!G$2+BK24*Pricing!H$2+BL24*Pricing!I$2+BM24*Pricing!J$2+BN24*Pricing!K$2)*IF(AC$63="N",(1+AE$63),1) -> 0 | BY24: =AC24*G$74*IF(AC$63="n",1+AE$63,1)*BG24 -> 0 | BZ24: =IF(I$83=0,0,D24*(SUM(L$83:M$86)+L$88)/I$83*BG24) -> 0 | CA24: =IF(I$83=0,0,D24*(SUM(O$83:P$86)+O$88)/I$83*BG24) -> 0 | CB24: =BR24+BS24*E$87 -> 0 | CD24: =BD24/2000*E$89 -> 0 | CE24: =IF(D$49=0,0,SUM(O$92:P$96)/D$49*D24)*BG24 -> 0 | CF24: =IF(D$49=0,0,SUM(AF$72:AF$99)/D$49*D24*BG24) -> 0 | CG24: =IF(D$49=0,0,SUM(O$98:P$103)/D$49*D24)*BG24 -> 0 | CH24: =IF(D$49=0,0,SUM(O$105:O$111)/D$49)*D24*BG24 -> 0 | CI24: =IF(D$49=0,0,SUM(AF$100:AF$111)/D$49*D24*BG24) -> 0 | CJ24: =IF(J$76>0,J$76/D$49*D24*G24,BP24*(G$76*(1+AE$63))) -> 0 | CK24: =IF(L$78=0,0,O$78/L$78)*AW24+IF(L$79=0,0,O$79/L$79)*BC24+IF(L$80=0,0,O$80/L$80)*BC24 -> 0 | CL24: =BF24*G$75*IF(AC$63="Y",1,1+AE$63) -> 0 | CM24: =BU24*G$77*IF(AC$63="Y",1,1+AE$63) -> 0 | CO24: =IF(O24=1,P24*$AM$52,0)+IF(O24=2,P24*$AM$53,0)+IF(O24=3,P24*$AM$54,0)+IF(O24=4,P24*$AM$55,0)+IF(O24=5,P24*$AM$56,0)+IF(O24=6,P24*$AM$57,0)+IF(O24=7,P24*$AM$58,0)+IF(O24=8,P24*$AM$59,0)+IF(O24=9,P24*$AM$60,0)+IF(O24=10,P24*$AM$61,0) -> 0 | CP24: =IF(Q24=1,R24*$AM$52,0)+IF(Q24=2,R24*$AM$53,0)+IF(Q24=3,R24*$AM$54,0)+IF(Q24=4,R24*$AM$55,0)+IF(Q24=5,R24*$AM$56,0)+IF(Q24=6,R24*$AM$57,0)+IF(Q24=7,R24*$AM$58,0)+IF(Q24=8,R24*$AM$59,0)+IF(Q24=9,R24*$AM$60,0)+IF(Q24=10,R24*$AM$61,0) -> 0 | CQ24: =IF(S24=1,T24*$AM$52,0)+IF(S24=2,T24*$AM$53,0)+IF(S24=3,T24*$AM$54,0)+IF(S24=4,T24*$AM$55,0)+IF(S24=5,T24*$AM$56,0)+IF(S24=6,T24*$AM$57,0)+IF(S24=7,T24*$AM$58,0)+IF(S24=8,T24*$AM$59,0)+IF(S24=9,T24*$AM$60,0)+IF(S24=10,T24*$AM$61,0) -> 0 | CR24: =IF(U24=1,V24*$AM$52,0)+IF(U24=2,V24*$AM$53,0)+IF(U24=3,V24*$AM$54,0)+IF(U24=4,V24*$AM$55,0)+IF(U24=5,V24*$AM$56,0)+IF(U24=6,V24*$AM$57,0)+IF(U24=7,V24*$AM$58,0)+IF(U24=8,V24*$AM$59,0)+IF(U24=9,V24*$AM$60,0)+IF(U24=10,V24*$AM$61,0) -> 0 | CS24: =IF(W24=1,X24*$AM$52,0)+IF(W24=2,X24*$AM$53,0)+IF(W24=3,X24*$AM$54,0)+IF(W24=4,X24*$AM$55,0)+IF(W24=5,X24*$AM$56,0)+IF(W24=6,X24*$AM$57,0)+IF(W24=7,X24*$AM$58,0)+IF(W24=8,X24*$AM$59,0)+IF(W24=9,X24*$AM$60,0)+IF(W24=10,X24*$AM$61,0) -> 0 | CT24: =IF(Y24=1,Z24*$AM$52,0)+IF(Y24=2,Z24*$AM$53,0)+IF(Y24=3,Z24*$AM$54,0)+IF(Y24=4,Z24*$AM$55,0)+IF(Y24=5,Z24*$AM$56,0)+IF(Y24=6,Z24*$AM$57,0)+IF(Y24=7,Z24*$AM$58,0)+IF(Y24=8,Z24*$AM$59,0)+IF(Y24=9,Z24*$AM$60,0)+IF(Y24=10,Z24*$AM$61,0) -> 0 | CU24: =IF(AA24=1,AB24*$AM$52,0)+IF(AA24=2,AB24*$AM$53,0)+IF(AA24=3,AB24*$AM$54,0)+IF(AA24=4,AB24*$AM$55,0)+IF(AA24=5,AB24*$AM$56,0)+IF(AA24=6,AB24*$AM$57,0)+IF(AA24=7,AB24*$AM$58,0)+IF(AA24=8,AB24*$AM$59,0)+IF(AA24=9,AB24*$AM$60,0)+IF(AA24=10,AB24*$AM$61,0) -> 0 | CV24: =D24 -> 0 | CW24: =SUM(CO24:CV24)*BG24 -> 0
O25: 9 | Q25: 10 | S25: 1 | T25: =K25 -> 0 | U25: 2 | W25: 3 | Y25: 4 | AA25: 5 | AC25: =IF(BG25=0,0,SUM(BD25:BE25)/BG25) -> 0 | AD25: =(D25*F25/324)*(1+K$71)+AV25 -> 0 | AE25: =IF(D25=0,0,AF25/D25) -> 0 | AF25: =SUM(BW25)*(1+M$64+Summary!P$64) -> 0 | AG25: =D25/AD25 -> #DIV/0! | AH25: =AF25*G25 -> 0 | AO25: =IF(O25=1,P25*$T$52,0)+IF(O25=2,P25*$T$53,0)+IF(O25=3,P25*$T$54,0)+IF(O25=4,P25*$T$55,0)+IF(O25=5,P25*$T$56,0)+IF(O25=6,P25*$T$57,0)+IF(O25=7,P25*$T$58,0)+IF(O25=8,P25*$T$59,0)+IF(O25=9,P25*$T$60,0)+IF(O25=10,P25*$T$61,0) -> 0 | AP25: =IF(Q25=1,R25*$T$52,0)+IF(Q25=2,R25*$T$53,0)+IF(Q25=3,R25*$T$54,0)+IF(Q25=4,R25*$T$55,0)+IF(Q25=5,R25*$T$56,0)+IF(Q25=6,R25*$T$57,0)+IF(Q25=7,R25*$T$58,0)+IF(Q25=8,R25*$T$59,0)+IF(Q25=9,R25*$T$60,0)+IF(Q25=10,R25*$T$61,0) -> 0 | AQ25: =IF(S25=1,T25*$T$52,0)+IF(S25=2,T25*$T$53,0)+IF(S25=3,T25*$T$54,0)+IF(S25=4,T25*$T$55,0)+IF(S25=5,T25*$T$56,0)+IF(S25=6,T25*$T$57,0)+IF(S25=7,T25*$T$58,0)+IF(S25=8,T25*$T$59,0)+IF(S25=9,T25*$T$60,0)+IF(S25=10,T25*$T$61,0) -> 0 | AR25: =IF(U25=1,V25*$T$52,0)+IF(U25=2,V25*$T$53,0)+IF(U25=3,V25*$T$54,0)+IF(U25=4,V25*$T$55,0)+IF(U25=5,V25*$T$56,0)+IF(U25=6,V25*$T$57,0)+IF(U25=7,V25*$T$58,0)+IF(U25=8,V25*$T$59,0)+IF(U25=9,V25*$T$60,0)+IF(U25=10,V25*$T$61,0) -> 0 | AS25: =IF(W25=1,X25*$T$52,0)+IF(W25=2,X25*$T$53,0)+IF(W25=3,X25*$T$54,0)+IF(W25=4,X25*$T$55,0)+IF(W25=5,X25*$T$56,0)+IF(W25=6,X25*$T$57,0)+IF(W25=7,X25*$T$58,0)+IF(W25=8,X25*$T$59,0)+IF(W25=9,X25*$T$60,0)+IF(W25=10,X25*$T$61,0) -> 0 | AT25: =IF(Y25=1,Z25*$T$52,0)+IF(Y25=2,Z25*$T$53,0)+IF(Y25=3,Z25*$T$54,0)+IF(Y25=4,Z25*$T$55,0)+IF(Y25=5,Z25*$T$56,0)+IF(Y25=6,Z25*$T$57,0)+IF(Y25=7,Z25*$T$58,0)+IF(Y25=8,Z25*$T$59,0)+IF(Y25=9,Z25*$T$60,0)+IF(Y25=10,Z25*$T$61,0) -> 0 | AU25: =IF(AA25=1,AB25*$T$52,0)+IF(AA25=2,AB25*$T$53,0)+IF(AA25=3,AB25*$T$54,0)+IF(AA25=4,AB25*$T$55,0)+IF(AA25=5,AB25*$T$56,0)+IF(AA25=6,AB25*$T$57,0)+IF(AA25=7,AB25*$T$58,0)+IF(AA25=8,AB25*$T$59,0)+IF(AA25=9,AB25*$T$60,0)+IF(AA25=10,AB25*$T$61,0) -> 0 | AV25: =SUM(AO25:AU25) -> 0 | AW25: =ROUNDUP(IF(O25=1,P25*$P$52,0)+IF(O25=2,P25*$P$53,0)+IF(O25=3,P25*$P$54,0)+IF(O25=4,P25*$P$55,0)+IF(O25=5,P25*$P$56,0)+IF(O25=6,P25*$P$57,0)+IF(O25=7,P25*$P$58,0)+IF(O25=8,P25*$P$59,0)+IF(O25=9,P25*$P$60,0)+IF(O25=10,P25*$P$61,0),0)*BG25 -> 0 | AX25: =ROUNDUP(IF(Q25=1,R25*$P$52,0)+IF(Q25=2,R25*$P$53,0)+IF(Q25=3,R25*$P$54,0)+IF(Q25=4,R25*$P$55,0)+IF(Q25=5,R25*$P$56,0)+IF(Q25=6,R25*$P$57,0)+IF(Q25=7,R25*$P$58,0)+IF(Q25=8,R25*$P$59,0)+IF(Q25=9,R25*$P$60,0)+IF(Q25=10,R25*$P$61,0),0) -> 0 | AY25: =ROUNDUP(IF(S25=1,T25*$P$52,0)+IF(S25=2,T25*$P$53,0)+IF(S25=3,T25*$P$54,0)+IF(S25=4,T25*$P$55,0)+IF(S25=5,T25*$P$56,0)+IF(S25=6,T25*$P$57,0)+IF(S25=7,T25*$P$58,0)+IF(S25=8,T25*$P$59,0)+IF(S25=9,T25*$P$60,0)+IF(S25=10,T25*$P$61,0),0) -> 0 | AZ25: =ROUNDUP(IF(U25=1,V25*$P$52,0)+IF(U25=2,V25*$P$53,0)+IF(U25=3,V25*$P$54,0)+IF(U25=4,V25*$P$55,0)+IF(U25=5,V25*$P$56,0)+IF(U25=6,V25*$P$57,0)+IF(U25=7,V25*$P$58,0)+IF(U25=8,V25*$P$59,0)+IF(U25=9,V25*$P$60,0)+IF(U25=10,V25*$P$61,0),0) -> 0 | BA25: =ROUNDUP(IF(W25=1,X25*$P$52,0)+IF(W25=2,X25*$P$53,0)+IF(W25=3,X25*$P$54,0)+IF(W25=4,X25*$P$55,0)+IF(W25=5,X25*$P$56,0)+IF(W25=6,X25*$P$57,0)+IF(W25=7,X25*$P$58,0)+IF(W25=8,X25*$P$59,0)+IF(W25=9,X25*$P$60,0)+IF(W25=10,X25*$P$61,0),0) -> 0 | BB25: =ROUNDUP(IF(Y25=1,Z25*$P$52,0)+IF(Y25=2,Z25*$P$53,0)+IF(Y25=3,Z25*$P$54,0)+IF(Y25=4,Z25*$P$55,0)+IF(Y25=5,Z25*$P$56,0)+IF(Y25=6,Z25*$P$57,0)+IF(Y25=7,Z25*$P$58,0)+IF(Y25=8,Z25*$P$59,0)+IF(Y25=9,Z25*$P$60,0)+IF(Y25=10,Z25*$P$61,0),0) -> 0 | BC25: =ROUNDUP(IF(AA25=1,AB25*$P$52,0)+IF(AA25=2,AB25*$P$53,0)+IF(AA25=3,AB25*$P$54,0)+IF(AA25=4,AB25*$P$55,0)+IF(AA25=5,AB25*$P$56,0)+IF(AA25=6,AB25*$P$57,0)+IF(AA25=7,AB25*$P$58,0)+IF(AA25=8,AB25*$P$59,0)+IF(AA25=9,AB25*$P$60,0)+IF(AA25=10,AB25*$P$61,0),0) -> 0 | BD25: =SUM(AW25:BC25)*BG25 -> 0 | BE25: =IF(M25=0,0,(M25/12+M25/12)/(M25/12*M25/12)*D25*((L25/16*L25/16)*10.6870159))*(1+K$74)*BG25 -> 0 | BF25: =IF(N25="Y",D25*(1+K$75)*BG25,0) -> 0 | BG25: =G25 -> 0 | BH25: =IF(N25="y",D25,0) -> 0 | BI25: =IF($I25=1,$AD25,0)*BG25 -> 0 | BJ25: =IF($I25=2,$AD25,0)*BG25 -> 0 | BK25: =IF($I25=3,$AD25,0)*BG25 -> 0 | BL25: =IF($I25=4,$AD25,0)*BG25 -> 0 | BM25: =IF($I25=5,$AD25,0)*BG25 -> 0 | BN25: =IF($I25=6,$AD25,0)*BG25 -> 0 | BO25: =SUM(BI25:BN25) -> 0 | BP25: =IF(H25="N",0,D25)*BG25 -> 0 | BQ25: =K25*BG25 -> 0 | BR25: =IF(O25=1,D$52*P25/12,IF(O25=2,D$53*P25/12,IF(O25=3,D$54*P25/12,IF(O25=4,D$55*P25/12,IF(O25=5,D$56*P25/12,IF(O25=6,D$57*P25/12,IF(O25=7,D$58*P25/12,IF(O25=8,D$59*P25/12,IF(O25=9,D$60*P25/12,IF(O25=10,D$61*P25/12,0))))))*BG25)))) -> 0 | BS25: =IF(Q25=1,D$52*R25/12,IF(Q25=2,D$53*R25/12,IF(Q25=3,D$54*R25/12,IF(Q25=4,D$55*R25/12,IF(Q25=5,D$56*R25/12,IF(Q25=6,D$57*R25/12,IF(Q25=7,D$58*R25/12,IF(Q25=8,D$59*R25/12,IF(Q25=9,D$60*R25/12,IF(Q25=10,D$61*R25/12,0))))))*BG25)))) -> 0 | BT25: =D25*BG25 -> 0 | BU25: =D25*J25/324*(1+K$77)*BG25 -> 0 | BV25: =AC25*BG25 -> 0 | BW25: =IF(BG25=0,0,SUM(BX25:CM25)/BG25) -> 0 | BX25: =(BI25*Pricing!F$2+BJ25*Pricing!G$2+BK25*Pricing!H$2+BL25*Pricing!I$2+BM25*Pricing!J$2+BN25*Pricing!K$2)*IF(AC$63="N",(1+AE$63),1) -> 0 | BY25: =AC25*G$74*IF(AC$63="n",1+AE$63,1)*BG25 -> 0 | BZ25: =IF(I$83=0,0,D25*(SUM(L$83:M$86)+L$88)/I$83*BG25) -> 0 | CA25: =IF(I$83=0,0,D25*(SUM(O$83:P$86)+O$88)/I$83*BG25) -> 0 | CB25: =BR25+BS25*E$87 -> 0 | CD25: =BD25/2000*E$89 -> 0 | CE25: =IF(D$49=0,0,SUM(O$92:P$96)/D$49*D25)*BG25 -> 0 | CF25: =IF(D$49=0,0,SUM(AF$72:AF$99)/D$49*D25*BG25) -> 0 | CG25: =IF(D$49=0,0,SUM(O$98:P$103)/D$49*D25)*BG25 -> 0 | CH25: =IF(D$49=0,0,SUM(O$105:O$111)/D$49)*D25*BG25 -> 0 | CI25: =IF(D$49=0,0,SUM(AF$100:AF$111)/D$49*D25*BG25) -> 0 | CJ25: =IF(J$76>0,J$76/D$49*D25*G25,BP25*(G$76*(1+AE$63))) -> 0 | CK25: =IF(L$78=0,0,O$78/L$78)*AW25+IF(L$79=0,0,O$79/L$79)*BC25+IF(L$80=0,0,O$80/L$80)*BC25 -> 0 | CL25: =BF25*G$75*IF(AC$63="Y",1,1+AE$63) -> 0 | CM25: =BU25*G$77*IF(AC$63="Y",1,1+AE$63) -> 0 | CO25: =IF(O25=1,P25*$AM$52,0)+IF(O25=2,P25*$AM$53,0)+IF(O25=3,P25*$AM$54,0)+IF(O25=4,P25*$AM$55,0)+IF(O25=5,P25*$AM$56,0)+IF(O25=6,P25*$AM$57,0)+IF(O25=7,P25*$AM$58,0)+IF(O25=8,P25*$AM$59,0)+IF(O25=9,P25*$AM$60,0)+IF(O25=10,P25*$AM$61,0) -> 0 | CP25: =IF(Q25=1,R25*$AM$52,0)+IF(Q25=2,R25*$AM$53,0)+IF(Q25=3,R25*$AM$54,0)+IF(Q25=4,R25*$AM$55,0)+IF(Q25=5,R25*$AM$56,0)+IF(Q25=6,R25*$AM$57,0)+IF(Q25=7,R25*$AM$58,0)+IF(Q25=8,R25*$AM$59,0)+IF(Q25=9,R25*$AM$60,0)+IF(Q25=10,R25*$AM$61,0) -> 0 | CQ25: =IF(S25=1,T25*$AM$52,0)+IF(S25=2,T25*$AM$53,0)+IF(S25=3,T25*$AM$54,0)+IF(S25=4,T25*$AM$55,0)+IF(S25=5,T25*$AM$56,0)+IF(S25=6,T25*$AM$57,0)+IF(S25=7,T25*$AM$58,0)+IF(S25=8,T25*$AM$59,0)+IF(S25=9,T25*$AM$60,0)+IF(S25=10,T25*$AM$61,0) -> 0 | CR25: =IF(U25=1,V25*$AM$52,0)+IF(U25=2,V25*$AM$53,0)+IF(U25=3,V25*$AM$54,0)+IF(U25=4,V25*$AM$55,0)+IF(U25=5,V25*$AM$56,0)+IF(U25=6,V25*$AM$57,0)+IF(U25=7,V25*$AM$58,0)+IF(U25=8,V25*$AM$59,0)+IF(U25=9,V25*$AM$60,0)+IF(U25=10,V25*$AM$61,0) -> 0 | CS25: =IF(W25=1,X25*$AM$52,0)+IF(W25=2,X25*$AM$53,0)+IF(W25=3,X25*$AM$54,0)+IF(W25=4,X25*$AM$55,0)+IF(W25=5,X25*$AM$56,0)+IF(W25=6,X25*$AM$57,0)+IF(W25=7,X25*$AM$58,0)+IF(W25=8,X25*$AM$59,0)+IF(W25=9,X25*$AM$60,0)+IF(W25=10,X25*$AM$61,0) -> 0 | CT25: =IF(Y25=1,Z25*$AM$52,0)+IF(Y25=2,Z25*$AM$53,0)+IF(Y25=3,Z25*$AM$54,0)+IF(Y25=4,Z25*$AM$55,0)+IF(Y25=5,Z25*$AM$56,0)+IF(Y25=6,Z25*$AM$57,0)+IF(Y25=7,Z25*$AM$58,0)+IF(Y25=8,Z25*$AM$59,0)+IF(Y25=9,Z25*$AM$60,0)+IF(Y25=10,Z25*$AM$61,0) -> 0 | CU25: =IF(AA25=1,AB25*$AM$52,0)+IF(AA25=2,AB25*$AM$53,0)+IF(AA25=3,AB25*$AM$54,0)+IF(AA25=4,AB25*$AM$55,0)+IF(AA25=5,AB25*$AM$56,0)+IF(AA25=6,AB25*$AM$57,0)+IF(AA25=7,AB25*$AM$58,0)+IF(AA25=8,AB25*$AM$59,0)+IF(AA25=9,AB25*$AM$60,0)+IF(AA25=10,AB25*$AM$61,0) -> 0 | CV25: =D25 -> 0 | CW25: =SUM(CO25:CV25)*BG25 -> 0
O26: 9 | Q26: 10 | S26: 1 | T26: =K26 -> 0 | U26: 2 | W26: 3 | Y26: 4 | AA26: 5 | AC26: =IF(BG26=0,0,SUM(BD26:BE26)/BG26) -> 0 | AD26: =(D26*F26/324)*(1+K$71)+AV26 -> 0 | AE26: =IF(D26=0,0,AF26/D26) -> 0 | AF26: =SUM(BW26)*(1+M$64+Summary!P$64) -> 0 | AG26: =D26/AD26 -> #DIV/0! | AH26: =AF26*G26 -> 0 | AO26: =IF(O26=1,P26*$T$52,0)+IF(O26=2,P26*$T$53,0)+IF(O26=3,P26*$T$54,0)+IF(O26=4,P26*$T$55,0)+IF(O26=5,P26*$T$56,0)+IF(O26=6,P26*$T$57,0)+IF(O26=7,P26*$T$58,0)+IF(O26=8,P26*$T$59,0)+IF(O26=9,P26*$T$60,0)+IF(O26=10,P26*$T$61,0) -> 0 | AP26: =IF(Q26=1,R26*$T$52,0)+IF(Q26=2,R26*$T$53,0)+IF(Q26=3,R26*$T$54,0)+IF(Q26=4,R26*$T$55,0)+IF(Q26=5,R26*$T$56,0)+IF(Q26=6,R26*$T$57,0)+IF(Q26=7,R26*$T$58,0)+IF(Q26=8,R26*$T$59,0)+IF(Q26=9,R26*$T$60,0)+IF(Q26=10,R26*$T$61,0) -> 0 | AQ26: =IF(S26=1,T26*$T$52,0)+IF(S26=2,T26*$T$53,0)+IF(S26=3,T26*$T$54,0)+IF(S26=4,T26*$T$55,0)+IF(S26=5,T26*$T$56,0)+IF(S26=6,T26*$T$57,0)+IF(S26=7,T26*$T$58,0)+IF(S26=8,T26*$T$59,0)+IF(S26=9,T26*$T$60,0)+IF(S26=10,T26*$T$61,0) -> 0 | AR26: =IF(U26=1,V26*$T$52,0)+IF(U26=2,V26*$T$53,0)+IF(U26=3,V26*$T$54,0)+IF(U26=4,V26*$T$55,0)+IF(U26=5,V26*$T$56,0)+IF(U26=6,V26*$T$57,0)+IF(U26=7,V26*$T$58,0)+IF(U26=8,V26*$T$59,0)+IF(U26=9,V26*$T$60,0)+IF(U26=10,V26*$T$61,0) -> 0 | AS26: =IF(W26=1,X26*$T$52,0)+IF(W26=2,X26*$T$53,0)+IF(W26=3,X26*$T$54,0)+IF(W26=4,X26*$T$55,0)+IF(W26=5,X26*$T$56,0)+IF(W26=6,X26*$T$57,0)+IF(W26=7,X26*$T$58,0)+IF(W26=8,X26*$T$59,0)+IF(W26=9,X26*$T$60,0)+IF(W26=10,X26*$T$61,0) -> 0 | AT26: =IF(Y26=1,Z26*$T$52,0)+IF(Y26=2,Z26*$T$53,0)+IF(Y26=3,Z26*$T$54,0)+IF(Y26=4,Z26*$T$55,0)+IF(Y26=5,Z26*$T$56,0)+IF(Y26=6,Z26*$T$57,0)+IF(Y26=7,Z26*$T$58,0)+IF(Y26=8,Z26*$T$59,0)+IF(Y26=9,Z26*$T$60,0)+IF(Y26=10,Z26*$T$61,0) -> 0 | AU26: =IF(AA26=1,AB26*$T$52,0)+IF(AA26=2,AB26*$T$53,0)+IF(AA26=3,AB26*$T$54,0)+IF(AA26=4,AB26*$T$55,0)+IF(AA26=5,AB26*$T$56,0)+IF(AA26=6,AB26*$T$57,0)+IF(AA26=7,AB26*$T$58,0)+IF(AA26=8,AB26*$T$59,0)+IF(AA26=9,AB26*$T$60,0)+IF(AA26=10,AB26*$T$61,0) -> 0 | AV26: =SUM(AO26:AU26) -> 0 | AW26: =ROUNDUP(IF(O26=1,P26*$P$52,0)+IF(O26=2,P26*$P$53,0)+IF(O26=3,P26*$P$54,0)+IF(O26=4,P26*$P$55,0)+IF(O26=5,P26*$P$56,0)+IF(O26=6,P26*$P$57,0)+IF(O26=7,P26*$P$58,0)+IF(O26=8,P26*$P$59,0)+IF(O26=9,P26*$P$60,0)+IF(O26=10,P26*$P$61,0),0)*BG26 -> 0 | AX26: =ROUNDUP(IF(Q26=1,R26*$P$52,0)+IF(Q26=2,R26*$P$53,0)+IF(Q26=3,R26*$P$54,0)+IF(Q26=4,R26*$P$55,0)+IF(Q26=5,R26*$P$56,0)+IF(Q26=6,R26*$P$57,0)+IF(Q26=7,R26*$P$58,0)+IF(Q26=8,R26*$P$59,0)+IF(Q26=9,R26*$P$60,0)+IF(Q26=10,R26*$P$61,0),0) -> 0 | AY26: =ROUNDUP(IF(S26=1,T26*$P$52,0)+IF(S26=2,T26*$P$53,0)+IF(S26=3,T26*$P$54,0)+IF(S26=4,T26*$P$55,0)+IF(S26=5,T26*$P$56,0)+IF(S26=6,T26*$P$57,0)+IF(S26=7,T26*$P$58,0)+IF(S26=8,T26*$P$59,0)+IF(S26=9,T26*$P$60,0)+IF(S26=10,T26*$P$61,0),0) -> 0 | AZ26: =ROUNDUP(IF(U26=1,V26*$P$52,0)+IF(U26=2,V26*$P$53,0)+IF(U26=3,V26*$P$54,0)+IF(U26=4,V26*$P$55,0)+IF(U26=5,V26*$P$56,0)+IF(U26=6,V26*$P$57,0)+IF(U26=7,V26*$P$58,0)+IF(U26=8,V26*$P$59,0)+IF(U26=9,V26*$P$60,0)+IF(U26=10,V26*$P$61,0),0) -> 0 | BA26: =ROUNDUP(IF(W26=1,X26*$P$52,0)+IF(W26=2,X26*$P$53,0)+IF(W26=3,X26*$P$54,0)+IF(W26=4,X26*$P$55,0)+IF(W26=5,X26*$P$56,0)+IF(W26=6,X26*$P$57,0)+IF(W26=7,X26*$P$58,0)+IF(W26=8,X26*$P$59,0)+IF(W26=9,X26*$P$60,0)+IF(W26=10,X26*$P$61,0),0) -> 0 | BB26: =ROUNDUP(IF(Y26=1,Z26*$P$52,0)+IF(Y26=2,Z26*$P$53,0)+IF(Y26=3,Z26*$P$54,0)+IF(Y26=4,Z26*$P$55,0)+IF(Y26=5,Z26*$P$56,0)+IF(Y26=6,Z26*$P$57,0)+IF(Y26=7,Z26*$P$58,0)+IF(Y26=8,Z26*$P$59,0)+IF(Y26=9,Z26*$P$60,0)+IF(Y26=10,Z26*$P$61,0),0) -> 0 | BC26: =ROUNDUP(IF(AA26=1,AB26*$P$52,0)+IF(AA26=2,AB26*$P$53,0)+IF(AA26=3,AB26*$P$54,0)+IF(AA26=4,AB26*$P$55,0)+IF(AA26=5,AB26*$P$56,0)+IF(AA26=6,AB26*$P$57,0)+IF(AA26=7,AB26*$P$58,0)+IF(AA26=8,AB26*$P$59,0)+IF(AA26=9,AB26*$P$60,0)+IF(AA26=10,AB26*$P$61,0),0) -> 0 | BD26: =SUM(AW26:BC26)*BG26 -> 0 | BE26: =IF(M26=0,0,(M26/12+M26/12)/(M26/12*M26/12)*D26*((L26/16*L26/16)*10.6870159))*(1+K$74)*BG26 -> 0 | BF26: =IF(N26="Y",D26*(1+K$75)*BG26,0) -> 0 | BG26: =G26 -> 0 | BH26: =IF(N26="y",D26,0) -> 0 | BI26: =IF($I26=1,$AD26,0)*BG26 -> 0 | BJ26: =IF($I26=2,$AD26,0)*BG26 -> 0 | BK26: =IF($I26=3,$AD26,0)*BG26 -> 0 | BL26: =IF($I26=4,$AD26,0)*BG26 -> 0 | BM26: =IF($I26=5,$AD26,0)*BG26 -> 0 | BN26: =IF($I26=6,$AD26,0)*BG26 -> 0 | BO26: =SUM(BI26:BN26) -> 0 | BP26: =IF(H26="N",0,D26)*BG26 -> 0 | BQ26: =K26*BG26 -> 0 | BR26: =IF(O26=1,D$52*P26/12,IF(O26=2,D$53*P26/12,IF(O26=3,D$54*P26/12,IF(O26=4,D$55*P26/12,IF(O26=5,D$56*P26/12,IF(O26=6,D$57*P26/12,IF(O26=7,D$58*P26/12,IF(O26=8,D$59*P26/12,IF(O26=9,D$60*P26/12,IF(O26=10,D$61*P26/12,0))))))*BG26)))) -> 0 | BS26: =IF(Q26=1,D$52*R26/12,IF(Q26=2,D$53*R26/12,IF(Q26=3,D$54*R26/12,IF(Q26=4,D$55*R26/12,IF(Q26=5,D$56*R26/12,IF(Q26=6,D$57*R26/12,IF(Q26=7,D$58*R26/12,IF(Q26=8,D$59*R26/12,IF(Q26=9,D$60*R26/12,IF(Q26=10,D$61*R26/12,0))))))*BG26)))) -> 0 | BT26: =D26*BG26 -> 0 | BU26: =D26*J26/324*(1+K$77)*BG26 -> 0 | BV26: =AC26*BG26 -> 0 | BW26: =IF(BG26=0,0,SUM(BX26:CM26)/BG26) -> 0 | BX26: =(BI26*Pricing!F$2+BJ26*Pricing!G$2+BK26*Pricing!H$2+BL26*Pricing!I$2+BM26*Pricing!J$2+BN26*Pricing!K$2)*IF(AC$63="N",(1+AE$63),1) -> 0 | BY26: =AC26*G$74*IF(AC$63="n",1+AE$63,1)*BG26 -> 0 | BZ26: =IF(I$83=0,0,D26*(SUM(L$83:M$86)+L$88)/I$83*BG26) -> 0 | CA26: =IF(I$83=0,0,D26*(SUM(O$83:P$86)+O$88)/I$83*BG26) -> 0 | CB26: =BR26+BS26*E$87 -> 0 | CD26: =BD26/2000*E$89 -> 0 | CE26: =IF(D$49=0,0,SUM(O$92:P$96)/D$49*D26)*BG26 -> 0 | CF26: =IF(D$49=0,0,SUM(AF$72:AF$99)/D$49*D26*BG26) -> 0 | CG26: =IF(D$49=0,0,SUM(O$98:P$103)/D$49*D26)*BG26 -> 0 | CH26: =IF(D$49=0,0,SUM(O$105:O$111)/D$49)*D26*BG26 -> 0 | CI26: =IF(D$49=0,0,SUM(AF$100:AF$111)/D$49*D26*BG26) -> 0 | CJ26: =IF(J$76>0,J$76/D$49*D26*G26,BP26*(G$76*(1+AE$63))) -> 0 | CK26: =IF(L$78=0,0,O$78/L$78)*AW26+IF(L$79=0,0,O$79/L$79)*BC26+IF(L$80=0,0,O$80/L$80)*BC26 -> 0 | CL26: =BF26*G$75*IF(AC$63="Y",1,1+AE$63) -> 0 | CM26: =BU26*G$77*IF(AC$63="Y",1,1+AE$63) -> 0 | CO26: =IF(O26=1,P26*$AM$52,0)+IF(O26=2,P26*$AM$53,0)+IF(O26=3,P26*$AM$54,0)+IF(O26=4,P26*$AM$55,0)+IF(O26=5,P26*$AM$56,0)+IF(O26=6,P26*$AM$57,0)+IF(O26=7,P26*$AM$58,0)+IF(O26=8,P26*$AM$59,0)+IF(O26=9,P26*$AM$60,0)+IF(O26=10,P26*$AM$61,0) -> 0 | CP26: =IF(Q26=1,R26*$AM$52,0)+IF(Q26=2,R26*$AM$53,0)+IF(Q26=3,R26*$AM$54,0)+IF(Q26=4,R26*$AM$55,0)+IF(Q26=5,R26*$AM$56,0)+IF(Q26=6,R26*$AM$57,0)+IF(Q26=7,R26*$AM$58,0)+IF(Q26=8,R26*$AM$59,0)+IF(Q26=9,R26*$AM$60,0)+IF(Q26=10,R26*$AM$61,0) -> 0 | CQ26: =IF(S26=1,T26*$AM$52,0)+IF(S26=2,T26*$AM$53,0)+IF(S26=3,T26*$AM$54,0)+IF(S26=4,T26*$AM$55,0)+IF(S26=5,T26*$AM$56,0)+IF(S26=6,T26*$AM$57,0)+IF(S26=7,T26*$AM$58,0)+IF(S26=8,T26*$AM$59,0)+IF(S26=9,T26*$AM$60,0)+IF(S26=10,T26*$AM$61,0) -> 0 | CR26: =IF(U26=1,V26*$AM$52,0)+IF(U26=2,V26*$AM$53,0)+IF(U26=3,V26*$AM$54,0)+IF(U26=4,V26*$AM$55,0)+IF(U26=5,V26*$AM$56,0)+IF(U26=6,V26*$AM$57,0)+IF(U26=7,V26*$AM$58,0)+IF(U26=8,V26*$AM$59,0)+IF(U26=9,V26*$AM$60,0)+IF(U26=10,V26*$AM$61,0) -> 0 | CS26: =IF(W26=1,X26*$AM$52,0)+IF(W26=2,X26*$AM$53,0)+IF(W26=3,X26*$AM$54,0)+IF(W26=4,X26*$AM$55,0)+IF(W26=5,X26*$AM$56,0)+IF(W26=6,X26*$AM$57,0)+IF(W26=7,X26*$AM$58,0)+IF(W26=8,X26*$AM$59,0)+IF(W26=9,X26*$AM$60,0)+IF(W26=10,X26*$AM$61,0) -> 0 | CT26: =IF(Y26=1,Z26*$AM$52,0)+IF(Y26=2,Z26*$AM$53,0)+IF(Y26=3,Z26*$AM$54,0)+IF(Y26=4,Z26*$AM$55,0)+IF(Y26=5,Z26*$AM$56,0)+IF(Y26=6,Z26*$AM$57,0)+IF(Y26=7,Z26*$AM$58,0)+IF(Y26=8,Z26*$AM$59,0)+IF(Y26=9,Z26*$AM$60,0)+IF(Y26=10,Z26*$AM$61,0) -> 0 | CU26: =IF(AA26=1,AB26*$AM$52,0)+IF(AA26=2,AB26*$AM$53,0)+IF(AA26=3,AB26*$AM$54,0)+IF(AA26=4,AB26*$AM$55,0)+IF(AA26=5,AB26*$AM$56,0)+IF(AA26=6,AB26*$AM$57,0)+IF(AA26=7,AB26*$AM$58,0)+IF(AA26=8,AB26*$AM$59,0)+IF(AA26=9,AB26*$AM$60,0)+IF(AA26=10,AB26*$AM$61,0) -> 0 | CV26: =D26 -> 0 | CW26: =SUM(CO26:CV26)*BG26 -> 0
S27: 1 | T27: =K27 -> 0 | U27: 2 | AC27: =IF(BG27=0,0,SUM(BD27:BE27)/BG27) -> 0 | AD27: =(D27*F27/324)*(1+K$71)+AV27 -> 0 | AE27: =IF(D27=0,0,AF27/D27) -> 0 | AF27: =SUM(BW27)*(1+M$64+Summary!P$64) -> 0 | AG27: =D27/AD27 -> #DIV/0! | AH27: =AF27*G27 -> 0 | AO27: =IF(O27=1,P27*$T$52,0)+IF(O27=2,P27*$T$53,0)+IF(O27=3,P27*$T$54,0)+IF(O27=4,P27*$T$55,0)+IF(O27=5,P27*$T$56,0)+IF(O27=6,P27*$T$57,0)+IF(O27=7,P27*$T$58,0)+IF(O27=8,P27*$T$59,0)+IF(O27=9,P27*$T$60,0)+IF(O27=10,P27*$T$61,0) -> 0 | AP27: =IF(Q27=1,R27*$T$52,0)+IF(Q27=2,R27*$T$53,0)+IF(Q27=3,R27*$T$54,0)+IF(Q27=4,R27*$T$55,0)+IF(Q27=5,R27*$T$56,0)+IF(Q27=6,R27*$T$57,0)+IF(Q27=7,R27*$T$58,0)+IF(Q27=8,R27*$T$59,0)+IF(Q27=9,R27*$T$60,0)+IF(Q27=10,R27*$T$61,0) -> 0 | AQ27: =IF(S27=1,T27*$T$52,0)+IF(S27=2,T27*$T$53,0)+IF(S27=3,T27*$T$54,0)+IF(S27=4,T27*$T$55,0)+IF(S27=5,T27*$T$56,0)+IF(S27=6,T27*$T$57,0)+IF(S27=7,T27*$T$58,0)+IF(S27=8,T27*$T$59,0)+IF(S27=9,T27*$T$60,0)+IF(S27=10,T27*$T$61,0) -> 0 | AR27: =IF(U27=1,V27*$T$52,0)+IF(U27=2,V27*$T$53,0)+IF(U27=3,V27*$T$54,0)+IF(U27=4,V27*$T$55,0)+IF(U27=5,V27*$T$56,0)+IF(U27=6,V27*$T$57,0)+IF(U27=7,V27*$T$58,0)+IF(U27=8,V27*$T$59,0)+IF(U27=9,V27*$T$60,0)+IF(U27=10,V27*$T$61,0) -> 0 | AS27: =IF(W27=1,X27*$T$52,0)+IF(W27=2,X27*$T$53,0)+IF(W27=3,X27*$T$54,0)+IF(W27=4,X27*$T$55,0)+IF(W27=5,X27*$T$56,0)+IF(W27=6,X27*$T$57,0)+IF(W27=7,X27*$T$58,0)+IF(W27=8,X27*$T$59,0)+IF(W27=9,X27*$T$60,0)+IF(W27=10,X27*$T$61,0) -> 0 | AT27: =IF(Y27=1,Z27*$T$52,0)+IF(Y27=2,Z27*$T$53,0)+IF(Y27=3,Z27*$T$54,0)+IF(Y27=4,Z27*$T$55,0)+IF(Y27=5,Z27*$T$56,0)+IF(Y27=6,Z27*$T$57,0)+IF(Y27=7,Z27*$T$58,0)+IF(Y27=8,Z27*$T$59,0)+IF(Y27=9,Z27*$T$60,0)+IF(Y27=10,Z27*$T$61,0) -> 0 | AU27: =IF(AA27=1,AB27*$T$52,0)+IF(AA27=2,AB27*$T$53,0)+IF(AA27=3,AB27*$T$54,0)+IF(AA27=4,AB27*$T$55,0)+IF(AA27=5,AB27*$T$56,0)+IF(AA27=6,AB27*$T$57,0)+IF(AA27=7,AB27*$T$58,0)+IF(AA27=8,AB27*$T$59,0)+IF(AA27=9,AB27*$T$60,0)+IF(AA27=10,AB27*$T$61,0) -> 0 | AV27: =SUM(AO27:AU27) -> 0 | AW27: =ROUNDUP(IF(O27=1,P27*$P$52,0)+IF(O27=2,P27*$P$53,0)+IF(O27=3,P27*$P$54,0)+IF(O27=4,P27*$P$55,0)+IF(O27=5,P27*$P$56,0)+IF(O27=6,P27*$P$57,0)+IF(O27=7,P27*$P$58,0)+IF(O27=8,P27*$P$59,0)+IF(O27=9,P27*$P$60,0)+IF(O27=10,P27*$P$61,0),0)*BG27 -> 0 | AX27: =ROUNDUP(IF(Q27=1,R27*$P$52,0)+IF(Q27=2,R27*$P$53,0)+IF(Q27=3,R27*$P$54,0)+IF(Q27=4,R27*$P$55,0)+IF(Q27=5,R27*$P$56,0)+IF(Q27=6,R27*$P$57,0)+IF(Q27=7,R27*$P$58,0)+IF(Q27=8,R27*$P$59,0)+IF(Q27=9,R27*$P$60,0)+IF(Q27=10,R27*$P$61,0),0) -> 0 | AY27: =ROUNDUP(IF(S27=1,T27*$P$52,0)+IF(S27=2,T27*$P$53,0)+IF(S27=3,T27*$P$54,0)+IF(S27=4,T27*$P$55,0)+IF(S27=5,T27*$P$56,0)+IF(S27=6,T27*$P$57,0)+IF(S27=7,T27*$P$58,0)+IF(S27=8,T27*$P$59,0)+IF(S27=9,T27*$P$60,0)+IF(S27=10,T27*$P$61,0),0) -> 0 | AZ27: =ROUNDUP(IF(U27=1,V27*$P$52,0)+IF(U27=2,V27*$P$53,0)+IF(U27=3,V27*$P$54,0)+IF(U27=4,V27*$P$55,0)+IF(U27=5,V27*$P$56,0)+IF(U27=6,V27*$P$57,0)+IF(U27=7,V27*$P$58,0)+IF(U27=8,V27*$P$59,0)+IF(U27=9,V27*$P$60,0)+IF(U27=10,V27*$P$61,0),0) -> 0 | BA27: =ROUNDUP(IF(W27=1,X27*$P$52,0)+IF(W27=2,X27*$P$53,0)+IF(W27=3,X27*$P$54,0)+IF(W27=4,X27*$P$55,0)+IF(W27=5,X27*$P$56,0)+IF(W27=6,X27*$P$57,0)+IF(W27=7,X27*$P$58,0)+IF(W27=8,X27*$P$59,0)+IF(W27=9,X27*$P$60,0)+IF(W27=10,X27*$P$61,0),0) -> 0 | BB27: =ROUNDUP(IF(Y27=1,Z27*$P$52,0)+IF(Y27=2,Z27*$P$53,0)+IF(Y27=3,Z27*$P$54,0)+IF(Y27=4,Z27*$P$55,0)+IF(Y27=5,Z27*$P$56,0)+IF(Y27=6,Z27*$P$57,0)+IF(Y27=7,Z27*$P$58,0)+IF(Y27=8,Z27*$P$59,0)+IF(Y27=9,Z27*$P$60,0)+IF(Y27=10,Z27*$P$61,0),0) -> 0 | BC27: =ROUNDUP(IF(AA27=1,AB27*$P$52,0)+IF(AA27=2,AB27*$P$53,0)+IF(AA27=3,AB27*$P$54,0)+IF(AA27=4,AB27*$P$55,0)+IF(AA27=5,AB27*$P$56,0)+IF(AA27=6,AB27*$P$57,0)+IF(AA27=7,AB27*$P$58,0)+IF(AA27=8,AB27*$P$59,0)+IF(AA27=9,AB27*$P$60,0)+IF(AA27=10,AB27*$P$61,0),0) -> 0 | BD27: =SUM(AW27:BC27)*BG27 -> 0 | BE27: =IF(M27=0,0,(M27/12+M27/12)/(M27/12*M27/12)*D27*((L27/16*L27/16)*10.6870159))*(1+K$74)*BG27 -> 0 | BF27: =IF(N27="Y",D27*(1+K$75)*BG27,0) -> 0 | BG27: =G27 -> 0 | BH27: =IF(N27="y",D27,0) -> 0 | BI27: =IF($I27=1,$AD27,0)*BG27 -> 0 | BJ27: =IF($I27=2,$AD27,0)*BG27 -> 0 | BK27: =IF($I27=3,$AD27,0)*BG27 -> 0 | BL27: =IF($I27=4,$AD27,0)*BG27 -> 0 | BM27: =IF($I27=5,$AD27,0)*BG27 -> 0 | BN27: =IF($I27=6,$AD27,0)*BG27 -> 0 | BO27: =SUM(BI27:BN27) -> 0 | BP27: =IF(H27="N",0,D27)*BG27 -> 0 | BQ27: =K27*BG27 -> 0 | BR27: =IF(O27=1,D$52*P27/12,IF(O27=2,D$53*P27/12,IF(O27=3,D$54*P27/12,IF(O27=4,D$55*P27/12,IF(O27=5,D$56*P27/12,IF(O27=6,D$57*P27/12,IF(O27=7,D$58*P27/12,IF(O27=8,D$59*P27/12,IF(O27=9,D$60*P27/12,IF(O27=10,D$61*P27/12,0))))))*BG27)))) -> 0 | BS27: =IF(Q27=1,D$52*R27/12,IF(Q27=2,D$53*R27/12,IF(Q27=3,D$54*R27/12,IF(Q27=4,D$55*R27/12,IF(Q27=5,D$56*R27/12,IF(Q27=6,D$57*R27/12,IF(Q27=7,D$58*R27/12,IF(Q27=8,D$59*R27/12,IF(Q27=9,D$60*R27/12,IF(Q27=10,D$61*R27/12,0))))))*BG27)))) -> 0 | BT27: =D27*BG27 -> 0 | BU27: =D27*J27/324*(1+K$77)*BG27 -> 0 | BV27: =AC27*BG27 -> 0 | BW27: =IF(BG27=0,0,SUM(BX27:CM27)/BG27) -> 0 | BX27: =(BI27*Pricing!F$2+BJ27*Pricing!G$2+BK27*Pricing!H$2+BL27*Pricing!I$2+BM27*Pricing!J$2+BN27*Pricing!K$2)*IF(AC$63="N",(1+AE$63),1) -> 0 | BY27: =AC27*G$74*IF(AC$63="n",1+AE$63,1)*BG27 -> 0 | BZ27: =IF(I$83=0,0,D27*(SUM(L$83:M$86)+L$88)/I$83*BG27) -> 0 | CA27: =IF(I$83=0,0,D27*(SUM(O$83:P$86)+O$88)/I$83*BG27) -> 0 | CB27: =BR27+BS27*E$87 -> 0 | CD27: =BD27/2000*E$89 -> 0 | CE27: =IF(D$49=0,0,SUM(O$92:P$96)/D$49*D27)*BG27 -> 0 | CF27: =IF(D$49=0,0,SUM(AF$72:AF$99)/D$49*D27*BG27) -> 0 | CG27: =IF(D$49=0,0,SUM(O$98:P$103)/D$49*D27)*BG27 -> 0 | CH27: =IF(D$49=0,0,SUM(O$105:O$111)/D$49)*D27*BG27 -> 0 | CI27: =IF(D$49=0,0,SUM(AF$100:AF$111)/D$49*D27*BG27) -> 0 | CJ27: =IF(J$76>0,J$76/D$49*D27*G27,BP27*(G$76*(1+AE$63))) -> 0 | CK27: =IF(L$78=0,0,O$78/L$78)*AW27+IF(L$79=0,0,O$79/L$79)*BC27+IF(L$80=0,0,O$80/L$80)*BC27 -> 0 | CL27: =BF27*G$75*IF(AC$63="Y",1,1+AE$63) -> 0 | CM27: =BU27*G$77*IF(AC$63="Y",1,1+AE$63) -> 0 | CO27: =IF(O27=1,P27*$AM$52,0)+IF(O27=2,P27*$AM$53,0)+IF(O27=3,P27*$AM$54,0)+IF(O27=4,P27*$AM$55,0)+IF(O27=5,P27*$AM$56,0)+IF(O27=6,P27*$AM$57,0)+IF(O27=7,P27*$AM$58,0)+IF(O27=8,P27*$AM$59,0)+IF(O27=9,P27*$AM$60,0)+IF(O27=10,P27*$AM$61,0) -> 0 | CP27: =IF(Q27=1,R27*$AM$52,0)+IF(Q27=2,R27*$AM$53,0)+IF(Q27=3,R27*$AM$54,0)+IF(Q27=4,R27*$AM$55,0)+IF(Q27=5,R27*$AM$56,0)+IF(Q27=6,R27*$AM$57,0)+IF(Q27=7,R27*$AM$58,0)+IF(Q27=8,R27*$AM$59,0)+IF(Q27=9,R27*$AM$60,0)+IF(Q27=10,R27*$AM$61,0) -> 0 | CQ27: =IF(S27=1,T27*$AM$52,0)+IF(S27=2,T27*$AM$53,0)+IF(S27=3,T27*$AM$54,0)+IF(S27=4,T27*$AM$55,0)+IF(S27=5,T27*$AM$56,0)+IF(S27=6,T27*$AM$57,0)+IF(S27=7,T27*$AM$58,0)+IF(S27=8,T27*$AM$59,0)+IF(S27=9,T27*$AM$60,0)+IF(S27=10,T27*$AM$61,0) -> 0 | CR27: =IF(U27=1,V27*$AM$52,0)+IF(U27=2,V27*$AM$53,0)+IF(U27=3,V27*$AM$54,0)+IF(U27=4,V27*$AM$55,0)+IF(U27=5,V27*$AM$56,0)+IF(U27=6,V27*$AM$57,0)+IF(U27=7,V27*$AM$58,0)+IF(U27=8,V27*$AM$59,0)+IF(U27=9,V27*$AM$60,0)+IF(U27=10,V27*$AM$61,0) -> 0 | CS27: =IF(W27=1,X27*$AM$52,0)+IF(W27=2,X27*$AM$53,0)+IF(W27=3,X27*$AM$54,0)+IF(W27=4,X27*$AM$55,0)+IF(W27=5,X27*$AM$56,0)+IF(W27=6,X27*$AM$57,0)+IF(W27=7,X27*$AM$58,0)+IF(W27=8,X27*$AM$59,0)+IF(W27=9,X27*$AM$60,0)+IF(W27=10,X27*$AM$61,0) -> 0 | CT27: =IF(Y27=1,Z27*$AM$52,0)+IF(Y27=2,Z27*$AM$53,0)+IF(Y27=3,Z27*$AM$54,0)+IF(Y27=4,Z27*$AM$55,0)+IF(Y27=5,Z27*$AM$56,0)+IF(Y27=6,Z27*$AM$57,0)+IF(Y27=7,Z27*$AM$58,0)+IF(Y27=8,Z27*$AM$59,0)+IF(Y27=9,Z27*$AM$60,0)+IF(Y27=10,Z27*$AM$61,0) -> 0 | CU27: =IF(AA27=1,AB27*$AM$52,0)+IF(AA27=2,AB27*$AM$53,0)+IF(AA27=3,AB27*$AM$54,0)+IF(AA27=4,AB27*$AM$55,0)+IF(AA27=5,AB27*$AM$56,0)+IF(AA27=6,AB27*$AM$57,0)+IF(AA27=7,AB27*$AM$58,0)+IF(AA27=8,AB27*$AM$59,0)+IF(AA27=9,AB27*$AM$60,0)+IF(AA27=10,AB27*$AM$61,0) -> 0 | CV27: =D27 -> 0 | CW27: =SUM(CO27:CV27)*BG27 -> 0
